Classfile /home/yappy/MasaoMakerSP/scripts/dis/mc2/IdouGamen.class
  Last modified Jun 30, 2003; size 15486 bytes
  SHA-256 checksum ecffbeb0bb0f345fba2589778d0a660134f8d6807a7fe9b869302353e4950dbf
  Compiled from "MasaoConstruction.java"
class IdouGamen
  minor version: 3
  major version: 45
  flags: (0x0020) ACC_SUPER
  this_class: #131                        // IdouGamen
  super_class: #132                       // java/lang/Object
  interfaces: 0, fields: 28, methods: 12, attributes: 1
Constant pool:
    #1 = Methodref          #132.#196     // java/lang/Object."<init>":()V
    #2 = Class              #197          // CharacterObject
    #3 = Methodref          #2.#196       // CharacterObject."<init>":()V
    #4 = Fieldref           #131.#198     // IdouGamen.co_j:LCharacterObject;
    #5 = Class              #199          // java/lang/String
    #6 = Fieldref           #131.#200     // IdouGamen.map_string:[Ljava/lang/String;
    #7 = Class              #146          // "[[I"
    #8 = Fieldref           #131.#201     // IdouGamen.map_bg:[[I
    #9 = Fieldref           #131.#202     // IdouGamen.stage_c:[I
   #10 = Fieldref           #131.#203     // IdouGamen.stage_x:[I
   #11 = Fieldref           #131.#204     // IdouGamen.stage_y:[I
   #12 = Fieldref           #131.#205     // IdouGamen.stage_cf:[Z
   #13 = Fieldref           #131.#206     // IdouGamen.ie_c:[I
   #14 = Fieldref           #131.#207     // IdouGamen.ie_x:[I
   #15 = Fieldref           #131.#208     // IdouGamen.ie_y:[I
   #16 = Fieldref           #131.#209     // IdouGamen.zure_x:I
   #17 = Fieldref           #131.#210     // IdouGamen.zure_y:I
   #18 = Fieldref           #131.#211     // IdouGamen.mp_mode:I
   #19 = Fieldref           #131.#212     // IdouGamen.cc_p1_x:[I
   #20 = Fieldref           #131.#213     // IdouGamen.cc_p1_y:[I
   #21 = Fieldref           #131.#214     // IdouGamen.cc_p2_x:[I
   #22 = Fieldref           #131.#215     // IdouGamen.cc_p2_y:[I
   #23 = Fieldref           #131.#216     // IdouGamen.gg:LGameGraphics;
   #24 = Fieldref           #131.#217     // IdouGamen.gk:LGameKey;
   #25 = Fieldref           #131.#218     // IdouGamen.km:LKeyboardMenu;
   #26 = Fieldref           #131.#219     // IdouGamen.mp:LMainProgram;
   #27 = Fieldref           #131.#220     // IdouGamen.stage_kcID:I
   #28 = Fieldref           #131.#221     // IdouGamen.door_koID:I
   #29 = Fieldref           #131.#222     // IdouGamen.dokan_khID:I
   #30 = Fieldref           #131.#223     // IdouGamen.door_score_open:I
   #31 = Fieldref           #2.#224       // CharacterObject.x:I
   #32 = Fieldref           #2.#225       // CharacterObject.y:I
   #33 = Fieldref           #2.#226       // CharacterObject.vx:I
   #34 = Fieldref           #2.#227       // CharacterObject.vy:I
   #35 = Fieldref           #2.#228       // CharacterObject.muki:I
   #36 = Fieldref           #2.#229       // CharacterObject.ac:I
   #37 = Fieldref           #230.#231     // MainProgram.tr1_c:I
   #38 = Fieldref           #131.#232     // IdouGamen.shop_kattaitem:I
   #39 = Methodref          #233.#234     // KeyboardMenu.initAll:()V
   #40 = Fieldref           #233.#235     // KeyboardMenu.mode:I
   #41 = Fieldref           #236.#237     // GameGraphics.ap:Ljava/applet/Applet;
   #42 = Class              #238          // java/lang/StringBuffer
   #43 = Methodref          #42.#196      // java/lang/StringBuffer."<init>":()V
   #44 = String             #239          // chizu-
   #45 = Methodref          #42.#240      // java/lang/StringBuffer.append:(Ljava/lang/String;)Ljava/lang/StringBuffer;
   #46 = Methodref          #42.#241      // java/lang/StringBuffer.append:(I)Ljava/lang/StringBuffer;
   #47 = Methodref          #42.#242      // java/lang/StringBuffer.toString:()Ljava/lang/String;
   #48 = Methodref          #243.#244     // java/applet/Applet.getParameter:(Ljava/lang/String;)Ljava/lang/String;
   #49 = String             #245          // ...............
   #50 = Methodref          #5.#246       // java/lang/String.charAt:(I)C
   #51 = Methodref          #131.#247     // IdouGamen.drawOs2:()V
   #52 = Fieldref           #131.#248     // IdouGamen.cc_hankei:I
   #53 = Fieldref           #230.#249     // MainProgram.score:I
   #54 = Fieldref           #230.#250     // MainProgram.door_score:I
   #55 = Methodref          #131.#251     // IdouGamen.checkStage:()I
   #56 = Fieldref           #2.#252       // CharacterObject.pt:I
   #57 = Class              #253          // java/awt/Color
   #58 = Methodref          #57.#254      // java/awt/Color."<init>":(III)V
   #59 = Methodref          #236.#255     // GameGraphics.setBackcolor:(Ljava/awt/Color;)V
   #60 = Methodref          #236.#256     // GameGraphics.fill2:()V
   #61 = Fieldref           #236.#257     // GameGraphics.os2_g:Ljava/awt/Graphics;
   #62 = Fieldref           #236.#258     // GameGraphics.li:[Ljava/awt/Image;
   #63 = Methodref          #259.#260     // java/awt/Graphics.drawImage:(Ljava/awt/Image;IILjava/awt/image/ImageObserver;)Z
   #64 = Methodref          #236.#261     // GameGraphics.drawPT2:(III)V
   #65 = Fieldref           #236.#262     // GameGraphics.os_g:Ljava/awt/Graphics;
   #66 = Fieldref           #236.#263     // GameGraphics.os2_img:Ljava/awt/Image;
   #67 = Fieldref           #264.#265     // GameKey.tr1_f:Z
   #68 = Methodref          #131.#266     // IdouGamen.jMove:()V
   #69 = Fieldref           #233.#267     // KeyboardMenu.cancel_c:I
   #70 = Methodref          #233.#268     // KeyboardMenu.off:(I)V
   #71 = Fieldref           #233.#269     // KeyboardMenu.kettei_c:I
   #72 = Methodref          #233.#270     // KeyboardMenu.init1:(I)V
   #73 = Fieldref           #230.#271     // MainProgram.mes1_name:Ljava/lang/String;
   #74 = Methodref          #233.#272     // KeyboardMenu.setMessage:(ILjava/lang/String;)V
   #75 = Methodref          #230.#273     // MainProgram.addSerifu:(III)V
   #76 = Fieldref           #57.#274      // java/awt/Color.cyan:Ljava/awt/Color;
   #77 = Methodref          #233.#275     // KeyboardMenu.activeSerifu:(IIIILjava/awt/Color;)V
   #78 = Fieldref           #230.#276     // MainProgram.mes2_name:Ljava/lang/String;
   #79 = Fieldref           #233.#277     // KeyboardMenu.list_kazu:I
   #80 = String             #278          // shop_serifu1
   #81 = Fieldref           #230.#279     // MainProgram.shop_item_teika:[I
   #82 = Fieldref           #230.#280     // MainProgram.shop_item_name:[Ljava/lang/String;
   #83 = Methodref          #233.#281     // KeyboardMenu.addItem2:(ILjava/lang/String;I)V
   #84 = Fieldref           #233.#282     // KeyboardMenu.list_IDlist:[I
   #85 = Methodref          #233.#283     // KeyboardMenu.activeKaimono:(IIII)V
   #86 = String             #284          // Error
   #87 = String             #285          // Please set any item on shop menu.
   #88 = Methodref          #233.#286     // KeyboardMenu.addItem:(ILjava/lang/String;)V
   #89 = Fieldref           #57.#287      // java/awt/Color.red:Ljava/awt/Color;
   #90 = Fieldref           #233.#288     // KeyboardMenu.selectedIndex:[I
   #91 = Fieldref           #233.#289     // KeyboardMenu.list_s:I
   #92 = String             #290          // shop_serifu2
   #93 = String             #291          // shop_serifu3
   #94 = String             #292          // shop_serifu4
   #95 = Fieldref           #230.#293     // MainProgram.shop_name:Ljava/lang/String;
   #96 = Methodref          #233.#294     // KeyboardMenu.activeSerifutuki:(IIIILjava/lang/String;)V
   #97 = Methodref          #233.#295     // KeyboardMenu.offActivewindow:(II)V
   #98 = String             #296          // shop_serifu5
   #99 = Methodref          #233.#297     // KeyboardMenu.activeIchigyou:(IIII)V
  #100 = Fieldref           #230.#298     // MainProgram.j_left:I
  #101 = String             #299          // shop_serifu6
  #102 = String             #300          // setumei_menu1
  #103 = String             #301          // setumei_menu2
  #104 = String             #302          // setumei_menu3
  #105 = String             #303          // setumei_menu4
  #106 = Fieldref           #230.#304     // MainProgram.setumei_name:Ljava/lang/String;
  #107 = Methodref          #233.#305     // KeyboardMenu.move:()V
  #108 = Methodref          #236.#306     // GameGraphics.drawPT:(IIII)V
  #109 = Methodref          #233.#307     // KeyboardMenu.drawMenus:()V
  #110 = Methodref          #131.#308     // IdouGamen.circleCLS:(I)V
  #111 = Methodref          #131.#309     // IdouGamen.getBGZ:(II)I
  #112 = Fieldref           #230.#310     // MainProgram.dokan_mode:I
  #113 = Methodref          #233.#311     // KeyboardMenu.onKao:(IIIII)V
  #114 = Fieldref           #264.#312     // GameKey.up_f:Z
  #115 = Fieldref           #264.#313     // GameKey.down_f:Z
  #116 = Fieldref           #264.#314     // GameKey.left_f:Z
  #117 = Fieldref           #264.#315     // GameKey.right_f:Z
  #118 = Float              0.2617992f
  #119 = Methodref          #316.#317     // java/lang/Math.sin:(D)D
  #120 = Methodref          #316.#318     // java/lang/Math.cos:(D)D
  #121 = Fieldref           #57.#319      // java/awt/Color.black:Ljava/awt/Color;
  #122 = Methodref          #259.#320     // java/awt/Graphics.setColor:(Ljava/awt/Color;)V
  #123 = Methodref          #259.#321     // java/awt/Graphics.fillPolygon:([I[II)V
  #124 = Double             0.017453292519943295d
  #126 = Fieldref           #131.#322     // IdouGamen.cc_kakudo:I
  #127 = Double             500.0d
  #129 = Double             700.0d
  #131 = Class              #323          // IdouGamen
  #132 = Class              #324          // java/lang/Object
  #133 = Utf8               gk
  #134 = Utf8               LGameKey;
  #135 = Utf8               gg
  #136 = Utf8               LGameGraphics;
  #137 = Utf8               km
  #138 = Utf8               LKeyboardMenu;
  #139 = Utf8               mp
  #140 = Utf8               LMainProgram;
  #141 = Utf8               co_j
  #142 = Utf8               LCharacterObject;
  #143 = Utf8               map_string
  #144 = Utf8               [Ljava/lang/String;
  #145 = Utf8               map_bg
  #146 = Utf8               [[I
  #147 = Utf8               stage_c
  #148 = Utf8               [I
  #149 = Utf8               stage_x
  #150 = Utf8               stage_y
  #151 = Utf8               stage_cf
  #152 = Utf8               [Z
  #153 = Utf8               stage_kcID
  #154 = Utf8               I
  #155 = Utf8               door_koID
  #156 = Utf8               dokan_khID
  #157 = Utf8               door_score_open
  #158 = Utf8               ie_c
  #159 = Utf8               ie_x
  #160 = Utf8               ie_y
  #161 = Utf8               zure_x
  #162 = Utf8               ConstantValue
  #163 = Integer            16
  #164 = Utf8               zure_y
  #165 = Integer            24
  #166 = Utf8               mp_mode
  #167 = Utf8               shop_kattaitem
  #168 = Utf8               cc_hankei
  #169 = Utf8               cc_kakudo
  #170 = Utf8               cc_p1_x
  #171 = Utf8               cc_p1_y
  #172 = Utf8               cc_p2_x
  #173 = Utf8               cc_p2_y
  #174 = Utf8               <init>
  #175 = Utf8               (LGameGraphics;LGameKey;LKeyboardMenu;LMainProgram;)V
  #176 = Utf8               Code
  #177 = Utf8               LineNumberTable
  #178 = Utf8               worldInit
  #179 = Utf8               ()V
  #180 = Utf8               worldInit2
  #181 = Utf8               worldInit3
  #182 = Utf8               drawOs2
  #183 = Utf8               drawMap
  #184 = Utf8               getBGZ
  #185 = Utf8               (II)I
  #186 = Utf8               checkStage
  #187 = Utf8               ()I
  #188 = Utf8               mainProgram
  #189 = Utf8               jMove
  #190 = Utf8               circleCLS
  #191 = Utf8               (I)V
  #192 = Utf8               squareCLS
  #193 = Utf8               (II)V
  #194 = Utf8               SourceFile
  #195 = Utf8               MasaoConstruction.java
  #196 = NameAndType        #174:#179     // "<init>":()V
  #197 = Utf8               CharacterObject
  #198 = NameAndType        #141:#142     // co_j:LCharacterObject;
  #199 = Utf8               java/lang/String
  #200 = NameAndType        #143:#144     // map_string:[Ljava/lang/String;
  #201 = NameAndType        #145:#146     // map_bg:[[I
  #202 = NameAndType        #147:#148     // stage_c:[I
  #203 = NameAndType        #149:#148     // stage_x:[I
  #204 = NameAndType        #150:#148     // stage_y:[I
  #205 = NameAndType        #151:#152     // stage_cf:[Z
  #206 = NameAndType        #158:#148     // ie_c:[I
  #207 = NameAndType        #159:#148     // ie_x:[I
  #208 = NameAndType        #160:#148     // ie_y:[I
  #209 = NameAndType        #161:#154     // zure_x:I
  #210 = NameAndType        #164:#154     // zure_y:I
  #211 = NameAndType        #166:#154     // mp_mode:I
  #212 = NameAndType        #170:#148     // cc_p1_x:[I
  #213 = NameAndType        #171:#148     // cc_p1_y:[I
  #214 = NameAndType        #172:#148     // cc_p2_x:[I
  #215 = NameAndType        #173:#148     // cc_p2_y:[I
  #216 = NameAndType        #135:#136     // gg:LGameGraphics;
  #217 = NameAndType        #133:#134     // gk:LGameKey;
  #218 = NameAndType        #137:#138     // km:LKeyboardMenu;
  #219 = NameAndType        #139:#140     // mp:LMainProgram;
  #220 = NameAndType        #153:#154     // stage_kcID:I
  #221 = NameAndType        #155:#154     // door_koID:I
  #222 = NameAndType        #156:#154     // dokan_khID:I
  #223 = NameAndType        #157:#154     // door_score_open:I
  #224 = NameAndType        #325:#154     // x:I
  #225 = NameAndType        #326:#154     // y:I
  #226 = NameAndType        #327:#154     // vx:I
  #227 = NameAndType        #328:#154     // vy:I
  #228 = NameAndType        #329:#154     // muki:I
  #229 = NameAndType        #330:#154     // ac:I
  #230 = Class              #331          // MainProgram
  #231 = NameAndType        #332:#154     // tr1_c:I
  #232 = NameAndType        #167:#154     // shop_kattaitem:I
  #233 = Class              #333          // KeyboardMenu
  #234 = NameAndType        #334:#179     // initAll:()V
  #235 = NameAndType        #335:#154     // mode:I
  #236 = Class              #336          // GameGraphics
  #237 = NameAndType        #337:#338     // ap:Ljava/applet/Applet;
  #238 = Utf8               java/lang/StringBuffer
  #239 = Utf8               chizu-
  #240 = NameAndType        #339:#340     // append:(Ljava/lang/String;)Ljava/lang/StringBuffer;
  #241 = NameAndType        #339:#341     // append:(I)Ljava/lang/StringBuffer;
  #242 = NameAndType        #342:#343     // toString:()Ljava/lang/String;
  #243 = Class              #344          // java/applet/Applet
  #244 = NameAndType        #345:#346     // getParameter:(Ljava/lang/String;)Ljava/lang/String;
  #245 = Utf8               ...............
  #246 = NameAndType        #347:#348     // charAt:(I)C
  #247 = NameAndType        #182:#179     // drawOs2:()V
  #248 = NameAndType        #168:#154     // cc_hankei:I
  #249 = NameAndType        #349:#154     // score:I
  #250 = NameAndType        #350:#154     // door_score:I
  #251 = NameAndType        #186:#187     // checkStage:()I
  #252 = NameAndType        #351:#154     // pt:I
  #253 = Utf8               java/awt/Color
  #254 = NameAndType        #174:#352     // "<init>":(III)V
  #255 = NameAndType        #353:#354     // setBackcolor:(Ljava/awt/Color;)V
  #256 = NameAndType        #355:#179     // fill2:()V
  #257 = NameAndType        #356:#357     // os2_g:Ljava/awt/Graphics;
  #258 = NameAndType        #358:#359     // li:[Ljava/awt/Image;
  #259 = Class              #360          // java/awt/Graphics
  #260 = NameAndType        #361:#362     // drawImage:(Ljava/awt/Image;IILjava/awt/image/ImageObserver;)Z
  #261 = NameAndType        #363:#352     // drawPT2:(III)V
  #262 = NameAndType        #364:#357     // os_g:Ljava/awt/Graphics;
  #263 = NameAndType        #365:#366     // os2_img:Ljava/awt/Image;
  #264 = Class              #367          // GameKey
  #265 = NameAndType        #368:#369     // tr1_f:Z
  #266 = NameAndType        #189:#179     // jMove:()V
  #267 = NameAndType        #370:#154     // cancel_c:I
  #268 = NameAndType        #371:#191     // off:(I)V
  #269 = NameAndType        #372:#154     // kettei_c:I
  #270 = NameAndType        #373:#191     // init1:(I)V
  #271 = NameAndType        #374:#375     // mes1_name:Ljava/lang/String;
  #272 = NameAndType        #376:#377     // setMessage:(ILjava/lang/String;)V
  #273 = NameAndType        #378:#352     // addSerifu:(III)V
  #274 = NameAndType        #379:#380     // cyan:Ljava/awt/Color;
  #275 = NameAndType        #381:#382     // activeSerifu:(IIIILjava/awt/Color;)V
  #276 = NameAndType        #383:#375     // mes2_name:Ljava/lang/String;
  #277 = NameAndType        #384:#154     // list_kazu:I
  #278 = Utf8               shop_serifu1
  #279 = NameAndType        #385:#148     // shop_item_teika:[I
  #280 = NameAndType        #386:#144     // shop_item_name:[Ljava/lang/String;
  #281 = NameAndType        #387:#388     // addItem2:(ILjava/lang/String;I)V
  #282 = NameAndType        #389:#148     // list_IDlist:[I
  #283 = NameAndType        #390:#391     // activeKaimono:(IIII)V
  #284 = Utf8               Error
  #285 = Utf8               Please set any item on shop menu.
  #286 = NameAndType        #392:#377     // addItem:(ILjava/lang/String;)V
  #287 = NameAndType        #393:#380     // red:Ljava/awt/Color;
  #288 = NameAndType        #394:#148     // selectedIndex:[I
  #289 = NameAndType        #395:#154     // list_s:I
  #290 = Utf8               shop_serifu2
  #291 = Utf8               shop_serifu3
  #292 = Utf8               shop_serifu4
  #293 = NameAndType        #396:#375     // shop_name:Ljava/lang/String;
  #294 = NameAndType        #397:#398     // activeSerifutuki:(IIIILjava/lang/String;)V
  #295 = NameAndType        #399:#193     // offActivewindow:(II)V
  #296 = Utf8               shop_serifu5
  #297 = NameAndType        #400:#391     // activeIchigyou:(IIII)V
  #298 = NameAndType        #401:#154     // j_left:I
  #299 = Utf8               shop_serifu6
  #300 = Utf8               setumei_menu1
  #301 = Utf8               setumei_menu2
  #302 = Utf8               setumei_menu3
  #303 = Utf8               setumei_menu4
  #304 = NameAndType        #402:#375     // setumei_name:Ljava/lang/String;
  #305 = NameAndType        #403:#179     // move:()V
  #306 = NameAndType        #404:#391     // drawPT:(IIII)V
  #307 = NameAndType        #405:#179     // drawMenus:()V
  #308 = NameAndType        #190:#191     // circleCLS:(I)V
  #309 = NameAndType        #184:#185     // getBGZ:(II)I
  #310 = NameAndType        #406:#154     // dokan_mode:I
  #311 = NameAndType        #407:#408     // onKao:(IIIII)V
  #312 = NameAndType        #409:#369     // up_f:Z
  #313 = NameAndType        #410:#369     // down_f:Z
  #314 = NameAndType        #411:#369     // left_f:Z
  #315 = NameAndType        #412:#369     // right_f:Z
  #316 = Class              #413          // java/lang/Math
  #317 = NameAndType        #414:#415     // sin:(D)D
  #318 = NameAndType        #416:#415     // cos:(D)D
  #319 = NameAndType        #417:#380     // black:Ljava/awt/Color;
  #320 = NameAndType        #418:#354     // setColor:(Ljava/awt/Color;)V
  #321 = NameAndType        #419:#420     // fillPolygon:([I[II)V
  #322 = NameAndType        #169:#154     // cc_kakudo:I
  #323 = Utf8               IdouGamen
  #324 = Utf8               java/lang/Object
  #325 = Utf8               x
  #326 = Utf8               y
  #327 = Utf8               vx
  #328 = Utf8               vy
  #329 = Utf8               muki
  #330 = Utf8               ac
  #331 = Utf8               MainProgram
  #332 = Utf8               tr1_c
  #333 = Utf8               KeyboardMenu
  #334 = Utf8               initAll
  #335 = Utf8               mode
  #336 = Utf8               GameGraphics
  #337 = Utf8               ap
  #338 = Utf8               Ljava/applet/Applet;
  #339 = Utf8               append
  #340 = Utf8               (Ljava/lang/String;)Ljava/lang/StringBuffer;
  #341 = Utf8               (I)Ljava/lang/StringBuffer;
  #342 = Utf8               toString
  #343 = Utf8               ()Ljava/lang/String;
  #344 = Utf8               java/applet/Applet
  #345 = Utf8               getParameter
  #346 = Utf8               (Ljava/lang/String;)Ljava/lang/String;
  #347 = Utf8               charAt
  #348 = Utf8               (I)C
  #349 = Utf8               score
  #350 = Utf8               door_score
  #351 = Utf8               pt
  #352 = Utf8               (III)V
  #353 = Utf8               setBackcolor
  #354 = Utf8               (Ljava/awt/Color;)V
  #355 = Utf8               fill2
  #356 = Utf8               os2_g
  #357 = Utf8               Ljava/awt/Graphics;
  #358 = Utf8               li
  #359 = Utf8               [Ljava/awt/Image;
  #360 = Utf8               java/awt/Graphics
  #361 = Utf8               drawImage
  #362 = Utf8               (Ljava/awt/Image;IILjava/awt/image/ImageObserver;)Z
  #363 = Utf8               drawPT2
  #364 = Utf8               os_g
  #365 = Utf8               os2_img
  #366 = Utf8               Ljava/awt/Image;
  #367 = Utf8               GameKey
  #368 = Utf8               tr1_f
  #369 = Utf8               Z
  #370 = Utf8               cancel_c
  #371 = Utf8               off
  #372 = Utf8               kettei_c
  #373 = Utf8               init1
  #374 = Utf8               mes1_name
  #375 = Utf8               Ljava/lang/String;
  #376 = Utf8               setMessage
  #377 = Utf8               (ILjava/lang/String;)V
  #378 = Utf8               addSerifu
  #379 = Utf8               cyan
  #380 = Utf8               Ljava/awt/Color;
  #381 = Utf8               activeSerifu
  #382 = Utf8               (IIIILjava/awt/Color;)V
  #383 = Utf8               mes2_name
  #384 = Utf8               list_kazu
  #385 = Utf8               shop_item_teika
  #386 = Utf8               shop_item_name
  #387 = Utf8               addItem2
  #388 = Utf8               (ILjava/lang/String;I)V
  #389 = Utf8               list_IDlist
  #390 = Utf8               activeKaimono
  #391 = Utf8               (IIII)V
  #392 = Utf8               addItem
  #393 = Utf8               red
  #394 = Utf8               selectedIndex
  #395 = Utf8               list_s
  #396 = Utf8               shop_name
  #397 = Utf8               activeSerifutuki
  #398 = Utf8               (IIIILjava/lang/String;)V
  #399 = Utf8               offActivewindow
  #400 = Utf8               activeIchigyou
  #401 = Utf8               j_left
  #402 = Utf8               setumei_name
  #403 = Utf8               move
  #404 = Utf8               drawPT
  #405 = Utf8               drawMenus
  #406 = Utf8               dokan_mode
  #407 = Utf8               onKao
  #408 = Utf8               (IIIII)V
  #409 = Utf8               up_f
  #410 = Utf8               down_f
  #411 = Utf8               left_f
  #412 = Utf8               right_f
  #413 = Utf8               java/lang/Math
  #414 = Utf8               sin
  #415 = Utf8               (D)D
  #416 = Utf8               cos
  #417 = Utf8               black
  #418 = Utf8               setColor
  #419 = Utf8               fillPolygon
  #420 = Utf8               ([I[II)V
{
  GameKey gk;
    descriptor: LGameKey;
    flags: (0x0000)

  GameGraphics gg;
    descriptor: LGameGraphics;
    flags: (0x0000)

  KeyboardMenu km;
    descriptor: LKeyboardMenu;
    flags: (0x0000)

  MainProgram mp;
    descriptor: LMainProgram;
    flags: (0x0000)

  CharacterObject co_j;
    descriptor: LCharacterObject;
    flags: (0x0000)

  java.lang.String[] map_string;
    descriptor: [Ljava/lang/String;
    flags: (0x0000)

  int[][] map_bg;
    descriptor: [[I
    flags: (0x0000)

  int[] stage_c;
    descriptor: [I
    flags: (0x0000)

  int[] stage_x;
    descriptor: [I
    flags: (0x0000)

  int[] stage_y;
    descriptor: [I
    flags: (0x0000)

  boolean[] stage_cf;
    descriptor: [Z
    flags: (0x0000)

  int stage_kcID;
    descriptor: I
    flags: (0x0000)

  int door_koID;
    descriptor: I
    flags: (0x0000)

  int dokan_khID;
    descriptor: I
    flags: (0x0000)

  int door_score_open;
    descriptor: I
    flags: (0x0000)

  int[] ie_c;
    descriptor: [I
    flags: (0x0000)

  int[] ie_x;
    descriptor: [I
    flags: (0x0000)

  int[] ie_y;
    descriptor: [I
    flags: (0x0000)

  final int zure_x;
    descriptor: I
    flags: (0x0010) ACC_FINAL
    ConstantValue: int 16

  final int zure_y;
    descriptor: I
    flags: (0x0010) ACC_FINAL
    ConstantValue: int 24

  int mp_mode;
    descriptor: I
    flags: (0x0000)

  int shop_kattaitem;
    descriptor: I
    flags: (0x0000)

  int cc_hankei;
    descriptor: I
    flags: (0x0000)

  int cc_kakudo;
    descriptor: I
    flags: (0x0000)

  int[] cc_p1_x;
    descriptor: [I
    flags: (0x0000)

  int[] cc_p1_y;
    descriptor: [I
    flags: (0x0000)

  int[] cc_p2_x;
    descriptor: [I
    flags: (0x0000)

  int[] cc_p2_y;
    descriptor: [I
    flags: (0x0000)

  IdouGamen(GameGraphics, GameKey, KeyboardMenu, MainProgram);
    descriptor: (LGameGraphics;LGameKey;LKeyboardMenu;LMainProgram;)V
    flags: (0x0000)
    Code:
      stack=3, locals=6, args_size=5
         0: aload_0
         1: invokespecial #1                  // Method java/lang/Object."<init>":()V
         4: aload_0
         5: new           #2                  // class CharacterObject
         8: dup
         9: invokespecial #3                  // Method CharacterObject."<init>":()V
        12: putfield      #4                  // Field co_j:LCharacterObject;
        15: aload_0
        16: bipush        9
        18: anewarray     #5                  // class java/lang/String
        21: putfield      #6                  // Field map_string:[Ljava/lang/String;
        24: aload_0
        25: bipush        15
        27: bipush        9
        29: multianewarray #7,  2             // class "[[I"
        33: putfield      #8                  // Field map_bg:[[I
        36: aload_0
        37: bipush        10
        39: newarray       int
        41: putfield      #9                  // Field stage_c:[I
        44: aload_0
        45: bipush        10
        47: newarray       int
        49: putfield      #10                 // Field stage_x:[I
        52: aload_0
        53: bipush        10
        55: newarray       int
        57: putfield      #11                 // Field stage_y:[I
        60: aload_0
        61: bipush        10
        63: newarray       boolean
        65: putfield      #12                 // Field stage_cf:[Z
        68: aload_0
        69: bipush        16
        71: newarray       int
        73: putfield      #13                 // Field ie_c:[I
        76: aload_0
        77: bipush        16
        79: newarray       int
        81: putfield      #14                 // Field ie_x:[I
        84: aload_0
        85: bipush        16
        87: newarray       int
        89: putfield      #15                 // Field ie_y:[I
        92: aload_0
        93: bipush        16
        95: putfield      #16                 // Field zure_x:I
        98: aload_0
        99: bipush        24
       101: putfield      #17                 // Field zure_y:I
       104: aload_0
       105: iconst_0
       106: putfield      #18                 // Field mp_mode:I
       109: aload_0
       110: bipush        17
       112: newarray       int
       114: putfield      #19                 // Field cc_p1_x:[I
       117: aload_0
       118: bipush        17
       120: newarray       int
       122: putfield      #20                 // Field cc_p1_y:[I
       125: aload_0
       126: bipush        17
       128: newarray       int
       130: putfield      #21                 // Field cc_p2_x:[I
       133: aload_0
       134: bipush        17
       136: newarray       int
       138: putfield      #22                 // Field cc_p2_y:[I
       141: aload_0
       142: aload_1
       143: putfield      #23                 // Field gg:LGameGraphics;
       146: aload_0
       147: aload_2
       148: putfield      #24                 // Field gk:LGameKey;
       151: aload_0
       152: aload_3
       153: putfield      #25                 // Field km:LKeyboardMenu;
       156: aload_0
       157: aload         4
       159: putfield      #26                 // Field mp:LMainProgram;
       162: aload_0
       163: getfield      #19                 // Field cc_p1_x:[I
       166: bipush        13
       168: sipush        -200
       171: iastore
       172: aload_0
       173: getfield      #20                 // Field cc_p1_y:[I
       176: bipush        13
       178: sipush        160
       181: iastore
       182: aload_0
       183: getfield      #19                 // Field cc_p1_x:[I
       186: bipush        14
       188: sipush        -200
       191: iastore
       192: aload_0
       193: getfield      #20                 // Field cc_p1_y:[I
       196: bipush        14
       198: sipush        520
       201: iastore
       202: aload_0
       203: getfield      #19                 // Field cc_p1_x:[I
       206: bipush        15
       208: sipush        712
       211: iastore
       212: aload_0
       213: getfield      #20                 // Field cc_p1_y:[I
       216: bipush        15
       218: sipush        520
       221: iastore
       222: aload_0
       223: getfield      #19                 // Field cc_p1_x:[I
       226: bipush        16
       228: sipush        712
       231: iastore
       232: aload_0
       233: getfield      #20                 // Field cc_p1_y:[I
       236: bipush        16
       238: sipush        160
       241: iastore
       242: aload_0
       243: getfield      #21                 // Field cc_p2_x:[I
       246: bipush        13
       248: sipush        712
       251: iastore
       252: aload_0
       253: getfield      #22                 // Field cc_p2_y:[I
       256: bipush        13
       258: sipush        160
       261: iastore
       262: aload_0
       263: getfield      #21                 // Field cc_p2_x:[I
       266: bipush        14
       268: sipush        712
       271: iastore
       272: aload_0
       273: getfield      #22                 // Field cc_p2_y:[I
       276: bipush        14
       278: sipush        -200
       281: iastore
       282: aload_0
       283: getfield      #21                 // Field cc_p2_x:[I
       286: bipush        15
       288: sipush        -200
       291: iastore
       292: aload_0
       293: getfield      #22                 // Field cc_p2_y:[I
       296: bipush        15
       298: sipush        -200
       301: iastore
       302: aload_0
       303: getfield      #21                 // Field cc_p2_x:[I
       306: bipush        16
       308: sipush        -200
       311: iastore
       312: aload_0
       313: getfield      #22                 // Field cc_p2_y:[I
       316: bipush        16
       318: sipush        160
       321: iastore
       322: return
      LineNumberTable:
        line 14806: 0
        line 14744: 4
        line 14747: 15
        line 14748: 24
        line 14750: 36
        line 14754: 44
        line 14755: 52
        line 14756: 60
        line 14765: 68
        line 14781: 76
        line 14782: 84
        line 14785: 92
        line 14786: 98
        line 14788: 104
        line 14795: 109
        line 14796: 117
        line 14797: 125
        line 14798: 133
        line 14810: 141
        line 14811: 146
        line 14812: 151
        line 14813: 156
        line 14816: 162
        line 14817: 172
        line 14818: 182
        line 14819: 192
        line 14820: 202
        line 14821: 212
        line 14822: 222
        line 14823: 232
        line 14824: 242
        line 14825: 252
        line 14826: 262
        line 14827: 272
        line 14828: 282
        line 14829: 292
        line 14830: 302
        line 14831: 312
        line 14832: 322

  void worldInit();
    descriptor: ()V
    flags: (0x0000)
    Code:
      stack=4, locals=7, args_size=1
         0: iconst_0
         1: istore_1
         2: goto          22
         5: aload_0
         6: getfield      #9                  // Field stage_c:[I
         9: iload_1
        10: iconst_0
        11: iastore
        12: aload_0
        13: getfield      #12                 // Field stage_cf:[Z
        16: iload_1
        17: iconst_0
        18: bastore
        19: iinc          1, 1
        22: iload_1
        23: bipush        9
        25: if_icmple     5
        28: aload_0
        29: iconst_0
        30: putfield      #27                 // Field stage_kcID:I
        33: aload_0
        34: iconst_0
        35: putfield      #28                 // Field door_koID:I
        38: aload_0
        39: iconst_0
        40: putfield      #29                 // Field dokan_khID:I
        43: aload_0
        44: iconst_0
        45: putfield      #30                 // Field door_score_open:I
        48: iconst_0
        49: istore_1
        50: goto          63
        53: aload_0
        54: getfield      #13                 // Field ie_c:[I
        57: iload_1
        58: iconst_0
        59: iastore
        60: iinc          1, 1
        63: iload_1
        64: bipush        15
        66: if_icmple     53
        69: aload_0
        70: getfield      #4                  // Field co_j:LCharacterObject;
        73: iconst_0
        74: putfield      #31                 // Field CharacterObject.x:I
        77: aload_0
        78: getfield      #4                  // Field co_j:LCharacterObject;
        81: iconst_0
        82: putfield      #32                 // Field CharacterObject.y:I
        85: aload_0
        86: getfield      #4                  // Field co_j:LCharacterObject;
        89: iconst_0
        90: putfield      #33                 // Field CharacterObject.vx:I
        93: aload_0
        94: getfield      #4                  // Field co_j:LCharacterObject;
        97: iconst_0
        98: putfield      #34                 // Field CharacterObject.vy:I
       101: aload_0
       102: getfield      #4                  // Field co_j:LCharacterObject;
       105: iconst_1
       106: putfield      #35                 // Field CharacterObject.muki:I
       109: aload_0
       110: getfield      #4                  // Field co_j:LCharacterObject;
       113: iconst_0
       114: putfield      #36                 // Field CharacterObject.ac:I
       117: aload_0
       118: getfield      #26                 // Field mp:LMainProgram;
       121: iconst_2
       122: putfield      #37                 // Field MainProgram.tr1_c:I
       125: aload_0
       126: iconst_m1
       127: putfield      #38                 // Field shop_kattaitem:I
       130: aload_0
       131: iconst_0
       132: putfield      #18                 // Field mp_mode:I
       135: aload_0
       136: getfield      #25                 // Field km:LKeyboardMenu;
       139: invokevirtual #39                 // Method KeyboardMenu.initAll:()V
       142: aload_0
       143: getfield      #25                 // Field km:LKeyboardMenu;
       146: bipush        100
       148: putfield      #40                 // Field KeyboardMenu.mode:I
       151: iconst_0
       152: istore        4
       154: goto          223
       157: aload_0
       158: getfield      #23                 // Field gg:LGameGraphics;
       161: getfield      #41                 // Field GameGraphics.ap:Ljava/applet/Applet;
       164: new           #42                 // class java/lang/StringBuffer
       167: dup
       168: invokespecial #43                 // Method java/lang/StringBuffer."<init>":()V
       171: ldc           #44                 // String chizu-
       173: invokevirtual #45                 // Method java/lang/StringBuffer.append:(Ljava/lang/String;)Ljava/lang/StringBuffer;
       176: iload         4
       178: invokevirtual #46                 // Method java/lang/StringBuffer.append:(I)Ljava/lang/StringBuffer;
       181: invokevirtual #47                 // Method java/lang/StringBuffer.toString:()Ljava/lang/String;
       184: invokevirtual #48                 // Method java/applet/Applet.getParameter:(Ljava/lang/String;)Ljava/lang/String;
       187: astore        6
       189: new           #42                 // class java/lang/StringBuffer
       192: dup
       193: invokespecial #43                 // Method java/lang/StringBuffer."<init>":()V
       196: aload         6
       198: invokevirtual #45                 // Method java/lang/StringBuffer.append:(Ljava/lang/String;)Ljava/lang/StringBuffer;
       201: ldc           #49                 // String ...............
       203: invokevirtual #45                 // Method java/lang/StringBuffer.append:(Ljava/lang/String;)Ljava/lang/StringBuffer;
       206: invokevirtual #47                 // Method java/lang/StringBuffer.toString:()Ljava/lang/String;
       209: astore        6
       211: aload_0
       212: getfield      #6                  // Field map_string:[Ljava/lang/String;
       215: iload         4
       217: aload         6
       219: aastore
       220: iinc          4, 1
       223: iload         4
       225: bipush        8
       227: if_icmple     157
       230: iconst_0
       231: istore        4
       233: goto          1317
       236: iconst_0
       237: istore_3
       238: goto          1308
       241: aload_0
       242: getfield      #6                  // Field map_string:[Ljava/lang/String;
       245: iload         4
       247: aaload
       248: iload_3
       249: invokevirtual #50                 // Method java/lang/String.charAt:(I)C
       252: istore        5
       254: iload         5
       256: bipush        65
       258: if_icmpne     299
       261: aload_0
       262: getfield      #4                  // Field co_j:LCharacterObject;
       265: iload_3
       266: bipush        32
       268: imul
       269: putfield      #31                 // Field CharacterObject.x:I
       272: aload_0
       273: getfield      #4                  // Field co_j:LCharacterObject;
       276: iload         4
       278: bipush        32
       280: imul
       281: putfield      #32                 // Field CharacterObject.y:I
       284: aload_0
       285: getfield      #8                  // Field map_bg:[[I
       288: iload_3
       289: aaload
       290: iload         4
       292: sipush        220
       295: iastore
       296: goto          1305
       299: iload         5
       301: bipush        66
       303: if_icmpne     350
       306: aload_0
       307: getfield      #8                  // Field map_bg:[[I
       310: iload_3
       311: aaload
       312: iload         4
       314: sipush        216
       317: iastore
       318: aload_0
       319: getfield      #13                 // Field ie_c:[I
       322: iconst_3
       323: bipush        100
       325: iastore
       326: aload_0
       327: getfield      #14                 // Field ie_x:[I
       330: iconst_3
       331: iload_3
       332: bipush        32
       334: imul
       335: iastore
       336: aload_0
       337: getfield      #15                 // Field ie_y:[I
       340: iconst_3
       341: iload         4
       343: bipush        32
       345: imul
       346: iastore
       347: goto          1305
       350: iload         5
       352: bipush        67
       354: if_icmpne     401
       357: aload_0
       358: getfield      #8                  // Field map_bg:[[I
       361: iload_3
       362: aaload
       363: iload         4
       365: sipush        217
       368: iastore
       369: aload_0
       370: getfield      #13                 // Field ie_c:[I
       373: iconst_4
       374: bipush        100
       376: iastore
       377: aload_0
       378: getfield      #14                 // Field ie_x:[I
       381: iconst_4
       382: iload_3
       383: bipush        32
       385: imul
       386: iastore
       387: aload_0
       388: getfield      #15                 // Field ie_y:[I
       391: iconst_4
       392: iload         4
       394: bipush        32
       396: imul
       397: iastore
       398: goto          1305
       401: iload         5
       403: bipush        68
       405: if_icmpne     455
       408: aload_0
       409: getfield      #8                  // Field map_bg:[[I
       412: iload_3
       413: aaload
       414: iload         4
       416: sipush        218
       419: iastore
       420: aload_0
       421: getfield      #13                 // Field ie_c:[I
       424: bipush        10
       426: bipush        100
       428: iastore
       429: aload_0
       430: getfield      #14                 // Field ie_x:[I
       433: bipush        10
       435: iload_3
       436: bipush        32
       438: imul
       439: iastore
       440: aload_0
       441: getfield      #15                 // Field ie_y:[I
       444: bipush        10
       446: iload         4
       448: bipush        32
       450: imul
       451: iastore
       452: goto          1305
       455: iload         5
       457: bipush        69
       459: if_icmpne     509
       462: aload_0
       463: getfield      #8                  // Field map_bg:[[I
       466: iload_3
       467: aaload
       468: iload         4
       470: sipush        219
       473: iastore
       474: aload_0
       475: getfield      #13                 // Field ie_c:[I
       478: bipush        11
       480: bipush        100
       482: iastore
       483: aload_0
       484: getfield      #14                 // Field ie_x:[I
       487: bipush        11
       489: iload_3
       490: bipush        32
       492: imul
       493: iastore
       494: aload_0
       495: getfield      #15                 // Field ie_y:[I
       498: bipush        11
       500: iload         4
       502: bipush        32
       504: imul
       505: iastore
       506: goto          1305
       509: iload         5
       511: bipush        97
       513: if_icmpne     584
       516: aload_0
       517: getfield      #9                  // Field stage_c:[I
       520: iconst_0
       521: iaload
       522: ifne          569
       525: aload_0
       526: getfield      #8                  // Field map_bg:[[I
       529: iload_3
       530: aaload
       531: iload         4
       533: sipush        223
       536: iastore
       537: aload_0
       538: getfield      #9                  // Field stage_c:[I
       541: iconst_0
       542: bipush        100
       544: iastore
       545: aload_0
       546: getfield      #10                 // Field stage_x:[I
       549: iconst_0
       550: iload_3
       551: bipush        32
       553: imul
       554: iastore
       555: aload_0
       556: getfield      #11                 // Field stage_y:[I
       559: iconst_0
       560: iload         4
       562: bipush        32
       564: imul
       565: iastore
       566: goto          1305
       569: aload_0
       570: getfield      #8                  // Field map_bg:[[I
       573: iload_3
       574: aaload
       575: iload         4
       577: sipush        220
       580: iastore
       581: goto          1305
       584: iload         5
       586: bipush        98
       588: if_icmpne     659
       591: aload_0
       592: getfield      #9                  // Field stage_c:[I
       595: iconst_1
       596: iaload
       597: ifne          644
       600: aload_0
       601: getfield      #8                  // Field map_bg:[[I
       604: iload_3
       605: aaload
       606: iload         4
       608: sipush        224
       611: iastore
       612: aload_0
       613: getfield      #9                  // Field stage_c:[I
       616: iconst_1
       617: bipush        100
       619: iastore
       620: aload_0
       621: getfield      #10                 // Field stage_x:[I
       624: iconst_1
       625: iload_3
       626: bipush        32
       628: imul
       629: iastore
       630: aload_0
       631: getfield      #11                 // Field stage_y:[I
       634: iconst_1
       635: iload         4
       637: bipush        32
       639: imul
       640: iastore
       641: goto          1305
       644: aload_0
       645: getfield      #8                  // Field map_bg:[[I
       648: iload_3
       649: aaload
       650: iload         4
       652: sipush        220
       655: iastore
       656: goto          1305
       659: iload         5
       661: bipush        99
       663: if_icmpne     734
       666: aload_0
       667: getfield      #9                  // Field stage_c:[I
       670: iconst_2
       671: iaload
       672: ifne          719
       675: aload_0
       676: getfield      #8                  // Field map_bg:[[I
       679: iload_3
       680: aaload
       681: iload         4
       683: sipush        225
       686: iastore
       687: aload_0
       688: getfield      #9                  // Field stage_c:[I
       691: iconst_2
       692: bipush        100
       694: iastore
       695: aload_0
       696: getfield      #10                 // Field stage_x:[I
       699: iconst_2
       700: iload_3
       701: bipush        32
       703: imul
       704: iastore
       705: aload_0
       706: getfield      #11                 // Field stage_y:[I
       709: iconst_2
       710: iload         4
       712: bipush        32
       714: imul
       715: iastore
       716: goto          1305
       719: aload_0
       720: getfield      #8                  // Field map_bg:[[I
       723: iload_3
       724: aaload
       725: iload         4
       727: sipush        220
       730: iastore
       731: goto          1305
       734: iload         5
       736: bipush        100
       738: if_icmpne     809
       741: aload_0
       742: getfield      #9                  // Field stage_c:[I
       745: iconst_3
       746: iaload
       747: ifne          794
       750: aload_0
       751: getfield      #8                  // Field map_bg:[[I
       754: iload_3
       755: aaload
       756: iload         4
       758: sipush        226
       761: iastore
       762: aload_0
       763: getfield      #9                  // Field stage_c:[I
       766: iconst_3
       767: bipush        100
       769: iastore
       770: aload_0
       771: getfield      #10                 // Field stage_x:[I
       774: iconst_3
       775: iload_3
       776: bipush        32
       778: imul
       779: iastore
       780: aload_0
       781: getfield      #11                 // Field stage_y:[I
       784: iconst_3
       785: iload         4
       787: bipush        32
       789: imul
       790: iastore
       791: goto          1305
       794: aload_0
       795: getfield      #8                  // Field map_bg:[[I
       798: iload_3
       799: aaload
       800: iload         4
       802: sipush        220
       805: iastore
       806: goto          1305
       809: iload         5
       811: bipush        101
       813: if_icmpne     860
       816: aload_0
       817: getfield      #8                  // Field map_bg:[[I
       820: iload_3
       821: aaload
       822: iload         4
       824: sipush        213
       827: iastore
       828: aload_0
       829: getfield      #13                 // Field ie_c:[I
       832: iconst_0
       833: bipush        100
       835: iastore
       836: aload_0
       837: getfield      #14                 // Field ie_x:[I
       840: iconst_0
       841: iload_3
       842: bipush        32
       844: imul
       845: iastore
       846: aload_0
       847: getfield      #15                 // Field ie_y:[I
       850: iconst_0
       851: iload         4
       853: bipush        32
       855: imul
       856: iastore
       857: goto          1305
       860: iload         5
       862: bipush        102
       864: if_icmpne     911
       867: aload_0
       868: getfield      #8                  // Field map_bg:[[I
       871: iload_3
       872: aaload
       873: iload         4
       875: sipush        214
       878: iastore
       879: aload_0
       880: getfield      #13                 // Field ie_c:[I
       883: iconst_1
       884: bipush        100
       886: iastore
       887: aload_0
       888: getfield      #14                 // Field ie_x:[I
       891: iconst_1
       892: iload_3
       893: bipush        32
       895: imul
       896: iastore
       897: aload_0
       898: getfield      #15                 // Field ie_y:[I
       901: iconst_1
       902: iload         4
       904: bipush        32
       906: imul
       907: iastore
       908: goto          1305
       911: iload         5
       913: bipush        103
       915: if_icmpne     962
       918: aload_0
       919: getfield      #8                  // Field map_bg:[[I
       922: iload_3
       923: aaload
       924: iload         4
       926: sipush        215
       929: iastore
       930: aload_0
       931: getfield      #13                 // Field ie_c:[I
       934: iconst_2
       935: bipush        100
       937: iastore
       938: aload_0
       939: getfield      #14                 // Field ie_x:[I
       942: iconst_2
       943: iload_3
       944: bipush        32
       946: imul
       947: iastore
       948: aload_0
       949: getfield      #15                 // Field ie_y:[I
       952: iconst_2
       953: iload         4
       955: bipush        32
       957: imul
       958: iastore
       959: goto          1305
       962: iload         5
       964: bipush        104
       966: if_icmpne     1016
       969: aload_0
       970: getfield      #8                  // Field map_bg:[[I
       973: iload_3
       974: aaload
       975: iload         4
       977: sipush        212
       980: iastore
       981: aload_0
       982: getfield      #13                 // Field ie_c:[I
       985: bipush        9
       987: bipush        100
       989: iastore
       990: aload_0
       991: getfield      #14                 // Field ie_x:[I
       994: bipush        9
       996: iload_3
       997: bipush        32
       999: imul
      1000: iastore
      1001: aload_0
      1002: getfield      #15                 // Field ie_y:[I
      1005: bipush        9
      1007: iload         4
      1009: bipush        32
      1011: imul
      1012: iastore
      1013: goto          1305
      1016: iload         5
      1018: bipush        105
      1020: if_icmpne     1067
      1023: aload_0
      1024: getfield      #8                  // Field map_bg:[[I
      1027: iload_3
      1028: aaload
      1029: iload         4
      1031: sipush        206
      1034: iastore
      1035: aload_0
      1036: getfield      #13                 // Field ie_c:[I
      1039: iconst_5
      1040: bipush        100
      1042: iastore
      1043: aload_0
      1044: getfield      #14                 // Field ie_x:[I
      1047: iconst_5
      1048: iload_3
      1049: bipush        32
      1051: imul
      1052: iastore
      1053: aload_0
      1054: getfield      #15                 // Field ie_y:[I
      1057: iconst_5
      1058: iload         4
      1060: bipush        32
      1062: imul
      1063: iastore
      1064: goto          1305
      1067: iload         5
      1069: bipush        106
      1071: if_icmpne     1121
      1074: aload_0
      1075: getfield      #8                  // Field map_bg:[[I
      1078: iload_3
      1079: aaload
      1080: iload         4
      1082: sipush        207
      1085: iastore
      1086: aload_0
      1087: getfield      #13                 // Field ie_c:[I
      1090: bipush        6
      1092: bipush        100
      1094: iastore
      1095: aload_0
      1096: getfield      #14                 // Field ie_x:[I
      1099: bipush        6
      1101: iload_3
      1102: bipush        32
      1104: imul
      1105: iastore
      1106: aload_0
      1107: getfield      #15                 // Field ie_y:[I
      1110: bipush        6
      1112: iload         4
      1114: bipush        32
      1116: imul
      1117: iastore
      1118: goto          1305
      1121: iload         5
      1123: bipush        107
      1125: if_icmpne     1175
      1128: aload_0
      1129: getfield      #8                  // Field map_bg:[[I
      1132: iload_3
      1133: aaload
      1134: iload         4
      1136: sipush        208
      1139: iastore
      1140: aload_0
      1141: getfield      #13                 // Field ie_c:[I
      1144: bipush        7
      1146: bipush        100
      1148: iastore
      1149: aload_0
      1150: getfield      #14                 // Field ie_x:[I
      1153: bipush        7
      1155: iload_3
      1156: bipush        32
      1158: imul
      1159: iastore
      1160: aload_0
      1161: getfield      #15                 // Field ie_y:[I
      1164: bipush        7
      1166: iload         4
      1168: bipush        32
      1170: imul
      1171: iastore
      1172: goto          1305
      1175: iload         5
      1177: bipush        108
      1179: if_icmpne     1229
      1182: aload_0
      1183: getfield      #8                  // Field map_bg:[[I
      1186: iload_3
      1187: aaload
      1188: iload         4
      1190: sipush        209
      1193: iastore
      1194: aload_0
      1195: getfield      #13                 // Field ie_c:[I
      1198: bipush        8
      1200: bipush        100
      1202: iastore
      1203: aload_0
      1204: getfield      #14                 // Field ie_x:[I
      1207: bipush        8
      1209: iload_3
      1210: bipush        32
      1212: imul
      1213: iastore
      1214: aload_0
      1215: getfield      #15                 // Field ie_y:[I
      1218: bipush        8
      1220: iload         4
      1222: bipush        32
      1224: imul
      1225: iastore
      1226: goto          1305
      1229: iload         5
      1231: bipush        49
      1233: if_icmpne     1251
      1236: aload_0
      1237: getfield      #8                  // Field map_bg:[[I
      1240: iload_3
      1241: aaload
      1242: iload         4
      1244: sipush        220
      1247: iastore
      1248: goto          1305
      1251: iload         5
      1253: bipush        50
      1255: if_icmpne     1273
      1258: aload_0
      1259: getfield      #8                  // Field map_bg:[[I
      1262: iload_3
      1263: aaload
      1264: iload         4
      1266: sipush        221
      1269: iastore
      1270: goto          1305
      1273: iload         5
      1275: bipush        51
      1277: if_icmpne     1295
      1280: aload_0
      1281: getfield      #8                  // Field map_bg:[[I
      1284: iload_3
      1285: aaload
      1286: iload         4
      1288: sipush        222
      1291: iastore
      1292: goto          1305
      1295: aload_0
      1296: getfield      #8                  // Field map_bg:[[I
      1299: iload_3
      1300: aaload
      1301: iload         4
      1303: iconst_0
      1304: iastore
      1305: iinc          3, 1
      1308: iload_3
      1309: bipush        14
      1311: if_icmple     241
      1314: iinc          4, 1
      1317: iload         4
      1319: bipush        8
      1321: if_icmple     236
      1324: aload_0
      1325: getfield      #4                  // Field co_j:LCharacterObject;
      1328: getfield      #31                 // Field CharacterObject.x:I
      1331: bipush        16
      1333: iadd
      1334: sipush        256
      1337: if_icmple     1348
      1340: aload_0
      1341: getfield      #4                  // Field co_j:LCharacterObject;
      1344: iconst_0
      1345: putfield      #35                 // Field CharacterObject.muki:I
      1348: aload_0
      1349: invokevirtual #51                 // Method drawOs2:()V
      1352: return
      LineNumberTable:
        line 14844: 0
        line 14845: 5
        line 14846: 12
        line 14844: 19
        line 14848: 28
        line 14849: 33
        line 14850: 38
        line 14851: 43
        line 14854: 48
        line 14855: 53
        line 14854: 60
        line 14859: 69
        line 14860: 77
        line 14861: 85
        line 14862: 93
        line 14863: 101
        line 14864: 109
        line 14865: 117
        line 14868: 125
        line 14871: 130
        line 14874: 135
        line 14875: 142
        line 14878: 151
        line 14879: 157
        line 14880: 189
        line 14881: 211
        line 14878: 220
        line 14885: 230
        line 14886: 236
        line 14887: 241
        line 14888: 254
        line 14890: 261
        line 14891: 272
        line 14892: 284
        line 14894: 299
        line 14896: 306
        line 14897: 318
        line 14898: 326
        line 14899: 336
        line 14901: 350
        line 14903: 357
        line 14904: 369
        line 14905: 377
        line 14906: 387
        line 14908: 401
        line 14910: 408
        line 14911: 420
        line 14912: 429
        line 14913: 440
        line 14915: 455
        line 14917: 462
        line 14918: 474
        line 14919: 483
        line 14920: 494
        line 14922: 509
        line 14924: 516
        line 14925: 525
        line 14926: 537
        line 14927: 545
        line 14928: 555
        line 14932: 569
        line 14935: 584
        line 14937: 591
        line 14938: 600
        line 14939: 612
        line 14940: 620
        line 14941: 630
        line 14945: 644
        line 14948: 659
        line 14950: 666
        line 14951: 675
        line 14952: 687
        line 14953: 695
        line 14954: 705
        line 14958: 719
        line 14961: 734
        line 14963: 741
        line 14964: 750
        line 14965: 762
        line 14966: 770
        line 14967: 780
        line 14971: 794
        line 14974: 809
        line 14976: 816
        line 14977: 828
        line 14978: 836
        line 14979: 846
        line 14981: 860
        line 14983: 867
        line 14984: 879
        line 14985: 887
        line 14986: 897
        line 14988: 911
        line 14990: 918
        line 14991: 930
        line 14992: 938
        line 14993: 948
        line 14995: 962
        line 14997: 969
        line 14998: 981
        line 14999: 990
        line 15000: 1001
        line 15002: 1016
        line 15004: 1023
        line 15005: 1035
        line 15006: 1043
        line 15007: 1053
        line 15009: 1067
        line 15011: 1074
        line 15012: 1086
        line 15013: 1095
        line 15014: 1106
        line 15016: 1121
        line 15018: 1128
        line 15019: 1140
        line 15020: 1149
        line 15021: 1160
        line 15023: 1175
        line 15025: 1182
        line 15026: 1194
        line 15027: 1203
        line 15028: 1214
        line 15030: 1229
        line 15032: 1236
        line 15034: 1251
        line 15036: 1258
        line 15038: 1273
        line 15040: 1280
        line 15044: 1295
        line 14886: 1305
        line 14885: 1314
        line 15050: 1324
        line 15051: 1340
        line 15055: 1348
        line 15056: 1352

  void worldInit2();
    descriptor: ()V
    flags: (0x0000)
    Code:
      stack=3, locals=1, args_size=1
         0: aload_0
         1: getfield      #4                  // Field co_j:LCharacterObject;
         4: iconst_0
         5: putfield      #33                 // Field CharacterObject.vx:I
         8: aload_0
         9: getfield      #4                  // Field co_j:LCharacterObject;
        12: iconst_0
        13: putfield      #34                 // Field CharacterObject.vy:I
        16: aload_0
        17: getfield      #4                  // Field co_j:LCharacterObject;
        20: iconst_1
        21: putfield      #35                 // Field CharacterObject.muki:I
        24: aload_0
        25: getfield      #4                  // Field co_j:LCharacterObject;
        28: iconst_0
        29: putfield      #36                 // Field CharacterObject.ac:I
        32: aload_0
        33: getfield      #26                 // Field mp:LMainProgram;
        36: iconst_2
        37: putfield      #37                 // Field MainProgram.tr1_c:I
        40: aload_0
        41: sipush        200
        44: putfield      #18                 // Field mp_mode:I
        47: aload_0
        48: bipush        12
        50: putfield      #52                 // Field cc_hankei:I
        53: aload_0
        54: iconst_0
        55: putfield      #27                 // Field stage_kcID:I
        58: aload_0
        59: iconst_0
        60: putfield      #28                 // Field door_koID:I
        63: aload_0
        64: iconst_m1
        65: putfield      #38                 // Field shop_kattaitem:I
        68: aload_0
        69: iconst_0
        70: putfield      #30                 // Field door_score_open:I
        73: aload_0
        74: getfield      #13                 // Field ie_c:[I
        77: bipush        9
        79: iaload
        80: bipush        100
        82: if_icmpne     116
        85: aload_0
        86: getfield      #26                 // Field mp:LMainProgram;
        89: getfield      #53                 // Field MainProgram.score:I
        92: aload_0
        93: getfield      #26                 // Field mp:LMainProgram;
        96: getfield      #54                 // Field MainProgram.door_score:I
        99: if_icmplt     116
       102: aload_0
       103: getfield      #13                 // Field ie_c:[I
       106: bipush        9
       108: bipush        50
       110: iastore
       111: aload_0
       112: iconst_1
       113: putfield      #30                 // Field door_score_open:I
       116: aload_0
       117: getfield      #25                 // Field km:LKeyboardMenu;
       120: invokevirtual #39                 // Method KeyboardMenu.initAll:()V
       123: aload_0
       124: getfield      #25                 // Field km:LKeyboardMenu;
       127: bipush        100
       129: putfield      #40                 // Field KeyboardMenu.mode:I
       132: aload_0
       133: invokevirtual #51                 // Method drawOs2:()V
       136: return
      LineNumberTable:
        line 15064: 0
        line 15065: 8
        line 15066: 16
        line 15067: 24
        line 15068: 32
        line 15070: 40
        line 15071: 47
        line 15072: 53
        line 15073: 58
        line 15076: 63
        line 15079: 68
        line 15080: 73
        line 15082: 102
        line 15084: 111
        line 15088: 116
        line 15089: 123
        line 15092: 132
        line 15093: 136

  void worldInit3();
    descriptor: ()V
    flags: (0x0000)
    Code:
      stack=3, locals=4, args_size=1
         0: aload_0
         1: aload_0
         2: invokevirtual #55                 // Method checkStage:()I
         5: putfield      #27                 // Field stage_kcID:I
         8: aload_0
         9: getfield      #12                 // Field stage_cf:[Z
        12: aload_0
        13: getfield      #27                 // Field stage_kcID:I
        16: iconst_1
        17: isub
        18: iconst_1
        19: bastore
        20: aload_0
        21: getfield      #9                  // Field stage_c:[I
        24: aload_0
        25: getfield      #27                 // Field stage_kcID:I
        28: iconst_1
        29: isub
        30: bipush        50
        32: iastore
        33: iconst_0
        34: istore_1
        35: iconst_0
        36: istore_3
        37: goto          56
        40: aload_0
        41: getfield      #12                 // Field stage_cf:[Z
        44: iload_3
        45: baload
        46: iconst_1
        47: if_icmpne     53
        50: iinc          1, 1
        53: iinc          3, 1
        56: iload_3
        57: iconst_2
        58: if_icmple     40
        61: aload_0
        62: iconst_0
        63: putfield      #28                 // Field door_koID:I
        66: iload_1
        67: iconst_1
        68: if_icmplt     99
        71: aload_0
        72: getfield      #13                 // Field ie_c:[I
        75: iload_1
        76: iconst_1
        77: isub
        78: iaload
        79: bipush        100
        81: if_icmpne     99
        84: aload_0
        85: getfield      #13                 // Field ie_c:[I
        88: iload_1
        89: iconst_1
        90: isub
        91: bipush        50
        93: iastore
        94: aload_0
        95: iload_1
        96: putfield      #28                 // Field door_koID:I
        99: aload_0
       100: iconst_0
       101: putfield      #30                 // Field door_score_open:I
       104: aload_0
       105: getfield      #13                 // Field ie_c:[I
       108: bipush        9
       110: iaload
       111: bipush        100
       113: if_icmpne     147
       116: aload_0
       117: getfield      #26                 // Field mp:LMainProgram;
       120: getfield      #53                 // Field MainProgram.score:I
       123: aload_0
       124: getfield      #26                 // Field mp:LMainProgram;
       127: getfield      #54                 // Field MainProgram.door_score:I
       130: if_icmplt     147
       133: aload_0
       134: getfield      #13                 // Field ie_c:[I
       137: bipush        9
       139: bipush        50
       141: iastore
       142: aload_0
       143: iconst_1
       144: putfield      #30                 // Field door_score_open:I
       147: aload_0
       148: getfield      #4                  // Field co_j:LCharacterObject;
       151: iconst_0
       152: putfield      #33                 // Field CharacterObject.vx:I
       155: aload_0
       156: getfield      #4                  // Field co_j:LCharacterObject;
       159: iconst_0
       160: putfield      #34                 // Field CharacterObject.vy:I
       163: aload_0
       164: getfield      #4                  // Field co_j:LCharacterObject;
       167: iconst_1
       168: putfield      #35                 // Field CharacterObject.muki:I
       171: aload_0
       172: getfield      #4                  // Field co_j:LCharacterObject;
       175: iconst_0
       176: putfield      #36                 // Field CharacterObject.ac:I
       179: aload_0
       180: getfield      #26                 // Field mp:LMainProgram;
       183: iconst_2
       184: putfield      #37                 // Field MainProgram.tr1_c:I
       187: aload_0
       188: getfield      #4                  // Field co_j:LCharacterObject;
       191: iconst_0
       192: putfield      #56                 // Field CharacterObject.pt:I
       195: aload_0
       196: iconst_m1
       197: putfield      #38                 // Field shop_kattaitem:I
       200: aload_0
       201: sipush        200
       204: putfield      #18                 // Field mp_mode:I
       207: aload_0
       208: bipush        12
       210: putfield      #52                 // Field cc_hankei:I
       213: aload_0
       214: getfield      #25                 // Field km:LKeyboardMenu;
       217: invokevirtual #39                 // Method KeyboardMenu.initAll:()V
       220: aload_0
       221: getfield      #25                 // Field km:LKeyboardMenu;
       224: bipush        100
       226: putfield      #40                 // Field KeyboardMenu.mode:I
       229: aload_0
       230: invokevirtual #51                 // Method drawOs2:()V
       233: return
      LineNumberTable:
        line 15113: 0
        line 15114: 8
        line 15115: 20
        line 15118: 33
        line 15119: 35
        line 15120: 40
        line 15121: 50
        line 15119: 53
        line 15124: 61
        line 15125: 66
        line 15126: 71
        line 15128: 84
        line 15130: 94
        line 15135: 99
        line 15136: 104
        line 15138: 133
        line 15140: 142
        line 15144: 147
        line 15145: 155
        line 15146: 163
        line 15147: 171
        line 15148: 179
        line 15149: 187
        line 15152: 195
        line 15154: 200
        line 15155: 207
        line 15158: 213
        line 15159: 220
        line 15162: 229
        line 15163: 233

  void drawOs2();
    descriptor: ()V
    flags: (0x0000)
    Code:
      stack=6, locals=6, args_size=1
         0: aload_0
         1: getfield      #23                 // Field gg:LGameGraphics;
         4: new           #57                 // class java/awt/Color
         7: dup
         8: iconst_0
         9: bipush        127
        11: iconst_0
        12: invokespecial #58                 // Method java/awt/Color."<init>":(III)V
        15: invokevirtual #59                 // Method GameGraphics.setBackcolor:(Ljava/awt/Color;)V
        18: aload_0
        19: getfield      #23                 // Field gg:LGameGraphics;
        22: invokevirtual #60                 // Method GameGraphics.fill2:()V
        25: aload_0
        26: getfield      #23                 // Field gg:LGameGraphics;
        29: getfield      #61                 // Field GameGraphics.os2_g:Ljava/awt/Graphics;
        32: aload_0
        33: getfield      #23                 // Field gg:LGameGraphics;
        36: getfield      #62                 // Field GameGraphics.li:[Ljava/awt/Image;
        39: iconst_3
        40: aaload
        41: iconst_0
        42: iconst_0
        43: aload_0
        44: getfield      #23                 // Field gg:LGameGraphics;
        47: getfield      #41                 // Field GameGraphics.ap:Ljava/applet/Applet;
        50: invokevirtual #63                 // Method java/awt/Graphics.drawImage:(Ljava/awt/Image;IILjava/awt/image/ImageObserver;)Z
        53: pop
        54: iconst_0
        55: istore        5
        57: goto          223
        60: iconst_0
        61: istore        4
        63: goto          213
        66: aload_0
        67: getfield      #8                  // Field map_bg:[[I
        70: iload         4
        72: aaload
        73: iload         5
        75: iaload
        76: istore_2
        77: iload_2
        78: sipush        221
        81: if_icmpne     145
        84: aload_0
        85: getfield      #23                 // Field gg:LGameGraphics;
        88: iload         4
        90: bipush        32
        92: imul
        93: bipush        16
        95: iadd
        96: iload         5
        98: bipush        32
       100: imul
       101: bipush        24
       103: iadd
       104: bipush        16
       106: isub
       107: sipush        221
       110: invokevirtual #64                 // Method GameGraphics.drawPT2:(III)V
       113: aload_0
       114: getfield      #23                 // Field gg:LGameGraphics;
       117: iload         4
       119: bipush        32
       121: imul
       122: bipush        16
       124: iadd
       125: iload         5
       127: bipush        32
       129: imul
       130: bipush        24
       132: iadd
       133: bipush        16
       135: iadd
       136: sipush        221
       139: invokevirtual #64                 // Method GameGraphics.drawPT2:(III)V
       142: goto          210
       145: iload_2
       146: sipush        222
       149: if_icmpne     210
       152: aload_0
       153: getfield      #23                 // Field gg:LGameGraphics;
       156: iload         4
       158: bipush        32
       160: imul
       161: bipush        16
       163: iadd
       164: bipush        16
       166: isub
       167: iload         5
       169: bipush        32
       171: imul
       172: bipush        24
       174: iadd
       175: sipush        222
       178: invokevirtual #64                 // Method GameGraphics.drawPT2:(III)V
       181: aload_0
       182: getfield      #23                 // Field gg:LGameGraphics;
       185: iload         4
       187: bipush        32
       189: imul
       190: bipush        16
       192: iadd
       193: bipush        16
       195: iadd
       196: iload         5
       198: bipush        32
       200: imul
       201: bipush        24
       203: iadd
       204: sipush        222
       207: invokevirtual #64                 // Method GameGraphics.drawPT2:(III)V
       210: iinc          4, 1
       213: iload         4
       215: bipush        14
       217: if_icmple     66
       220: iinc          5, 1
       223: iload         5
       225: bipush        8
       227: if_icmple     60
       230: iconst_0
       231: istore        5
       233: goto          499
       236: iconst_0
       237: istore        4
       239: goto          489
       242: aload_0
       243: getfield      #8                  // Field map_bg:[[I
       246: iload         4
       248: aaload
       249: iload         5
       251: iaload
       252: istore_2
       253: iload_2
       254: bipush        61
       256: if_icmpeq     486
       259: iload_2
       260: bipush        62
       262: if_icmpeq     486
       265: iload_2
       266: sipush        256
       269: if_icmpeq     486
       272: iload_2
       273: sipush        216
       276: if_icmplt     316
       279: iload_2
       280: sipush        219
       283: if_icmpgt     316
       286: aload_0
       287: getfield      #23                 // Field gg:LGameGraphics;
       290: iload         4
       292: bipush        32
       294: imul
       295: bipush        16
       297: iadd
       298: iload         5
       300: bipush        32
       302: imul
       303: bipush        24
       305: iadd
       306: bipush        7
       308: isub
       309: iload_2
       310: invokevirtual #64                 // Method GameGraphics.drawPT2:(III)V
       313: goto          486
       316: iload_2
       317: sipush        206
       320: if_icmplt     360
       323: iload_2
       324: sipush        209
       327: if_icmpgt     360
       330: aload_0
       331: getfield      #23                 // Field gg:LGameGraphics;
       334: iload         4
       336: bipush        32
       338: imul
       339: bipush        16
       341: iadd
       342: iload         5
       344: bipush        32
       346: imul
       347: bipush        24
       349: iadd
       350: bipush        7
       352: isub
       353: iload_2
       354: invokevirtual #64                 // Method GameGraphics.drawPT2:(III)V
       357: goto          486
       360: iload_2
       361: sipush        212
       364: if_icmplt     462
       367: iload_2
       368: sipush        215
       371: if_icmpgt     462
       374: aload_0
       375: getfield      #23                 // Field gg:LGameGraphics;
       378: iload         4
       380: bipush        32
       382: imul
       383: bipush        16
       385: iadd
       386: bipush        16
       388: isub
       389: iload         5
       391: bipush        32
       393: imul
       394: bipush        24
       396: iadd
       397: sipush        222
       400: invokevirtual #64                 // Method GameGraphics.drawPT2:(III)V
       403: aload_0
       404: getfield      #23                 // Field gg:LGameGraphics;
       407: iload         4
       409: bipush        32
       411: imul
       412: bipush        16
       414: iadd
       415: bipush        16
       417: iadd
       418: iload         5
       420: bipush        32
       422: imul
       423: bipush        24
       425: iadd
       426: sipush        222
       429: invokevirtual #64                 // Method GameGraphics.drawPT2:(III)V
       432: aload_0
       433: getfield      #23                 // Field gg:LGameGraphics;
       436: iload         4
       438: bipush        32
       440: imul
       441: bipush        16
       443: iadd
       444: iload         5
       446: bipush        32
       448: imul
       449: bipush        24
       451: iadd
       452: bipush        7
       454: isub
       455: iload_2
       456: invokevirtual #64                 // Method GameGraphics.drawPT2:(III)V
       459: goto          486
       462: aload_0
       463: getfield      #23                 // Field gg:LGameGraphics;
       466: iload         4
       468: bipush        32
       470: imul
       471: bipush        16
       473: iadd
       474: iload         5
       476: bipush        32
       478: imul
       479: bipush        24
       481: iadd
       482: iload_2
       483: invokevirtual #64                 // Method GameGraphics.drawPT2:(III)V
       486: iinc          4, 1
       489: iload         4
       491: bipush        14
       493: if_icmple     242
       496: iinc          5, 1
       499: iload         5
       501: bipush        8
       503: if_icmple     236
       506: return
      LineNumberTable:
        line 15173: 0
        line 15176: 18
        line 15179: 25
        line 15183: 54
        line 15184: 60
        line 15185: 66
        line 15186: 77
        line 15188: 84
        line 15189: 113
        line 15191: 145
        line 15193: 152
        line 15194: 181
        line 15184: 210
        line 15183: 220
        line 15200: 230
        line 15201: 236
        line 15202: 242
        line 15203: 253
        line 15205: 272
        line 15207: 286
        line 15209: 316
        line 15211: 330
        line 15213: 360
        line 15217: 374
        line 15218: 403
        line 15220: 432
        line 15224: 462
        line 15201: 486
        line 15200: 496
        line 15229: 506

  void drawMap();
    descriptor: ()V
    flags: (0x0000)
    Code:
      stack=5, locals=1, args_size=1
         0: aload_0
         1: getfield      #23                 // Field gg:LGameGraphics;
         4: getfield      #65                 // Field GameGraphics.os_g:Ljava/awt/Graphics;
         7: aload_0
         8: getfield      #23                 // Field gg:LGameGraphics;
        11: getfield      #66                 // Field GameGraphics.os2_img:Ljava/awt/Image;
        14: iconst_0
        15: iconst_0
        16: aload_0
        17: getfield      #23                 // Field gg:LGameGraphics;
        20: getfield      #41                 // Field GameGraphics.ap:Ljava/applet/Applet;
        23: invokevirtual #63                 // Method java/awt/Graphics.drawImage:(Ljava/awt/Image;IILjava/awt/image/ImageObserver;)Z
        26: pop
        27: return
      LineNumberTable:
        line 15236: 0
        line 15237: 27

  int getBGZ(int, int);
    descriptor: (II)I
    flags: (0x0000)
    Code:
      stack=2, locals=5, args_size=3
         0: iload_1
         1: iflt          22
         4: iload_1
         5: sipush        479
         8: if_icmpgt     22
        11: iload_2
        12: iflt          22
        15: iload_2
        16: sipush        287
        19: if_icmple     24
        22: iconst_0
        23: ireturn
        24: iload_1
        25: bipush        32
        27: idiv
        28: istore_3
        29: iload_2
        30: bipush        32
        32: idiv
        33: istore        4
        35: aload_0
        36: getfield      #8                  // Field map_bg:[[I
        39: iload_3
        40: aaload
        41: iload         4
        43: iaload
        44: ireturn
      LineNumberTable:
        line 15246: 0
        line 15247: 22
        line 15250: 24
        line 15251: 29
        line 15252: 35

  int checkStage();
    descriptor: ()I
    flags: (0x0000)
    Code:
      stack=3, locals=4, args_size=1
         0: iconst_m1
         1: istore_3
         2: iconst_0
         3: istore_1
         4: goto          60
         7: aload_0
         8: getfield      #9                  // Field stage_c:[I
        11: iload_1
        12: iaload
        13: bipush        100
        15: if_icmpne     57
        18: aload_0
        19: getfield      #4                  // Field co_j:LCharacterObject;
        22: getfield      #31                 // Field CharacterObject.x:I
        25: aload_0
        26: getfield      #10                 // Field stage_x:[I
        29: iload_1
        30: iaload
        31: if_icmpne     57
        34: aload_0
        35: getfield      #4                  // Field co_j:LCharacterObject;
        38: getfield      #32                 // Field CharacterObject.y:I
        41: aload_0
        42: getfield      #11                 // Field stage_y:[I
        45: iload_1
        46: iaload
        47: if_icmpne     57
        50: iload_1
        51: iconst_1
        52: iadd
        53: istore_3
        54: goto          66
        57: iinc          1, 1
        60: iload_1
        61: bipush        9
        63: if_icmple     7
        66: iload_3
        67: ireturn
      LineNumberTable:
        line 15259: 0
        line 15262: 2
        line 15263: 7
        line 15265: 50
        line 15266: 54
        line 15262: 57
        line 15270: 66

  void mainProgram();
    descriptor: ()V
    flags: (0x0000)
    Code:
      stack=6, locals=11, args_size=1
         0: aload_0
         1: getfield      #24                 // Field gk:LGameKey;
         4: getfield      #67                 // Field GameKey.tr1_f:Z
         7: iconst_1
         8: if_icmpne     38
        11: aload_0
        12: getfield      #26                 // Field mp:LMainProgram;
        15: getfield      #37                 // Field MainProgram.tr1_c:I
        18: iconst_2
        19: if_icmpge     46
        22: aload_0
        23: getfield      #26                 // Field mp:LMainProgram;
        26: dup
        27: getfield      #37                 // Field MainProgram.tr1_c:I
        30: iconst_1
        31: iadd
        32: putfield      #37                 // Field MainProgram.tr1_c:I
        35: goto          46
        38: aload_0
        39: getfield      #26                 // Field mp:LMainProgram;
        42: iconst_0
        43: putfield      #37                 // Field MainProgram.tr1_c:I
        46: aload_0
        47: getfield      #18                 // Field mp_mode:I
        50: ifne          1821
        53: aload_0
        54: getfield      #25                 // Field km:LKeyboardMenu;
        57: getfield      #40                 // Field KeyboardMenu.mode:I
        60: bipush        100
        62: if_icmpne     72
        65: aload_0
        66: invokevirtual #68                 // Method jMove:()V
        69: goto          1814
        72: aload_0
        73: getfield      #25                 // Field km:LKeyboardMenu;
        76: getfield      #40                 // Field KeyboardMenu.mode:I
        79: sipush        200
        82: if_icmpne     200
        85: aload_0
        86: getfield      #25                 // Field km:LKeyboardMenu;
        89: getfield      #69                 // Field KeyboardMenu.cancel_c:I
        92: iconst_1
        93: if_icmpne     124
        96: aload_0
        97: getfield      #25                 // Field km:LKeyboardMenu;
       100: iconst_3
       101: invokevirtual #70                 // Method KeyboardMenu.off:(I)V
       104: aload_0
       105: getfield      #25                 // Field km:LKeyboardMenu;
       108: iconst_4
       109: invokevirtual #70                 // Method KeyboardMenu.off:(I)V
       112: aload_0
       113: getfield      #25                 // Field km:LKeyboardMenu;
       116: bipush        100
       118: putfield      #40                 // Field KeyboardMenu.mode:I
       121: goto          1814
       124: aload_0
       125: getfield      #25                 // Field km:LKeyboardMenu;
       128: getfield      #71                 // Field KeyboardMenu.kettei_c:I
       131: iconst_1
       132: if_icmpne     1814
       135: aload_0
       136: getfield      #25                 // Field km:LKeyboardMenu;
       139: iconst_3
       140: invokevirtual #72                 // Method KeyboardMenu.init1:(I)V
       143: aload_0
       144: getfield      #25                 // Field km:LKeyboardMenu;
       147: iconst_3
       148: aload_0
       149: getfield      #26                 // Field mp:LMainProgram;
       152: getfield      #73                 // Field MainProgram.mes1_name:Ljava/lang/String;
       155: invokevirtual #74                 // Method KeyboardMenu.setMessage:(ILjava/lang/String;)V
       158: aload_0
       159: getfield      #26                 // Field mp:LMainProgram;
       162: iconst_3
       163: iconst_2
       164: iconst_3
       165: invokevirtual #75                 // Method MainProgram.addSerifu:(III)V
       168: aload_0
       169: getfield      #25                 // Field km:LKeyboardMenu;
       172: iconst_3
       173: bipush        120
       175: sipush        150
       178: sipush        272
       181: getstatic     #76                 // Field java/awt/Color.cyan:Ljava/awt/Color;
       184: invokevirtual #77                 // Method KeyboardMenu.activeSerifu:(IIIILjava/awt/Color;)V
       187: aload_0
       188: getfield      #25                 // Field km:LKeyboardMenu;
       191: sipush        210
       194: putfield      #40                 // Field KeyboardMenu.mode:I
       197: goto          1814
       200: aload_0
       201: getfield      #25                 // Field km:LKeyboardMenu;
       204: getfield      #40                 // Field KeyboardMenu.mode:I
       207: sipush        210
       210: if_icmpne     263
       213: aload_0
       214: getfield      #25                 // Field km:LKeyboardMenu;
       217: getfield      #69                 // Field KeyboardMenu.cancel_c:I
       220: iconst_1
       221: if_icmpeq     235
       224: aload_0
       225: getfield      #25                 // Field km:LKeyboardMenu;
       228: getfield      #71                 // Field KeyboardMenu.kettei_c:I
       231: iconst_1
       232: if_icmpne     1814
       235: aload_0
       236: getfield      #25                 // Field km:LKeyboardMenu;
       239: iconst_3
       240: invokevirtual #70                 // Method KeyboardMenu.off:(I)V
       243: aload_0
       244: getfield      #25                 // Field km:LKeyboardMenu;
       247: iconst_4
       248: invokevirtual #70                 // Method KeyboardMenu.off:(I)V
       251: aload_0
       252: getfield      #25                 // Field km:LKeyboardMenu;
       255: bipush        100
       257: putfield      #40                 // Field KeyboardMenu.mode:I
       260: goto          1814
       263: aload_0
       264: getfield      #25                 // Field km:LKeyboardMenu;
       267: getfield      #40                 // Field KeyboardMenu.mode:I
       270: sipush        300
       273: if_icmpne     391
       276: aload_0
       277: getfield      #25                 // Field km:LKeyboardMenu;
       280: getfield      #69                 // Field KeyboardMenu.cancel_c:I
       283: iconst_1
       284: if_icmpne     315
       287: aload_0
       288: getfield      #25                 // Field km:LKeyboardMenu;
       291: iconst_3
       292: invokevirtual #70                 // Method KeyboardMenu.off:(I)V
       295: aload_0
       296: getfield      #25                 // Field km:LKeyboardMenu;
       299: iconst_4
       300: invokevirtual #70                 // Method KeyboardMenu.off:(I)V
       303: aload_0
       304: getfield      #25                 // Field km:LKeyboardMenu;
       307: bipush        100
       309: putfield      #40                 // Field KeyboardMenu.mode:I
       312: goto          1814
       315: aload_0
       316: getfield      #25                 // Field km:LKeyboardMenu;
       319: getfield      #71                 // Field KeyboardMenu.kettei_c:I
       322: iconst_1
       323: if_icmpne     1814
       326: aload_0
       327: getfield      #25                 // Field km:LKeyboardMenu;
       330: iconst_3
       331: invokevirtual #72                 // Method KeyboardMenu.init1:(I)V
       334: aload_0
       335: getfield      #25                 // Field km:LKeyboardMenu;
       338: iconst_3
       339: aload_0
       340: getfield      #26                 // Field mp:LMainProgram;
       343: getfield      #78                 // Field MainProgram.mes2_name:Ljava/lang/String;
       346: invokevirtual #74                 // Method KeyboardMenu.setMessage:(ILjava/lang/String;)V
       349: aload_0
       350: getfield      #26                 // Field mp:LMainProgram;
       353: iconst_3
       354: iconst_4
       355: iconst_3
       356: invokevirtual #75                 // Method MainProgram.addSerifu:(III)V
       359: aload_0
       360: getfield      #25                 // Field km:LKeyboardMenu;
       363: iconst_3
       364: bipush        120
       366: sipush        150
       369: sipush        272
       372: getstatic     #76                 // Field java/awt/Color.cyan:Ljava/awt/Color;
       375: invokevirtual #77                 // Method KeyboardMenu.activeSerifu:(IIIILjava/awt/Color;)V
       378: aload_0
       379: getfield      #25                 // Field km:LKeyboardMenu;
       382: sipush        210
       385: putfield      #40                 // Field KeyboardMenu.mode:I
       388: goto          1814
       391: aload_0
       392: getfield      #25                 // Field km:LKeyboardMenu;
       395: getfield      #40                 // Field KeyboardMenu.mode:I
       398: sipush        400
       401: if_icmpne     695
       404: aload_0
       405: getfield      #25                 // Field km:LKeyboardMenu;
       408: getfield      #69                 // Field KeyboardMenu.cancel_c:I
       411: iconst_1
       412: if_icmpne     443
       415: aload_0
       416: getfield      #25                 // Field km:LKeyboardMenu;
       419: iconst_3
       420: invokevirtual #70                 // Method KeyboardMenu.off:(I)V
       423: aload_0
       424: getfield      #25                 // Field km:LKeyboardMenu;
       427: iconst_4
       428: invokevirtual #70                 // Method KeyboardMenu.off:(I)V
       431: aload_0
       432: getfield      #25                 // Field km:LKeyboardMenu;
       435: bipush        100
       437: putfield      #40                 // Field KeyboardMenu.mode:I
       440: goto          1814
       443: aload_0
       444: getfield      #25                 // Field km:LKeyboardMenu;
       447: getfield      #71                 // Field KeyboardMenu.kettei_c:I
       450: iconst_1
       451: if_icmpne     1814
       454: aload_0
       455: getfield      #25                 // Field km:LKeyboardMenu;
       458: iconst_3
       459: invokevirtual #70                 // Method KeyboardMenu.off:(I)V
       462: aload_0
       463: getfield      #25                 // Field km:LKeyboardMenu;
       466: iconst_0
       467: putfield      #79                 // Field KeyboardMenu.list_kazu:I
       470: aload_0
       471: getfield      #25                 // Field km:LKeyboardMenu;
       474: bipush        6
       476: invokevirtual #72                 // Method KeyboardMenu.init1:(I)V
       479: aload_0
       480: getfield      #25                 // Field km:LKeyboardMenu;
       483: bipush        6
       485: aload_0
       486: getfield      #23                 // Field gg:LGameGraphics;
       489: getfield      #41                 // Field GameGraphics.ap:Ljava/applet/Applet;
       492: ldc           #80                 // String shop_serifu1
       494: invokevirtual #48                 // Method java/applet/Applet.getParameter:(Ljava/lang/String;)Ljava/lang/String;
       497: invokevirtual #74                 // Method KeyboardMenu.setMessage:(ILjava/lang/String;)V
       500: iconst_0
       501: istore_1
       502: goto          579
       505: aload_0
       506: getfield      #26                 // Field mp:LMainProgram;
       509: getfield      #81                 // Field MainProgram.shop_item_teika:[I
       512: iload_1
       513: iaload
       514: ifgt          520
       517: goto          576
       520: aload_0
       521: getfield      #25                 // Field km:LKeyboardMenu;
       524: bipush        6
       526: aload_0
       527: getfield      #26                 // Field mp:LMainProgram;
       530: getfield      #82                 // Field MainProgram.shop_item_name:[Ljava/lang/String;
       533: iload_1
       534: aaload
       535: aload_0
       536: getfield      #26                 // Field mp:LMainProgram;
       539: getfield      #81                 // Field MainProgram.shop_item_teika:[I
       542: iload_1
       543: iaload
       544: invokevirtual #83                 // Method KeyboardMenu.addItem2:(ILjava/lang/String;I)V
       547: aload_0
       548: getfield      #25                 // Field km:LKeyboardMenu;
       551: getfield      #84                 // Field KeyboardMenu.list_IDlist:[I
       554: aload_0
       555: getfield      #25                 // Field km:LKeyboardMenu;
       558: getfield      #79                 // Field KeyboardMenu.list_kazu:I
       561: iload_1
       562: iastore
       563: aload_0
       564: getfield      #25                 // Field km:LKeyboardMenu;
       567: dup
       568: getfield      #79                 // Field KeyboardMenu.list_kazu:I
       571: iconst_1
       572: iadd
       573: putfield      #79                 // Field KeyboardMenu.list_kazu:I
       576: iinc          1, 1
       579: iload_1
       580: bipush        8
       582: if_icmple     505
       585: aload_0
       586: getfield      #25                 // Field km:LKeyboardMenu;
       589: getfield      #79                 // Field KeyboardMenu.list_kazu:I
       592: iconst_1
       593: if_icmplt     626
       596: aload_0
       597: getfield      #25                 // Field km:LKeyboardMenu;
       600: bipush        6
       602: sipush        296
       605: bipush        76
       607: sipush        184
       610: invokevirtual #85                 // Method KeyboardMenu.activeKaimono:(IIII)V
       613: aload_0
       614: getfield      #25                 // Field km:LKeyboardMenu;
       617: sipush        410
       620: putfield      #40                 // Field KeyboardMenu.mode:I
       623: goto          1814
       626: aload_0
       627: getfield      #25                 // Field km:LKeyboardMenu;
       630: bipush        6
       632: invokevirtual #72                 // Method KeyboardMenu.init1:(I)V
       635: aload_0
       636: getfield      #25                 // Field km:LKeyboardMenu;
       639: iconst_3
       640: invokevirtual #72                 // Method KeyboardMenu.init1:(I)V
       643: aload_0
       644: getfield      #25                 // Field km:LKeyboardMenu;
       647: iconst_3
       648: ldc           #86                 // String Error
       650: invokevirtual #74                 // Method KeyboardMenu.setMessage:(ILjava/lang/String;)V
       653: aload_0
       654: getfield      #25                 // Field km:LKeyboardMenu;
       657: iconst_3
       658: ldc           #87                 // String Please set any item on shop menu.
       660: invokevirtual #88                 // Method KeyboardMenu.addItem:(ILjava/lang/String;)V
       663: aload_0
       664: getfield      #25                 // Field km:LKeyboardMenu;
       667: iconst_3
       668: bipush        120
       670: sipush        150
       673: sipush        216
       676: getstatic     #89                 // Field java/awt/Color.red:Ljava/awt/Color;
       679: invokevirtual #77                 // Method KeyboardMenu.activeSerifu:(IIIILjava/awt/Color;)V
       682: aload_0
       683: getfield      #25                 // Field km:LKeyboardMenu;
       686: sipush        210
       689: putfield      #40                 // Field KeyboardMenu.mode:I
       692: goto          1814
       695: aload_0
       696: getfield      #25                 // Field km:LKeyboardMenu;
       699: getfield      #40                 // Field KeyboardMenu.mode:I
       702: sipush        410
       705: if_icmpne     924
       708: aload_0
       709: getfield      #25                 // Field km:LKeyboardMenu;
       712: getfield      #69                 // Field KeyboardMenu.cancel_c:I
       715: iconst_1
       716: if_icmpne     748
       719: aload_0
       720: getfield      #25                 // Field km:LKeyboardMenu;
       723: iconst_4
       724: invokevirtual #70                 // Method KeyboardMenu.off:(I)V
       727: aload_0
       728: getfield      #25                 // Field km:LKeyboardMenu;
       731: bipush        6
       733: invokevirtual #70                 // Method KeyboardMenu.off:(I)V
       736: aload_0
       737: getfield      #25                 // Field km:LKeyboardMenu;
       740: bipush        100
       742: putfield      #40                 // Field KeyboardMenu.mode:I
       745: goto          1814
       748: aload_0
       749: getfield      #25                 // Field km:LKeyboardMenu;
       752: getfield      #71                 // Field KeyboardMenu.kettei_c:I
       755: iconst_1
       756: if_icmpne     1814
       759: aload_0
       760: getfield      #25                 // Field km:LKeyboardMenu;
       763: aload_0
       764: getfield      #25                 // Field km:LKeyboardMenu;
       767: getfield      #84                 // Field KeyboardMenu.list_IDlist:[I
       770: aload_0
       771: getfield      #25                 // Field km:LKeyboardMenu;
       774: getfield      #90                 // Field KeyboardMenu.selectedIndex:[I
       777: bipush        6
       779: iaload
       780: iaload
       781: putfield      #91                 // Field KeyboardMenu.list_s:I
       784: aload_0
       785: getfield      #25                 // Field km:LKeyboardMenu;
       788: bipush        7
       790: invokevirtual #72                 // Method KeyboardMenu.init1:(I)V
       793: aload_0
       794: getfield      #25                 // Field km:LKeyboardMenu;
       797: bipush        7
       799: new           #42                 // class java/lang/StringBuffer
       802: dup
       803: invokespecial #43                 // Method java/lang/StringBuffer."<init>":()V
       806: aload_0
       807: getfield      #26                 // Field mp:LMainProgram;
       810: getfield      #82                 // Field MainProgram.shop_item_name:[Ljava/lang/String;
       813: aload_0
       814: getfield      #25                 // Field km:LKeyboardMenu;
       817: getfield      #91                 // Field KeyboardMenu.list_s:I
       820: aaload
       821: invokevirtual #45                 // Method java/lang/StringBuffer.append:(Ljava/lang/String;)Ljava/lang/StringBuffer;
       824: aload_0
       825: getfield      #23                 // Field gg:LGameGraphics;
       828: getfield      #41                 // Field GameGraphics.ap:Ljava/applet/Applet;
       831: ldc           #92                 // String shop_serifu2
       833: invokevirtual #48                 // Method java/applet/Applet.getParameter:(Ljava/lang/String;)Ljava/lang/String;
       836: invokevirtual #45                 // Method java/lang/StringBuffer.append:(Ljava/lang/String;)Ljava/lang/StringBuffer;
       839: invokevirtual #47                 // Method java/lang/StringBuffer.toString:()Ljava/lang/String;
       842: invokevirtual #74                 // Method KeyboardMenu.setMessage:(ILjava/lang/String;)V
       845: aload_0
       846: getfield      #25                 // Field km:LKeyboardMenu;
       849: bipush        7
       851: aload_0
       852: getfield      #23                 // Field gg:LGameGraphics;
       855: getfield      #41                 // Field GameGraphics.ap:Ljava/applet/Applet;
       858: ldc           #93                 // String shop_serifu3
       860: invokevirtual #48                 // Method java/applet/Applet.getParameter:(Ljava/lang/String;)Ljava/lang/String;
       863: invokevirtual #88                 // Method KeyboardMenu.addItem:(ILjava/lang/String;)V
       866: aload_0
       867: getfield      #25                 // Field km:LKeyboardMenu;
       870: bipush        7
       872: aload_0
       873: getfield      #23                 // Field gg:LGameGraphics;
       876: getfield      #41                 // Field GameGraphics.ap:Ljava/applet/Applet;
       879: ldc           #94                 // String shop_serifu4
       881: invokevirtual #48                 // Method java/applet/Applet.getParameter:(Ljava/lang/String;)Ljava/lang/String;
       884: invokevirtual #88                 // Method KeyboardMenu.addItem:(ILjava/lang/String;)V
       887: aload_0
       888: getfield      #25                 // Field km:LKeyboardMenu;
       891: bipush        7
       893: bipush        48
       895: sipush        150
       898: sipush        236
       901: aload_0
       902: getfield      #26                 // Field mp:LMainProgram;
       905: getfield      #95                 // Field MainProgram.shop_name:Ljava/lang/String;
       908: invokevirtual #96                 // Method KeyboardMenu.activeSerifutuki:(IIIILjava/lang/String;)V
       911: aload_0
       912: getfield      #25                 // Field km:LKeyboardMenu;
       915: sipush        420
       918: putfield      #40                 // Field KeyboardMenu.mode:I
       921: goto          1814
       924: aload_0
       925: getfield      #25                 // Field km:LKeyboardMenu;
       928: getfield      #40                 // Field KeyboardMenu.mode:I
       931: sipush        420
       934: if_icmpne     1264
       937: aload_0
       938: getfield      #25                 // Field km:LKeyboardMenu;
       941: getfield      #69                 // Field KeyboardMenu.cancel_c:I
       944: iconst_1
       945: if_icmpne     972
       948: aload_0
       949: getfield      #25                 // Field km:LKeyboardMenu;
       952: bipush        7
       954: bipush        6
       956: invokevirtual #97                 // Method KeyboardMenu.offActivewindow:(II)V
       959: aload_0
       960: getfield      #25                 // Field km:LKeyboardMenu;
       963: sipush        410
       966: putfield      #40                 // Field KeyboardMenu.mode:I
       969: goto          1814
       972: aload_0
       973: getfield      #25                 // Field km:LKeyboardMenu;
       976: getfield      #71                 // Field KeyboardMenu.kettei_c:I
       979: iconst_1
       980: if_icmpne     1814
       983: aload_0
       984: getfield      #25                 // Field km:LKeyboardMenu;
       987: getfield      #90                 // Field KeyboardMenu.selectedIndex:[I
       990: bipush        7
       992: iaload
       993: ifne          1226
       996: aload_0
       997: getfield      #26                 // Field mp:LMainProgram;
      1000: getfield      #53                 // Field MainProgram.score:I
      1003: aload_0
      1004: getfield      #26                 // Field mp:LMainProgram;
      1007: getfield      #81                 // Field MainProgram.shop_item_teika:[I
      1010: aload_0
      1011: getfield      #25                 // Field km:LKeyboardMenu;
      1014: getfield      #91                 // Field KeyboardMenu.list_s:I
      1017: iaload
      1018: if_icmplt     1169
      1021: aload_0
      1022: getfield      #25                 // Field km:LKeyboardMenu;
      1025: iconst_3
      1026: invokevirtual #72                 // Method KeyboardMenu.init1:(I)V
      1029: aload_0
      1030: getfield      #25                 // Field km:LKeyboardMenu;
      1033: iconst_3
      1034: new           #42                 // class java/lang/StringBuffer
      1037: dup
      1038: invokespecial #43                 // Method java/lang/StringBuffer."<init>":()V
      1041: aload_0
      1042: getfield      #26                 // Field mp:LMainProgram;
      1045: getfield      #82                 // Field MainProgram.shop_item_name:[Ljava/lang/String;
      1048: aload_0
      1049: getfield      #25                 // Field km:LKeyboardMenu;
      1052: getfield      #91                 // Field KeyboardMenu.list_s:I
      1055: aaload
      1056: invokevirtual #45                 // Method java/lang/StringBuffer.append:(Ljava/lang/String;)Ljava/lang/StringBuffer;
      1059: aload_0
      1060: getfield      #23                 // Field gg:LGameGraphics;
      1063: getfield      #41                 // Field GameGraphics.ap:Ljava/applet/Applet;
      1066: ldc           #98                 // String shop_serifu5
      1068: invokevirtual #48                 // Method java/applet/Applet.getParameter:(Ljava/lang/String;)Ljava/lang/String;
      1071: invokevirtual #45                 // Method java/lang/StringBuffer.append:(Ljava/lang/String;)Ljava/lang/StringBuffer;
      1074: invokevirtual #47                 // Method java/lang/StringBuffer.toString:()Ljava/lang/String;
      1077: invokevirtual #88                 // Method KeyboardMenu.addItem:(ILjava/lang/String;)V
      1080: aload_0
      1081: getfield      #25                 // Field km:LKeyboardMenu;
      1084: iconst_3
      1085: bipush        48
      1087: sipush        240
      1090: sipush        236
      1093: invokevirtual #99                 // Method KeyboardMenu.activeIchigyou:(IIII)V
      1096: aload_0
      1097: getfield      #26                 // Field mp:LMainProgram;
      1100: dup
      1101: getfield      #53                 // Field MainProgram.score:I
      1104: aload_0
      1105: getfield      #26                 // Field mp:LMainProgram;
      1108: getfield      #81                 // Field MainProgram.shop_item_teika:[I
      1111: aload_0
      1112: getfield      #25                 // Field km:LKeyboardMenu;
      1115: getfield      #91                 // Field KeyboardMenu.list_s:I
      1118: iaload
      1119: isub
      1120: putfield      #53                 // Field MainProgram.score:I
      1123: aload_0
      1124: aload_0
      1125: getfield      #25                 // Field km:LKeyboardMenu;
      1128: getfield      #91                 // Field KeyboardMenu.list_s:I
      1131: putfield      #38                 // Field shop_kattaitem:I
      1134: aload_0
      1135: getfield      #38                 // Field shop_kattaitem:I
      1138: bipush        7
      1140: if_icmpne     1156
      1143: aload_0
      1144: getfield      #26                 // Field mp:LMainProgram;
      1147: dup
      1148: getfield      #100                // Field MainProgram.j_left:I
      1151: iconst_1
      1152: iadd
      1153: putfield      #100                // Field MainProgram.j_left:I
      1156: aload_0
      1157: getfield      #25                 // Field km:LKeyboardMenu;
      1160: sipush        430
      1163: putfield      #40                 // Field KeyboardMenu.mode:I
      1166: goto          1814
      1169: aload_0
      1170: getfield      #25                 // Field km:LKeyboardMenu;
      1173: iconst_3
      1174: invokevirtual #72                 // Method KeyboardMenu.init1:(I)V
      1177: aload_0
      1178: getfield      #25                 // Field km:LKeyboardMenu;
      1181: iconst_3
      1182: aload_0
      1183: getfield      #23                 // Field gg:LGameGraphics;
      1186: getfield      #41                 // Field GameGraphics.ap:Ljava/applet/Applet;
      1189: ldc           #101                // String shop_serifu6
      1191: invokevirtual #48                 // Method java/applet/Applet.getParameter:(Ljava/lang/String;)Ljava/lang/String;
      1194: invokevirtual #88                 // Method KeyboardMenu.addItem:(ILjava/lang/String;)V
      1197: aload_0
      1198: getfield      #25                 // Field km:LKeyboardMenu;
      1201: iconst_3
      1202: bipush        48
      1204: sipush        240
      1207: sipush        236
      1210: invokevirtual #99                 // Method KeyboardMenu.activeIchigyou:(IIII)V
      1213: aload_0
      1214: getfield      #25                 // Field km:LKeyboardMenu;
      1217: sipush        430
      1220: putfield      #40                 // Field KeyboardMenu.mode:I
      1223: goto          1814
      1226: aload_0
      1227: getfield      #25                 // Field km:LKeyboardMenu;
      1230: iconst_4
      1231: invokevirtual #70                 // Method KeyboardMenu.off:(I)V
      1234: aload_0
      1235: getfield      #25                 // Field km:LKeyboardMenu;
      1238: bipush        6
      1240: invokevirtual #70                 // Method KeyboardMenu.off:(I)V
      1243: aload_0
      1244: getfield      #25                 // Field km:LKeyboardMenu;
      1247: bipush        7
      1249: invokevirtual #70                 // Method KeyboardMenu.off:(I)V
      1252: aload_0
      1253: getfield      #25                 // Field km:LKeyboardMenu;
      1256: bipush        100
      1258: putfield      #40                 // Field KeyboardMenu.mode:I
      1261: goto          1814
      1264: aload_0
      1265: getfield      #25                 // Field km:LKeyboardMenu;
      1268: getfield      #40                 // Field KeyboardMenu.mode:I
      1271: sipush        430
      1274: if_icmpne     1345
      1277: aload_0
      1278: getfield      #25                 // Field km:LKeyboardMenu;
      1281: getfield      #69                 // Field KeyboardMenu.cancel_c:I
      1284: iconst_1
      1285: if_icmpeq     1299
      1288: aload_0
      1289: getfield      #25                 // Field km:LKeyboardMenu;
      1292: getfield      #71                 // Field KeyboardMenu.kettei_c:I
      1295: iconst_1
      1296: if_icmpne     1814
      1299: aload_0
      1300: getfield      #25                 // Field km:LKeyboardMenu;
      1303: iconst_3
      1304: invokevirtual #70                 // Method KeyboardMenu.off:(I)V
      1307: aload_0
      1308: getfield      #25                 // Field km:LKeyboardMenu;
      1311: iconst_4
      1312: invokevirtual #70                 // Method KeyboardMenu.off:(I)V
      1315: aload_0
      1316: getfield      #25                 // Field km:LKeyboardMenu;
      1319: bipush        6
      1321: invokevirtual #70                 // Method KeyboardMenu.off:(I)V
      1324: aload_0
      1325: getfield      #25                 // Field km:LKeyboardMenu;
      1328: bipush        7
      1330: invokevirtual #70                 // Method KeyboardMenu.off:(I)V
      1333: aload_0
      1334: getfield      #25                 // Field km:LKeyboardMenu;
      1337: bipush        100
      1339: putfield      #40                 // Field KeyboardMenu.mode:I
      1342: goto          1814
      1345: aload_0
      1346: getfield      #25                 // Field km:LKeyboardMenu;
      1349: getfield      #40                 // Field KeyboardMenu.mode:I
      1352: sipush        500
      1355: if_icmpne     1540
      1358: aload_0
      1359: getfield      #25                 // Field km:LKeyboardMenu;
      1362: getfield      #69                 // Field KeyboardMenu.cancel_c:I
      1365: iconst_1
      1366: if_icmpne     1397
      1369: aload_0
      1370: getfield      #25                 // Field km:LKeyboardMenu;
      1373: iconst_4
      1374: invokevirtual #70                 // Method KeyboardMenu.off:(I)V
      1377: aload_0
      1378: getfield      #25                 // Field km:LKeyboardMenu;
      1381: iconst_3
      1382: invokevirtual #70                 // Method KeyboardMenu.off:(I)V
      1385: aload_0
      1386: getfield      #25                 // Field km:LKeyboardMenu;
      1389: bipush        100
      1391: putfield      #40                 // Field KeyboardMenu.mode:I
      1394: goto          1814
      1397: aload_0
      1398: getfield      #25                 // Field km:LKeyboardMenu;
      1401: getfield      #71                 // Field KeyboardMenu.kettei_c:I
      1404: iconst_1
      1405: if_icmpne     1814
      1408: aload_0
      1409: getfield      #25                 // Field km:LKeyboardMenu;
      1412: iconst_3
      1413: invokevirtual #70                 // Method KeyboardMenu.off:(I)V
      1416: aload_0
      1417: getfield      #25                 // Field km:LKeyboardMenu;
      1420: iconst_2
      1421: invokevirtual #72                 // Method KeyboardMenu.init1:(I)V
      1424: aload_0
      1425: getfield      #25                 // Field km:LKeyboardMenu;
      1428: iconst_2
      1429: aload_0
      1430: getfield      #23                 // Field gg:LGameGraphics;
      1433: getfield      #41                 // Field GameGraphics.ap:Ljava/applet/Applet;
      1436: ldc           #102                // String setumei_menu1
      1438: invokevirtual #48                 // Method java/applet/Applet.getParameter:(Ljava/lang/String;)Ljava/lang/String;
      1441: invokevirtual #74                 // Method KeyboardMenu.setMessage:(ILjava/lang/String;)V
      1444: aload_0
      1445: getfield      #25                 // Field km:LKeyboardMenu;
      1448: iconst_2
      1449: aload_0
      1450: getfield      #23                 // Field gg:LGameGraphics;
      1453: getfield      #41                 // Field GameGraphics.ap:Ljava/applet/Applet;
      1456: ldc           #103                // String setumei_menu2
      1458: invokevirtual #48                 // Method java/applet/Applet.getParameter:(Ljava/lang/String;)Ljava/lang/String;
      1461: invokevirtual #88                 // Method KeyboardMenu.addItem:(ILjava/lang/String;)V
      1464: aload_0
      1465: getfield      #25                 // Field km:LKeyboardMenu;
      1468: iconst_2
      1469: aload_0
      1470: getfield      #23                 // Field gg:LGameGraphics;
      1473: getfield      #41                 // Field GameGraphics.ap:Ljava/applet/Applet;
      1476: ldc           #104                // String setumei_menu3
      1478: invokevirtual #48                 // Method java/applet/Applet.getParameter:(Ljava/lang/String;)Ljava/lang/String;
      1481: invokevirtual #88                 // Method KeyboardMenu.addItem:(ILjava/lang/String;)V
      1484: aload_0
      1485: getfield      #25                 // Field km:LKeyboardMenu;
      1488: iconst_2
      1489: aload_0
      1490: getfield      #23                 // Field gg:LGameGraphics;
      1493: getfield      #41                 // Field GameGraphics.ap:Ljava/applet/Applet;
      1496: ldc           #105                // String setumei_menu4
      1498: invokevirtual #48                 // Method java/applet/Applet.getParameter:(Ljava/lang/String;)Ljava/lang/String;
      1501: invokevirtual #88                 // Method KeyboardMenu.addItem:(ILjava/lang/String;)V
      1504: aload_0
      1505: getfield      #25                 // Field km:LKeyboardMenu;
      1508: iconst_2
      1509: bipush        120
      1511: sipush        150
      1514: sipush        224
      1517: aload_0
      1518: getfield      #26                 // Field mp:LMainProgram;
      1521: getfield      #106                // Field MainProgram.setumei_name:Ljava/lang/String;
      1524: invokevirtual #96                 // Method KeyboardMenu.activeSerifutuki:(IIIILjava/lang/String;)V
      1527: aload_0
      1528: getfield      #25                 // Field km:LKeyboardMenu;
      1531: sipush        510
      1534: putfield      #40                 // Field KeyboardMenu.mode:I
      1537: goto          1814
      1540: aload_0
      1541: getfield      #25                 // Field km:LKeyboardMenu;
      1544: getfield      #40                 // Field KeyboardMenu.mode:I
      1547: sipush        510
      1550: if_icmpne     1724
      1553: aload_0
      1554: getfield      #25                 // Field km:LKeyboardMenu;
      1557: getfield      #69                 // Field KeyboardMenu.cancel_c:I
      1560: iconst_1
      1561: if_icmpne     1592
      1564: aload_0
      1565: getfield      #25                 // Field km:LKeyboardMenu;
      1568: iconst_2
      1569: invokevirtual #70                 // Method KeyboardMenu.off:(I)V
      1572: aload_0
      1573: getfield      #25                 // Field km:LKeyboardMenu;
      1576: iconst_4
      1577: invokevirtual #70                 // Method KeyboardMenu.off:(I)V
      1580: aload_0
      1581: getfield      #25                 // Field km:LKeyboardMenu;
      1584: bipush        100
      1586: putfield      #40                 // Field KeyboardMenu.mode:I
      1589: goto          1814
      1592: aload_0
      1593: getfield      #25                 // Field km:LKeyboardMenu;
      1596: getfield      #71                 // Field KeyboardMenu.kettei_c:I
      1599: iconst_1
      1600: if_icmpne     1814
      1603: aload_0
      1604: getfield      #25                 // Field km:LKeyboardMenu;
      1607: iconst_3
      1608: invokevirtual #72                 // Method KeyboardMenu.init1:(I)V
      1611: aload_0
      1612: getfield      #25                 // Field km:LKeyboardMenu;
      1615: iconst_3
      1616: aload_0
      1617: getfield      #26                 // Field mp:LMainProgram;
      1620: getfield      #106                // Field MainProgram.setumei_name:Ljava/lang/String;
      1623: invokevirtual #74                 // Method KeyboardMenu.setMessage:(ILjava/lang/String;)V
      1626: aload_0
      1627: getfield      #25                 // Field km:LKeyboardMenu;
      1630: getfield      #90                 // Field KeyboardMenu.selectedIndex:[I
      1633: iconst_2
      1634: iaload
      1635: iconst_1
      1636: if_icmpne     1653
      1639: aload_0
      1640: getfield      #26                 // Field mp:LMainProgram;
      1643: iconst_3
      1644: bipush        11
      1646: iconst_3
      1647: invokevirtual #75                 // Method MainProgram.addSerifu:(III)V
      1650: goto          1691
      1653: aload_0
      1654: getfield      #25                 // Field km:LKeyboardMenu;
      1657: getfield      #90                 // Field KeyboardMenu.selectedIndex:[I
      1660: iconst_2
      1661: iaload
      1662: iconst_2
      1663: if_icmpne     1680
      1666: aload_0
      1667: getfield      #26                 // Field mp:LMainProgram;
      1670: iconst_3
      1671: bipush        12
      1673: iconst_3
      1674: invokevirtual #75                 // Method MainProgram.addSerifu:(III)V
      1677: goto          1691
      1680: aload_0
      1681: getfield      #26                 // Field mp:LMainProgram;
      1684: iconst_3
      1685: bipush        10
      1687: iconst_3
      1688: invokevirtual #75                 // Method MainProgram.addSerifu:(III)V
      1691: aload_0
      1692: getfield      #25                 // Field km:LKeyboardMenu;
      1695: iconst_3
      1696: sipush        200
      1699: sipush        191
      1702: sipush        272
      1705: getstatic     #76                 // Field java/awt/Color.cyan:Ljava/awt/Color;
      1708: invokevirtual #77                 // Method KeyboardMenu.activeSerifu:(IIIILjava/awt/Color;)V
      1711: aload_0
      1712: getfield      #25                 // Field km:LKeyboardMenu;
      1715: sipush        520
      1718: putfield      #40                 // Field KeyboardMenu.mode:I
      1721: goto          1814
      1724: aload_0
      1725: getfield      #25                 // Field km:LKeyboardMenu;
      1728: getfield      #40                 // Field KeyboardMenu.mode:I
      1731: sipush        520
      1734: if_icmpne     1814
      1737: aload_0
      1738: getfield      #25                 // Field km:LKeyboardMenu;
      1741: getfield      #69                 // Field KeyboardMenu.cancel_c:I
      1744: iconst_1
      1745: if_icmpne     1770
      1748: aload_0
      1749: getfield      #25                 // Field km:LKeyboardMenu;
      1752: iconst_3
      1753: iconst_2
      1754: invokevirtual #97                 // Method KeyboardMenu.offActivewindow:(II)V
      1757: aload_0
      1758: getfield      #25                 // Field km:LKeyboardMenu;
      1761: sipush        510
      1764: putfield      #40                 // Field KeyboardMenu.mode:I
      1767: goto          1814
      1770: aload_0
      1771: getfield      #25                 // Field km:LKeyboardMenu;
      1774: getfield      #71                 // Field KeyboardMenu.kettei_c:I
      1777: iconst_1
      1778: if_icmpne     1814
      1781: aload_0
      1782: getfield      #25                 // Field km:LKeyboardMenu;
      1785: iconst_2
      1786: invokevirtual #70                 // Method KeyboardMenu.off:(I)V
      1789: aload_0
      1790: getfield      #25                 // Field km:LKeyboardMenu;
      1793: iconst_3
      1794: invokevirtual #70                 // Method KeyboardMenu.off:(I)V
      1797: aload_0
      1798: getfield      #25                 // Field km:LKeyboardMenu;
      1801: iconst_4
      1802: invokevirtual #70                 // Method KeyboardMenu.off:(I)V
      1805: aload_0
      1806: getfield      #25                 // Field km:LKeyboardMenu;
      1809: bipush        100
      1811: putfield      #40                 // Field KeyboardMenu.mode:I
      1814: aload_0
      1815: getfield      #25                 // Field km:LKeyboardMenu;
      1818: invokevirtual #107                // Method KeyboardMenu.move:()V
      1821: aload_0
      1822: getfield      #4                  // Field co_j:LCharacterObject;
      1825: getfield      #56                 // Field CharacterObject.pt:I
      1828: sipush        1000
      1831: if_icmpne     1879
      1834: aload_0
      1835: getfield      #23                 // Field gg:LGameGraphics;
      1838: aload_0
      1839: getfield      #4                  // Field co_j:LCharacterObject;
      1842: getfield      #31                 // Field CharacterObject.x:I
      1845: bipush        16
      1847: iadd
      1848: aload_0
      1849: getfield      #4                  // Field co_j:LCharacterObject;
      1852: getfield      #32                 // Field CharacterObject.y:I
      1855: bipush        24
      1857: iadd
      1858: bipush        12
      1860: isub
      1861: bipush        6
      1863: isub
      1864: bipush        100
      1866: aload_0
      1867: getfield      #4                  // Field co_j:LCharacterObject;
      1870: getfield      #35                 // Field CharacterObject.muki:I
      1873: invokevirtual #108                // Method GameGraphics.drawPT:(IIII)V
      1876: goto          2047
      1879: aload_0
      1880: getfield      #4                  // Field co_j:LCharacterObject;
      1883: getfield      #56                 // Field CharacterObject.pt:I
      1886: sipush        1010
      1889: if_icmpne     1936
      1892: aload_0
      1893: getfield      #23                 // Field gg:LGameGraphics;
      1896: aload_0
      1897: getfield      #4                  // Field co_j:LCharacterObject;
      1900: getfield      #31                 // Field CharacterObject.x:I
      1903: bipush        16
      1905: iadd
      1906: aload_0
      1907: getfield      #4                  // Field co_j:LCharacterObject;
      1910: getfield      #32                 // Field CharacterObject.y:I
      1913: bipush        24
      1915: iadd
      1916: bipush        12
      1918: isub
      1919: iconst_5
      1920: iadd
      1921: bipush        100
      1923: aload_0
      1924: getfield      #4                  // Field co_j:LCharacterObject;
      1927: getfield      #35                 // Field CharacterObject.muki:I
      1930: invokevirtual #108                // Method GameGraphics.drawPT:(IIII)V
      1933: goto          2047
      1936: aload_0
      1937: getfield      #4                  // Field co_j:LCharacterObject;
      1940: getfield      #56                 // Field CharacterObject.pt:I
      1943: sipush        202
      1946: if_icmplt     2003
      1949: aload_0
      1950: getfield      #4                  // Field co_j:LCharacterObject;
      1953: getfield      #56                 // Field CharacterObject.pt:I
      1956: sipush        205
      1959: if_icmpgt     2003
      1962: aload_0
      1963: getfield      #23                 // Field gg:LGameGraphics;
      1966: aload_0
      1967: getfield      #4                  // Field co_j:LCharacterObject;
      1970: getfield      #31                 // Field CharacterObject.x:I
      1973: bipush        16
      1975: iadd
      1976: aload_0
      1977: getfield      #4                  // Field co_j:LCharacterObject;
      1980: getfield      #32                 // Field CharacterObject.y:I
      1983: bipush        24
      1985: iadd
      1986: bipush        12
      1988: isub
      1989: aload_0
      1990: getfield      #4                  // Field co_j:LCharacterObject;
      1993: getfield      #56                 // Field CharacterObject.pt:I
      1996: iconst_0
      1997: invokevirtual #108                // Method GameGraphics.drawPT:(IIII)V
      2000: goto          2047
      2003: aload_0
      2004: getfield      #23                 // Field gg:LGameGraphics;
      2007: aload_0
      2008: getfield      #4                  // Field co_j:LCharacterObject;
      2011: getfield      #31                 // Field CharacterObject.x:I
      2014: bipush        16
      2016: iadd
      2017: aload_0
      2018: getfield      #4                  // Field co_j:LCharacterObject;
      2021: getfield      #32                 // Field CharacterObject.y:I
      2024: bipush        24
      2026: iadd
      2027: bipush        12
      2029: isub
      2030: aload_0
      2031: getfield      #4                  // Field co_j:LCharacterObject;
      2034: getfield      #56                 // Field CharacterObject.pt:I
      2037: aload_0
      2038: getfield      #4                  // Field co_j:LCharacterObject;
      2041: getfield      #35                 // Field CharacterObject.muki:I
      2044: invokevirtual #108                // Method GameGraphics.drawPT:(IIII)V
      2047: aload_0
      2048: getfield      #25                 // Field km:LKeyboardMenu;
      2051: invokevirtual #109                // Method KeyboardMenu.drawMenus:()V
      2054: aload_0
      2055: getfield      #18                 // Field mp_mode:I
      2058: bipush        100
      2060: if_icmpne     2103
      2063: aload_0
      2064: aload_0
      2065: getfield      #52                 // Field cc_hankei:I
      2068: invokevirtual #110                // Method circleCLS:(I)V
      2071: aload_0
      2072: dup
      2073: getfield      #52                 // Field cc_hankei:I
      2076: bipush        12
      2078: isub
      2079: putfield      #52                 // Field cc_hankei:I
      2082: aload_0
      2083: getfield      #52                 // Field cc_hankei:I
      2086: ifge          2895
      2089: aload_0
      2090: iconst_0
      2091: putfield      #52                 // Field cc_hankei:I
      2094: aload_0
      2095: bipush        110
      2097: putfield      #18                 // Field mp_mode:I
      2100: goto          2895
      2103: aload_0
      2104: getfield      #18                 // Field mp_mode:I
      2107: bipush        110
      2109: if_icmpne     2123
      2112: aload_0
      2113: aload_0
      2114: getfield      #52                 // Field cc_hankei:I
      2117: invokevirtual #110                // Method circleCLS:(I)V
      2120: goto          2895
      2123: aload_0
      2124: getfield      #18                 // Field mp_mode:I
      2127: sipush        200
      2130: if_icmpne     2373
      2133: aload_0
      2134: aload_0
      2135: getfield      #52                 // Field cc_hankei:I
      2138: invokevirtual #110                // Method circleCLS:(I)V
      2141: aload_0
      2142: dup
      2143: getfield      #52                 // Field cc_hankei:I
      2146: bipush        12
      2148: iadd
      2149: putfield      #52                 // Field cc_hankei:I
      2152: aload_0
      2153: getfield      #52                 // Field cc_hankei:I
      2156: sipush        312
      2159: if_icmple     2895
      2162: aload_0
      2163: getfield      #27                 // Field stage_kcID:I
      2166: iconst_1
      2167: if_icmplt     2312
      2170: aload_0
      2171: sipush        300
      2174: putfield      #18                 // Field mp_mode:I
      2177: aload_0
      2178: iconst_0
      2179: putfield      #52                 // Field cc_hankei:I
      2182: aload_0
      2183: getfield      #11                 // Field stage_y:[I
      2186: aload_0
      2187: getfield      #27                 // Field stage_kcID:I
      2190: iconst_1
      2191: isub
      2192: iaload
      2193: bipush        32
      2195: idiv
      2196: istore        6
      2198: aload_0
      2199: getfield      #8                  // Field map_bg:[[I
      2202: aload_0
      2203: getfield      #10                 // Field stage_x:[I
      2206: aload_0
      2207: getfield      #27                 // Field stage_kcID:I
      2210: iconst_1
      2211: isub
      2212: iaload
      2213: bipush        32
      2215: idiv
      2216: aaload
      2217: iload         6
      2219: sipush        227
      2222: iastore
      2223: aload_0
      2224: getfield      #28                 // Field door_koID:I
      2227: iconst_1
      2228: if_icmplt     2268
      2231: aload_0
      2232: getfield      #8                  // Field map_bg:[[I
      2235: aload_0
      2236: getfield      #14                 // Field ie_x:[I
      2239: aload_0
      2240: getfield      #28                 // Field door_koID:I
      2243: iconst_1
      2244: isub
      2245: iaload
      2246: bipush        32
      2248: idiv
      2249: aaload
      2250: aload_0
      2251: getfield      #15                 // Field ie_y:[I
      2254: aload_0
      2255: getfield      #28                 // Field door_koID:I
      2258: iconst_1
      2259: isub
      2260: iaload
      2261: bipush        32
      2263: idiv
      2264: sipush        222
      2267: iastore
      2268: aload_0
      2269: getfield      #30                 // Field door_score_open:I
      2272: iconst_1
      2273: if_icmpne     2305
      2276: aload_0
      2277: getfield      #8                  // Field map_bg:[[I
      2280: aload_0
      2281: getfield      #14                 // Field ie_x:[I
      2284: bipush        9
      2286: iaload
      2287: bipush        32
      2289: idiv
      2290: aaload
      2291: aload_0
      2292: getfield      #15                 // Field ie_y:[I
      2295: bipush        9
      2297: iaload
      2298: bipush        32
      2300: idiv
      2301: sipush        222
      2304: iastore
      2305: aload_0
      2306: invokevirtual #51                 // Method drawOs2:()V
      2309: goto          2895
      2312: aload_0
      2313: iconst_0
      2314: putfield      #18                 // Field mp_mode:I
      2317: aload_0
      2318: getfield      #30                 // Field door_score_open:I
      2321: iconst_1
      2322: if_icmpne     2895
      2325: aload_0
      2326: sipush        400
      2329: putfield      #18                 // Field mp_mode:I
      2332: aload_0
      2333: iconst_0
      2334: putfield      #52                 // Field cc_hankei:I
      2337: aload_0
      2338: getfield      #8                  // Field map_bg:[[I
      2341: aload_0
      2342: getfield      #14                 // Field ie_x:[I
      2345: bipush        9
      2347: iaload
      2348: bipush        32
      2350: idiv
      2351: aaload
      2352: aload_0
      2353: getfield      #15                 // Field ie_y:[I
      2356: bipush        9
      2358: iaload
      2359: bipush        32
      2361: idiv
      2362: sipush        222
      2365: iastore
      2366: aload_0
      2367: invokevirtual #51                 // Method drawOs2:()V
      2370: goto          2895
      2373: aload_0
      2374: getfield      #18                 // Field mp_mode:I
      2377: sipush        300
      2380: if_icmpne     2694
      2383: aload_0
      2384: dup
      2385: getfield      #52                 // Field cc_hankei:I
      2388: iconst_1
      2389: iadd
      2390: putfield      #52                 // Field cc_hankei:I
      2393: aload_0
      2394: getfield      #52                 // Field cc_hankei:I
      2397: iconst_3
      2398: if_icmpgt     2407
      2401: iconst_0
      2402: istore        6
      2404: goto          2535
      2407: aload_0
      2408: getfield      #52                 // Field cc_hankei:I
      2411: bipush        6
      2413: if_icmpgt     2422
      2416: iconst_1
      2417: istore        6
      2419: goto          2535
      2422: aload_0
      2423: getfield      #52                 // Field cc_hankei:I
      2426: bipush        9
      2428: if_icmpgt     2437
      2431: iconst_0
      2432: istore        6
      2434: goto          2535
      2437: aload_0
      2438: getfield      #52                 // Field cc_hankei:I
      2441: bipush        12
      2443: if_icmpgt     2452
      2446: iconst_1
      2447: istore        6
      2449: goto          2535
      2452: aload_0
      2453: getfield      #52                 // Field cc_hankei:I
      2456: bipush        15
      2458: if_icmpgt     2467
      2461: iconst_0
      2462: istore        6
      2464: goto          2535
      2467: aload_0
      2468: getfield      #52                 // Field cc_hankei:I
      2471: bipush        18
      2473: if_icmpgt     2482
      2476: iconst_1
      2477: istore        6
      2479: goto          2535
      2482: aload_0
      2483: getfield      #52                 // Field cc_hankei:I
      2486: bipush        21
      2488: if_icmpgt     2497
      2491: iconst_0
      2492: istore        6
      2494: goto          2535
      2497: aload_0
      2498: getfield      #52                 // Field cc_hankei:I
      2501: bipush        24
      2503: if_icmpgt     2512
      2506: iconst_1
      2507: istore        6
      2509: goto          2535
      2512: aload_0
      2513: getfield      #52                 // Field cc_hankei:I
      2516: bipush        26
      2518: if_icmpgt     2527
      2521: iconst_0
      2522: istore        6
      2524: goto          2535
      2527: iconst_0
      2528: istore        6
      2530: aload_0
      2531: iconst_0
      2532: putfield      #18                 // Field mp_mode:I
      2535: iload         6
      2537: ifle          2584
      2540: aload_0
      2541: getfield      #23                 // Field gg:LGameGraphics;
      2544: aload_0
      2545: getfield      #10                 // Field stage_x:[I
      2548: aload_0
      2549: getfield      #27                 // Field stage_kcID:I
      2552: iconst_1
      2553: isub
      2554: iaload
      2555: bipush        16
      2557: iadd
      2558: aload_0
      2559: getfield      #11                 // Field stage_y:[I
      2562: aload_0
      2563: getfield      #27                 // Field stage_kcID:I
      2566: iconst_1
      2567: isub
      2568: iaload
      2569: bipush        24
      2571: iadd
      2572: sipush        222
      2575: aload_0
      2576: getfield      #27                 // Field stage_kcID:I
      2579: iadd
      2580: iconst_0
      2581: invokevirtual #108                // Method GameGraphics.drawPT:(IIII)V
      2584: iload         6
      2586: ifle          2644
      2589: aload_0
      2590: getfield      #28                 // Field door_koID:I
      2593: iconst_1
      2594: if_icmplt     2644
      2597: aload_0
      2598: getfield      #23                 // Field gg:LGameGraphics;
      2601: aload_0
      2602: getfield      #14                 // Field ie_x:[I
      2605: aload_0
      2606: getfield      #28                 // Field door_koID:I
      2609: iconst_1
      2610: isub
      2611: iaload
      2612: bipush        16
      2614: iadd
      2615: aload_0
      2616: getfield      #15                 // Field ie_y:[I
      2619: aload_0
      2620: getfield      #28                 // Field door_koID:I
      2623: iconst_1
      2624: isub
      2625: iaload
      2626: bipush        24
      2628: iadd
      2629: bipush        7
      2631: isub
      2632: sipush        212
      2635: aload_0
      2636: getfield      #28                 // Field door_koID:I
      2639: iadd
      2640: iconst_0
      2641: invokevirtual #108                // Method GameGraphics.drawPT:(IIII)V
      2644: iload         6
      2646: ifle          2895
      2649: aload_0
      2650: getfield      #30                 // Field door_score_open:I
      2653: iconst_1
      2654: if_icmpne     2895
      2657: aload_0
      2658: getfield      #23                 // Field gg:LGameGraphics;
      2661: aload_0
      2662: getfield      #14                 // Field ie_x:[I
      2665: bipush        9
      2667: iaload
      2668: bipush        16
      2670: iadd
      2671: aload_0
      2672: getfield      #15                 // Field ie_y:[I
      2675: bipush        9
      2677: iaload
      2678: bipush        24
      2680: iadd
      2681: bipush        7
      2683: isub
      2684: sipush        212
      2687: iconst_0
      2688: invokevirtual #108                // Method GameGraphics.drawPT:(IIII)V
      2691: goto          2895
      2694: aload_0
      2695: getfield      #18                 // Field mp_mode:I
      2698: sipush        400
      2701: if_icmpne     2895
      2704: aload_0
      2705: dup
      2706: getfield      #52                 // Field cc_hankei:I
      2709: iconst_1
      2710: iadd
      2711: putfield      #52                 // Field cc_hankei:I
      2714: aload_0
      2715: getfield      #52                 // Field cc_hankei:I
      2718: iconst_3
      2719: if_icmpgt     2728
      2722: iconst_0
      2723: istore        6
      2725: goto          2856
      2728: aload_0
      2729: getfield      #52                 // Field cc_hankei:I
      2732: bipush        6
      2734: if_icmpgt     2743
      2737: iconst_1
      2738: istore        6
      2740: goto          2856
      2743: aload_0
      2744: getfield      #52                 // Field cc_hankei:I
      2747: bipush        9
      2749: if_icmpgt     2758
      2752: iconst_0
      2753: istore        6
      2755: goto          2856
      2758: aload_0
      2759: getfield      #52                 // Field cc_hankei:I
      2762: bipush        12
      2764: if_icmpgt     2773
      2767: iconst_1
      2768: istore        6
      2770: goto          2856
      2773: aload_0
      2774: getfield      #52                 // Field cc_hankei:I
      2777: bipush        15
      2779: if_icmpgt     2788
      2782: iconst_0
      2783: istore        6
      2785: goto          2856
      2788: aload_0
      2789: getfield      #52                 // Field cc_hankei:I
      2792: bipush        18
      2794: if_icmpgt     2803
      2797: iconst_1
      2798: istore        6
      2800: goto          2856
      2803: aload_0
      2804: getfield      #52                 // Field cc_hankei:I
      2807: bipush        21
      2809: if_icmpgt     2818
      2812: iconst_0
      2813: istore        6
      2815: goto          2856
      2818: aload_0
      2819: getfield      #52                 // Field cc_hankei:I
      2822: bipush        24
      2824: if_icmpgt     2833
      2827: iconst_1
      2828: istore        6
      2830: goto          2856
      2833: aload_0
      2834: getfield      #52                 // Field cc_hankei:I
      2837: bipush        26
      2839: if_icmpgt     2848
      2842: iconst_0
      2843: istore        6
      2845: goto          2856
      2848: iconst_0
      2849: istore        6
      2851: aload_0
      2852: iconst_0
      2853: putfield      #18                 // Field mp_mode:I
      2856: iload         6
      2858: ifle          2895
      2861: aload_0
      2862: getfield      #23                 // Field gg:LGameGraphics;
      2865: aload_0
      2866: getfield      #14                 // Field ie_x:[I
      2869: bipush        9
      2871: iaload
      2872: bipush        16
      2874: iadd
      2875: aload_0
      2876: getfield      #15                 // Field ie_y:[I
      2879: bipush        9
      2881: iaload
      2882: bipush        24
      2884: iadd
      2885: bipush        7
      2887: isub
      2888: sipush        212
      2891: iconst_0
      2892: invokevirtual #108                // Method GameGraphics.drawPT:(IIII)V
      2895: return
      LineNumberTable:
        line 15282: 0
        line 15283: 11
        line 15284: 22
        line 15288: 38
        line 15291: 46
        line 15295: 53
        line 15297: 65
        line 15299: 72
        line 15301: 85
        line 15303: 96
        line 15304: 104
        line 15305: 112
        line 15307: 124
        line 15311: 135
        line 15312: 143
        line 15313: 158
        line 15314: 168
        line 15316: 187
        line 15319: 200
        line 15321: 213
        line 15323: 235
        line 15324: 243
        line 15325: 251
        line 15328: 263
        line 15330: 276
        line 15332: 287
        line 15333: 295
        line 15334: 303
        line 15336: 315
        line 15340: 326
        line 15341: 334
        line 15342: 349
        line 15343: 359
        line 15345: 378
        line 15348: 391
        line 15350: 404
        line 15352: 415
        line 15353: 423
        line 15354: 431
        line 15356: 443
        line 15359: 454
        line 15362: 462
        line 15363: 470
        line 15365: 479
        line 15367: 500
        line 15368: 505
        line 15371: 520
        line 15374: 547
        line 15377: 563
        line 15367: 576
        line 15380: 585
        line 15382: 596
        line 15384: 613
        line 15388: 626
        line 15391: 635
        line 15392: 643
        line 15393: 653
        line 15394: 663
        line 15396: 682
        line 15400: 695
        line 15402: 708
        line 15403: 719
        line 15404: 727
        line 15405: 736
        line 15407: 748
        line 15411: 759
        line 15414: 784
        line 15416: 793
        line 15419: 845
        line 15420: 866
        line 15422: 887
        line 15424: 911
        line 15427: 924
        line 15429: 937
        line 15431: 948
        line 15433: 959
        line 15435: 972
        line 15437: 983
        line 15440: 996
        line 15442: 1021
        line 15443: 1029
        line 15445: 1080
        line 15447: 1096
        line 15448: 1123
        line 15451: 1134
        line 15452: 1143
        line 15455: 1156
        line 15459: 1169
        line 15460: 1177
        line 15461: 1197
        line 15463: 1213
        line 15468: 1226
        line 15469: 1234
        line 15470: 1243
        line 15472: 1252
        line 15476: 1264
        line 15478: 1277
        line 15480: 1299
        line 15481: 1307
        line 15482: 1315
        line 15483: 1324
        line 15485: 1333
        line 15488: 1345
        line 15490: 1358
        line 15491: 1369
        line 15492: 1377
        line 15493: 1385
        line 15495: 1397
        line 15498: 1408
        line 15501: 1416
        line 15502: 1424
        line 15503: 1444
        line 15504: 1464
        line 15505: 1484
        line 15506: 1504
        line 15508: 1527
        line 15511: 1540
        line 15513: 1553
        line 15515: 1564
        line 15516: 1572
        line 15517: 1580
        line 15519: 1592
        line 15523: 1603
        line 15524: 1611
        line 15525: 1626
        line 15526: 1639
        line 15528: 1653
        line 15529: 1666
        line 15532: 1680
        line 15534: 1691
        line 15536: 1711
        line 15539: 1724
        line 15541: 1737
        line 15543: 1748
        line 15544: 1757
        line 15546: 1770
        line 15548: 1781
        line 15549: 1789
        line 15550: 1797
        line 15551: 1805
        line 15556: 1814
        line 15560: 1821
        line 15564: 1834
        line 15566: 1879
        line 15569: 1892
        line 15571: 1936
        line 15573: 1962
        line 15578: 2003
        line 15582: 2047
        line 15584: 2054
        line 15588: 2063
        line 15590: 2071
        line 15591: 2082
        line 15592: 2089
        line 15594: 2094
        line 15597: 2103
        line 15601: 2112
        line 15603: 2123
        line 15607: 2133
        line 15609: 2141
        line 15610: 2152
        line 15611: 2162
        line 15613: 2170
        line 15614: 2177
        line 15617: 2182
        line 15618: 2198
        line 15621: 2223
        line 15622: 2231
        line 15626: 2268
        line 15627: 2276
        line 15631: 2305
        line 15635: 2312
        line 15637: 2317
        line 15639: 2325
        line 15640: 2332
        line 15643: 2337
        line 15646: 2366
        line 15651: 2373
        line 15653: 2383
        line 15654: 2393
        line 15655: 2401
        line 15657: 2407
        line 15658: 2416
        line 15660: 2422
        line 15661: 2431
        line 15663: 2437
        line 15664: 2446
        line 15666: 2452
        line 15667: 2461
        line 15669: 2467
        line 15670: 2476
        line 15672: 2482
        line 15673: 2491
        line 15675: 2497
        line 15676: 2506
        line 15678: 2512
        line 15679: 2521
        line 15682: 2527
        line 15684: 2530
        line 15688: 2535
        line 15689: 2540
        line 15693: 2584
        line 15694: 2589
        line 15695: 2597
        line 15700: 2644
        line 15701: 2649
        line 15702: 2657
        line 15706: 2694
        line 15708: 2704
        line 15709: 2714
        line 15710: 2722
        line 15712: 2728
        line 15713: 2737
        line 15715: 2743
        line 15716: 2752
        line 15718: 2758
        line 15719: 2767
        line 15721: 2773
        line 15722: 2782
        line 15724: 2788
        line 15725: 2797
        line 15727: 2803
        line 15728: 2812
        line 15730: 2818
        line 15731: 2827
        line 15733: 2833
        line 15734: 2842
        line 15737: 2848
        line 15739: 2851
        line 15743: 2856
        line 15744: 2861
        line 15747: 2895

  void jMove();
    descriptor: ()V
    flags: (0x0000)
    Code:
      stack=6, locals=12, args_size=1
         0: aload_0
         1: getfield      #4                  // Field co_j:LCharacterObject;
         4: getfield      #31                 // Field CharacterObject.x:I
         7: istore        5
         9: aload_0
        10: getfield      #4                  // Field co_j:LCharacterObject;
        13: getfield      #32                 // Field CharacterObject.y:I
        16: istore        6
        18: aload_0
        19: getfield      #4                  // Field co_j:LCharacterObject;
        22: bipush        100
        24: putfield      #56                 // Field CharacterObject.pt:I
        27: aload_0
        28: getfield      #4                  // Field co_j:LCharacterObject;
        31: getfield      #33                 // Field CharacterObject.vx:I
        34: ifne          1295
        37: aload_0
        38: getfield      #4                  // Field co_j:LCharacterObject;
        41: getfield      #34                 // Field CharacterObject.vy:I
        44: ifne          1295
        47: aload_0
        48: getfield      #4                  // Field co_j:LCharacterObject;
        51: dup
        52: getfield      #36                 // Field CharacterObject.ac:I
        55: iconst_1
        56: iadd
        57: putfield      #36                 // Field CharacterObject.ac:I
        60: aload_0
        61: getfield      #4                  // Field co_j:LCharacterObject;
        64: getfield      #36                 // Field CharacterObject.ac:I
        67: bipush        7
        69: if_icmple     80
        72: aload_0
        73: getfield      #4                  // Field co_j:LCharacterObject;
        76: iconst_0
        77: putfield      #36                 // Field CharacterObject.ac:I
        80: aload_0
        81: getfield      #4                  // Field co_j:LCharacterObject;
        84: getfield      #36                 // Field CharacterObject.ac:I
        87: iconst_3
        88: if_icmple     148
        91: aload_0
        92: getfield      #4                  // Field co_j:LCharacterObject;
        95: sipush        1000
        98: putfield      #56                 // Field CharacterObject.pt:I
       101: aload_0
       102: iload         5
       104: iload         6
       106: invokevirtual #111                // Method getBGZ:(II)I
       109: istore_1
       110: iload_1
       111: sipush        216
       114: if_icmplt     124
       117: iload_1
       118: sipush        219
       121: if_icmple     138
       124: iload_1
       125: sipush        206
       128: if_icmplt     148
       131: iload_1
       132: sipush        209
       135: if_icmpgt     148
       138: aload_0
       139: getfield      #4                  // Field co_j:LCharacterObject;
       142: sipush        1010
       145: putfield      #56                 // Field CharacterObject.pt:I
       148: aload_0
       149: getfield      #26                 // Field mp:LMainProgram;
       152: getfield      #37                 // Field MainProgram.tr1_c:I
       155: iconst_1
       156: if_icmpne     991
       159: aload_0
       160: invokevirtual #55                 // Method checkStage:()I
       163: iconst_1
       164: if_icmplt     205
       167: aload_0
       168: bipush        100
       170: putfield      #18                 // Field mp_mode:I
       173: aload_0
       174: sipush        312
       177: putfield      #52                 // Field cc_hankei:I
       180: aload_0
       181: getfield      #4                  // Field co_j:LCharacterObject;
       184: iconst_0
       185: putfield      #36                 // Field CharacterObject.ac:I
       188: aload_0
       189: iconst_0
       190: putfield      #29                 // Field dokan_khID:I
       193: aload_0
       194: getfield      #4                  // Field co_j:LCharacterObject;
       197: bipush        100
       199: putfield      #56                 // Field CharacterObject.pt:I
       202: goto          1295
       205: aload_0
       206: iload         5
       208: iload         6
       210: invokevirtual #111                // Method getBGZ:(II)I
       213: sipush        206
       216: if_icmplt     425
       219: aload_0
       220: iload         5
       222: iload         6
       224: invokevirtual #111                // Method getBGZ:(II)I
       227: sipush        209
       230: if_icmpgt     425
       233: aload_0
       234: getfield      #26                 // Field mp:LMainProgram;
       237: getfield      #112                // Field MainProgram.dokan_mode:I
       240: iconst_2
       241: if_icmpne     375
       244: iconst_0
       245: istore        4
       247: iconst_0
       248: istore        8
       250: goto          365
       253: iconst_0
       254: istore        7
       256: goto          346
       259: iload         7
       261: bipush        32
       263: imul
       264: iload         5
       266: if_icmpne     282
       269: iload         8
       271: bipush        32
       273: imul
       274: iload         6
       276: if_icmpne     282
       279: goto          343
       282: aload_0
       283: getfield      #8                  // Field map_bg:[[I
       286: iload         7
       288: aaload
       289: iload         8
       291: iaload
       292: istore_3
       293: iload_3
       294: aload_0
       295: iload         5
       297: iload         6
       299: invokevirtual #111                // Method getBGZ:(II)I
       302: if_icmpne     343
       305: iload         7
       307: bipush        32
       309: imul
       310: istore        5
       312: iload         8
       314: bipush        32
       316: imul
       317: istore        6
       319: aload_0
       320: getfield      #4                  // Field co_j:LCharacterObject;
       323: iconst_0
       324: putfield      #36                 // Field CharacterObject.ac:I
       327: aload_0
       328: getfield      #4                  // Field co_j:LCharacterObject;
       331: sipush        1010
       334: putfield      #56                 // Field CharacterObject.pt:I
       337: iconst_1
       338: istore        4
       340: goto          353
       343: iinc          7, 1
       346: iload         7
       348: bipush        14
       350: if_icmple     259
       353: iload         4
       355: iconst_1
       356: if_icmpne     362
       359: goto          1295
       362: iinc          8, 1
       365: iload         8
       367: bipush        8
       369: if_icmple     253
       372: goto          1295
       375: aload_0
       376: bipush        100
       378: putfield      #18                 // Field mp_mode:I
       381: aload_0
       382: sipush        312
       385: putfield      #52                 // Field cc_hankei:I
       388: aload_0
       389: getfield      #4                  // Field co_j:LCharacterObject;
       392: iconst_0
       393: putfield      #36                 // Field CharacterObject.ac:I
       396: aload_0
       397: aload_0
       398: iload         5
       400: iload         6
       402: invokevirtual #111                // Method getBGZ:(II)I
       405: sipush        205
       408: isub
       409: putfield      #29                 // Field dokan_khID:I
       412: aload_0
       413: getfield      #4                  // Field co_j:LCharacterObject;
       416: sipush        1010
       419: putfield      #56                 // Field CharacterObject.pt:I
       422: goto          1295
       425: aload_0
       426: iload         5
       428: iload         6
       430: invokevirtual #111                // Method getBGZ:(II)I
       433: sipush        216
       436: if_icmpne     548
       439: aload_0
       440: getfield      #25                 // Field km:LKeyboardMenu;
       443: iconst_4
       444: invokevirtual #72                 // Method KeyboardMenu.init1:(I)V
       447: aload_0
       448: getfield      #25                 // Field km:LKeyboardMenu;
       451: iconst_4
       452: bipush        120
       454: bipush        42
       456: sipush        272
       459: sipush        230
       462: invokevirtual #113                // Method KeyboardMenu.onKao:(IIIII)V
       465: aload_0
       466: getfield      #25                 // Field km:LKeyboardMenu;
       469: iconst_3
       470: invokevirtual #72                 // Method KeyboardMenu.init1:(I)V
       473: aload_0
       474: getfield      #25                 // Field km:LKeyboardMenu;
       477: iconst_3
       478: aload_0
       479: getfield      #26                 // Field mp:LMainProgram;
       482: getfield      #73                 // Field MainProgram.mes1_name:Ljava/lang/String;
       485: invokevirtual #74                 // Method KeyboardMenu.setMessage:(ILjava/lang/String;)V
       488: aload_0
       489: getfield      #26                 // Field mp:LMainProgram;
       492: iconst_3
       493: iconst_1
       494: iconst_3
       495: invokevirtual #75                 // Method MainProgram.addSerifu:(III)V
       498: aload_0
       499: getfield      #25                 // Field km:LKeyboardMenu;
       502: iconst_3
       503: bipush        120
       505: sipush        150
       508: sipush        272
       511: getstatic     #76                 // Field java/awt/Color.cyan:Ljava/awt/Color;
       514: invokevirtual #77                 // Method KeyboardMenu.activeSerifu:(IIIILjava/awt/Color;)V
       517: aload_0
       518: getfield      #25                 // Field km:LKeyboardMenu;
       521: sipush        200
       524: putfield      #40                 // Field KeyboardMenu.mode:I
       527: aload_0
       528: getfield      #4                  // Field co_j:LCharacterObject;
       531: sipush        1010
       534: putfield      #56                 // Field CharacterObject.pt:I
       537: aload_0
       538: getfield      #4                  // Field co_j:LCharacterObject;
       541: iconst_0
       542: putfield      #36                 // Field CharacterObject.ac:I
       545: goto          1295
       548: aload_0
       549: iload         5
       551: iload         6
       553: invokevirtual #111                // Method getBGZ:(II)I
       556: sipush        217
       559: if_icmpne     671
       562: aload_0
       563: getfield      #25                 // Field km:LKeyboardMenu;
       566: iconst_4
       567: invokevirtual #72                 // Method KeyboardMenu.init1:(I)V
       570: aload_0
       571: getfield      #25                 // Field km:LKeyboardMenu;
       574: iconst_4
       575: bipush        120
       577: bipush        42
       579: sipush        272
       582: sipush        232
       585: invokevirtual #113                // Method KeyboardMenu.onKao:(IIIII)V
       588: aload_0
       589: getfield      #25                 // Field km:LKeyboardMenu;
       592: iconst_3
       593: invokevirtual #72                 // Method KeyboardMenu.init1:(I)V
       596: aload_0
       597: getfield      #25                 // Field km:LKeyboardMenu;
       600: iconst_3
       601: aload_0
       602: getfield      #26                 // Field mp:LMainProgram;
       605: getfield      #78                 // Field MainProgram.mes2_name:Ljava/lang/String;
       608: invokevirtual #74                 // Method KeyboardMenu.setMessage:(ILjava/lang/String;)V
       611: aload_0
       612: getfield      #26                 // Field mp:LMainProgram;
       615: iconst_3
       616: iconst_3
       617: iconst_3
       618: invokevirtual #75                 // Method MainProgram.addSerifu:(III)V
       621: aload_0
       622: getfield      #25                 // Field km:LKeyboardMenu;
       625: iconst_3
       626: bipush        120
       628: sipush        150
       631: sipush        272
       634: getstatic     #76                 // Field java/awt/Color.cyan:Ljava/awt/Color;
       637: invokevirtual #77                 // Method KeyboardMenu.activeSerifu:(IIIILjava/awt/Color;)V
       640: aload_0
       641: getfield      #25                 // Field km:LKeyboardMenu;
       644: sipush        300
       647: putfield      #40                 // Field KeyboardMenu.mode:I
       650: aload_0
       651: getfield      #4                  // Field co_j:LCharacterObject;
       654: sipush        1010
       657: putfield      #56                 // Field CharacterObject.pt:I
       660: aload_0
       661: getfield      #4                  // Field co_j:LCharacterObject;
       664: iconst_0
       665: putfield      #36                 // Field CharacterObject.ac:I
       668: goto          1295
       671: aload_0
       672: iload         5
       674: iload         6
       676: invokevirtual #111                // Method getBGZ:(II)I
       679: sipush        218
       682: if_icmpne     867
       685: aload_0
       686: getfield      #25                 // Field km:LKeyboardMenu;
       689: iconst_4
       690: invokevirtual #72                 // Method KeyboardMenu.init1:(I)V
       693: aload_0
       694: getfield      #25                 // Field km:LKeyboardMenu;
       697: iconst_4
       698: bipush        120
       700: bipush        42
       702: sipush        216
       705: sipush        234
       708: invokevirtual #113                // Method KeyboardMenu.onKao:(IIIII)V
       711: aload_0
       712: getfield      #38                 // Field shop_kattaitem:I
       715: ifge          783
       718: aload_0
       719: getfield      #25                 // Field km:LKeyboardMenu;
       722: iconst_3
       723: invokevirtual #72                 // Method KeyboardMenu.init1:(I)V
       726: aload_0
       727: getfield      #25                 // Field km:LKeyboardMenu;
       730: iconst_3
       731: aload_0
       732: getfield      #26                 // Field mp:LMainProgram;
       735: getfield      #95                 // Field MainProgram.shop_name:Ljava/lang/String;
       738: invokevirtual #74                 // Method KeyboardMenu.setMessage:(ILjava/lang/String;)V
       741: aload_0
       742: getfield      #26                 // Field mp:LMainProgram;
       745: iconst_3
       746: iconst_5
       747: iconst_3
       748: invokevirtual #75                 // Method MainProgram.addSerifu:(III)V
       751: aload_0
       752: getfield      #25                 // Field km:LKeyboardMenu;
       755: iconst_3
       756: bipush        120
       758: sipush        150
       761: sipush        216
       764: getstatic     #76                 // Field java/awt/Color.cyan:Ljava/awt/Color;
       767: invokevirtual #77                 // Method KeyboardMenu.activeSerifu:(IIIILjava/awt/Color;)V
       770: aload_0
       771: getfield      #25                 // Field km:LKeyboardMenu;
       774: sipush        400
       777: putfield      #40                 // Field KeyboardMenu.mode:I
       780: goto          846
       783: aload_0
       784: getfield      #25                 // Field km:LKeyboardMenu;
       787: iconst_3
       788: invokevirtual #72                 // Method KeyboardMenu.init1:(I)V
       791: aload_0
       792: getfield      #25                 // Field km:LKeyboardMenu;
       795: iconst_3
       796: aload_0
       797: getfield      #26                 // Field mp:LMainProgram;
       800: getfield      #95                 // Field MainProgram.shop_name:Ljava/lang/String;
       803: invokevirtual #74                 // Method KeyboardMenu.setMessage:(ILjava/lang/String;)V
       806: aload_0
       807: getfield      #26                 // Field mp:LMainProgram;
       810: iconst_3
       811: bipush        8
       813: iconst_3
       814: invokevirtual #75                 // Method MainProgram.addSerifu:(III)V
       817: aload_0
       818: getfield      #25                 // Field km:LKeyboardMenu;
       821: iconst_3
       822: bipush        120
       824: sipush        150
       827: sipush        216
       830: getstatic     #76                 // Field java/awt/Color.cyan:Ljava/awt/Color;
       833: invokevirtual #77                 // Method KeyboardMenu.activeSerifu:(IIIILjava/awt/Color;)V
       836: aload_0
       837: getfield      #25                 // Field km:LKeyboardMenu;
       840: sipush        210
       843: putfield      #40                 // Field KeyboardMenu.mode:I
       846: aload_0
       847: getfield      #4                  // Field co_j:LCharacterObject;
       850: sipush        1010
       853: putfield      #56                 // Field CharacterObject.pt:I
       856: aload_0
       857: getfield      #4                  // Field co_j:LCharacterObject;
       860: iconst_0
       861: putfield      #36                 // Field CharacterObject.ac:I
       864: goto          1295
       867: aload_0
       868: iload         5
       870: iload         6
       872: invokevirtual #111                // Method getBGZ:(II)I
       875: sipush        219
       878: if_icmpne     1295
       881: aload_0
       882: getfield      #25                 // Field km:LKeyboardMenu;
       885: iconst_4
       886: invokevirtual #72                 // Method KeyboardMenu.init1:(I)V
       889: aload_0
       890: getfield      #25                 // Field km:LKeyboardMenu;
       893: iconst_4
       894: bipush        120
       896: bipush        42
       898: sipush        272
       901: sipush        236
       904: invokevirtual #113                // Method KeyboardMenu.onKao:(IIIII)V
       907: aload_0
       908: getfield      #25                 // Field km:LKeyboardMenu;
       911: iconst_3
       912: invokevirtual #72                 // Method KeyboardMenu.init1:(I)V
       915: aload_0
       916: getfield      #25                 // Field km:LKeyboardMenu;
       919: iconst_3
       920: aload_0
       921: getfield      #26                 // Field mp:LMainProgram;
       924: getfield      #106                // Field MainProgram.setumei_name:Ljava/lang/String;
       927: invokevirtual #74                 // Method KeyboardMenu.setMessage:(ILjava/lang/String;)V
       930: aload_0
       931: getfield      #26                 // Field mp:LMainProgram;
       934: iconst_3
       935: bipush        9
       937: iconst_3
       938: invokevirtual #75                 // Method MainProgram.addSerifu:(III)V
       941: aload_0
       942: getfield      #25                 // Field km:LKeyboardMenu;
       945: iconst_3
       946: bipush        120
       948: sipush        150
       951: sipush        272
       954: getstatic     #76                 // Field java/awt/Color.cyan:Ljava/awt/Color;
       957: invokevirtual #77                 // Method KeyboardMenu.activeSerifu:(IIIILjava/awt/Color;)V
       960: aload_0
       961: getfield      #25                 // Field km:LKeyboardMenu;
       964: sipush        500
       967: putfield      #40                 // Field KeyboardMenu.mode:I
       970: aload_0
       971: getfield      #4                  // Field co_j:LCharacterObject;
       974: sipush        1010
       977: putfield      #56                 // Field CharacterObject.pt:I
       980: aload_0
       981: getfield      #4                  // Field co_j:LCharacterObject;
       984: iconst_0
       985: putfield      #36                 // Field CharacterObject.ac:I
       988: goto          1295
       991: aload_0
       992: getfield      #24                 // Field gk:LGameKey;
       995: getfield      #114                // Field GameKey.up_f:Z
       998: iconst_1
       999: if_icmpne     1039
      1002: aload_0
      1003: iload         5
      1005: iload         6
      1007: bipush        32
      1009: isub
      1010: invokevirtual #111                // Method getBGZ:(II)I
      1013: sipush        221
      1016: if_icmpne     1295
      1019: aload_0
      1020: getfield      #4                  // Field co_j:LCharacterObject;
      1023: bipush        -4
      1025: putfield      #34                 // Field CharacterObject.vy:I
      1028: aload_0
      1029: getfield      #4                  // Field co_j:LCharacterObject;
      1032: iconst_m1
      1033: putfield      #36                 // Field CharacterObject.ac:I
      1036: goto          1295
      1039: aload_0
      1040: getfield      #24                 // Field gk:LGameKey;
      1043: getfield      #115                // Field GameKey.down_f:Z
      1046: iconst_1
      1047: if_icmpne     1086
      1050: aload_0
      1051: iload         5
      1053: iload         6
      1055: bipush        32
      1057: iadd
      1058: invokevirtual #111                // Method getBGZ:(II)I
      1061: sipush        221
      1064: if_icmpne     1295
      1067: aload_0
      1068: getfield      #4                  // Field co_j:LCharacterObject;
      1071: iconst_4
      1072: putfield      #34                 // Field CharacterObject.vy:I
      1075: aload_0
      1076: getfield      #4                  // Field co_j:LCharacterObject;
      1079: iconst_m1
      1080: putfield      #36                 // Field CharacterObject.ac:I
      1083: goto          1295
      1086: aload_0
      1087: getfield      #24                 // Field gk:LGameKey;
      1090: getfield      #116                // Field GameKey.left_f:Z
      1093: iconst_1
      1094: if_icmpne     1193
      1097: aload_0
      1098: getfield      #4                  // Field co_j:LCharacterObject;
      1101: iconst_0
      1102: putfield      #35                 // Field CharacterObject.muki:I
      1105: aload_0
      1106: iload         5
      1108: bipush        32
      1110: isub
      1111: iload         6
      1113: invokevirtual #111                // Method getBGZ:(II)I
      1116: sipush        222
      1119: if_icmpne     1139
      1122: aload_0
      1123: getfield      #4                  // Field co_j:LCharacterObject;
      1126: bipush        -4
      1128: putfield      #33                 // Field CharacterObject.vx:I
      1131: aload_0
      1132: getfield      #4                  // Field co_j:LCharacterObject;
      1135: iconst_m1
      1136: putfield      #36                 // Field CharacterObject.ac:I
      1139: aload_0
      1140: iload         5
      1142: bipush        32
      1144: iadd
      1145: iload         6
      1147: invokevirtual #111                // Method getBGZ:(II)I
      1150: sipush        212
      1153: if_icmplt     1295
      1156: aload_0
      1157: iload         5
      1159: bipush        32
      1161: iadd
      1162: iload         6
      1164: invokevirtual #111                // Method getBGZ:(II)I
      1167: sipush        215
      1170: if_icmpgt     1295
      1173: aload_0
      1174: getfield      #4                  // Field co_j:LCharacterObject;
      1177: bipush        -4
      1179: putfield      #33                 // Field CharacterObject.vx:I
      1182: aload_0
      1183: getfield      #4                  // Field co_j:LCharacterObject;
      1186: iconst_m1
      1187: putfield      #36                 // Field CharacterObject.ac:I
      1190: goto          1295
      1193: aload_0
      1194: getfield      #24                 // Field gk:LGameKey;
      1197: getfield      #117                // Field GameKey.right_f:Z
      1200: iconst_1
      1201: if_icmpne     1295
      1204: aload_0
      1205: getfield      #4                  // Field co_j:LCharacterObject;
      1208: iconst_1
      1209: putfield      #35                 // Field CharacterObject.muki:I
      1212: aload_0
      1213: iload         5
      1215: bipush        32
      1217: iadd
      1218: iload         6
      1220: invokevirtual #111                // Method getBGZ:(II)I
      1223: sipush        222
      1226: if_icmpne     1245
      1229: aload_0
      1230: getfield      #4                  // Field co_j:LCharacterObject;
      1233: iconst_4
      1234: putfield      #33                 // Field CharacterObject.vx:I
      1237: aload_0
      1238: getfield      #4                  // Field co_j:LCharacterObject;
      1241: iconst_m1
      1242: putfield      #36                 // Field CharacterObject.ac:I
      1245: aload_0
      1246: iload         5
      1248: bipush        32
      1250: isub
      1251: iload         6
      1253: invokevirtual #111                // Method getBGZ:(II)I
      1256: sipush        212
      1259: if_icmplt     1295
      1262: aload_0
      1263: iload         5
      1265: bipush        32
      1267: isub
      1268: iload         6
      1270: invokevirtual #111                // Method getBGZ:(II)I
      1273: sipush        215
      1276: if_icmpgt     1295
      1279: aload_0
      1280: getfield      #4                  // Field co_j:LCharacterObject;
      1283: iconst_4
      1284: putfield      #33                 // Field CharacterObject.vx:I
      1287: aload_0
      1288: getfield      #4                  // Field co_j:LCharacterObject;
      1291: iconst_m1
      1292: putfield      #36                 // Field CharacterObject.ac:I
      1295: aload_0
      1296: getfield      #4                  // Field co_j:LCharacterObject;
      1299: getfield      #33                 // Field CharacterObject.vx:I
      1302: ifne          1315
      1305: aload_0
      1306: getfield      #4                  // Field co_j:LCharacterObject;
      1309: getfield      #34                 // Field CharacterObject.vy:I
      1312: ifeq          1841
      1315: aload_0
      1316: getfield      #4                  // Field co_j:LCharacterObject;
      1319: dup
      1320: getfield      #36                 // Field CharacterObject.ac:I
      1323: iconst_1
      1324: iadd
      1325: putfield      #36                 // Field CharacterObject.ac:I
      1328: aload_0
      1329: getfield      #4                  // Field co_j:LCharacterObject;
      1332: getfield      #36                 // Field CharacterObject.ac:I
      1335: iconst_3
      1336: if_icmple     1347
      1339: aload_0
      1340: getfield      #4                  // Field co_j:LCharacterObject;
      1343: iconst_0
      1344: putfield      #36                 // Field CharacterObject.ac:I
      1347: iload         5
      1349: aload_0
      1350: getfield      #4                  // Field co_j:LCharacterObject;
      1353: getfield      #33                 // Field CharacterObject.vx:I
      1356: iadd
      1357: istore        5
      1359: iload         6
      1361: aload_0
      1362: getfield      #4                  // Field co_j:LCharacterObject;
      1365: getfield      #34                 // Field CharacterObject.vy:I
      1368: iadd
      1369: istore        6
      1371: aload_0
      1372: getfield      #4                  // Field co_j:LCharacterObject;
      1375: getfield      #33                 // Field CharacterObject.vx:I
      1378: ifeq          1416
      1381: aload_0
      1382: getfield      #4                  // Field co_j:LCharacterObject;
      1385: getfield      #36                 // Field CharacterObject.ac:I
      1388: iconst_1
      1389: if_icmpgt     1404
      1392: aload_0
      1393: getfield      #4                  // Field co_j:LCharacterObject;
      1396: bipush        103
      1398: putfield      #56                 // Field CharacterObject.pt:I
      1401: goto          1497
      1404: aload_0
      1405: getfield      #4                  // Field co_j:LCharacterObject;
      1408: bipush        104
      1410: putfield      #56                 // Field CharacterObject.pt:I
      1413: goto          1497
      1416: aload_0
      1417: getfield      #4                  // Field co_j:LCharacterObject;
      1420: getfield      #34                 // Field CharacterObject.vy:I
      1423: iflt          1463
      1426: aload_0
      1427: getfield      #4                  // Field co_j:LCharacterObject;
      1430: getfield      #36                 // Field CharacterObject.ac:I
      1433: iconst_1
      1434: if_icmpgt     1450
      1437: aload_0
      1438: getfield      #4                  // Field co_j:LCharacterObject;
      1441: sipush        202
      1444: putfield      #56                 // Field CharacterObject.pt:I
      1447: goto          1497
      1450: aload_0
      1451: getfield      #4                  // Field co_j:LCharacterObject;
      1454: sipush        203
      1457: putfield      #56                 // Field CharacterObject.pt:I
      1460: goto          1497
      1463: aload_0
      1464: getfield      #4                  // Field co_j:LCharacterObject;
      1467: getfield      #36                 // Field CharacterObject.ac:I
      1470: iconst_1
      1471: if_icmpgt     1487
      1474: aload_0
      1475: getfield      #4                  // Field co_j:LCharacterObject;
      1478: sipush        204
      1481: putfield      #56                 // Field CharacterObject.pt:I
      1484: goto          1497
      1487: aload_0
      1488: getfield      #4                  // Field co_j:LCharacterObject;
      1491: sipush        205
      1494: putfield      #56                 // Field CharacterObject.pt:I
      1497: iload         5
      1499: bipush        32
      1501: irem
      1502: ifne          1691
      1505: iload         6
      1507: bipush        32
      1509: irem
      1510: ifne          1691
      1513: aload_0
      1514: iload         5
      1516: iload         6
      1518: invokevirtual #111                // Method getBGZ:(II)I
      1521: istore_1
      1522: iload_1
      1523: sipush        220
      1526: if_icmpeq     1571
      1529: iload_1
      1530: sipush        223
      1533: if_icmplt     1543
      1536: iload_1
      1537: sipush        227
      1540: if_icmple     1571
      1543: iload_1
      1544: sipush        216
      1547: if_icmplt     1557
      1550: iload_1
      1551: sipush        219
      1554: if_icmple     1571
      1557: iload_1
      1558: sipush        206
      1561: if_icmplt     1595
      1564: iload_1
      1565: sipush        209
      1568: if_icmpgt     1595
      1571: aload_0
      1572: getfield      #4                  // Field co_j:LCharacterObject;
      1575: iconst_0
      1576: putfield      #33                 // Field CharacterObject.vx:I
      1579: aload_0
      1580: getfield      #4                  // Field co_j:LCharacterObject;
      1583: iconst_0
      1584: putfield      #34                 // Field CharacterObject.vy:I
      1587: aload_0
      1588: getfield      #4                  // Field co_j:LCharacterObject;
      1591: iconst_0
      1592: putfield      #36                 // Field CharacterObject.ac:I
      1595: iconst_0
      1596: istore_1
      1597: aload_0
      1598: getfield      #4                  // Field co_j:LCharacterObject;
      1601: getfield      #33                 // Field CharacterObject.vx:I
      1604: ifle          1622
      1607: aload_0
      1608: iload         5
      1610: bipush        32
      1612: iadd
      1613: iload         6
      1615: invokevirtual #111                // Method getBGZ:(II)I
      1618: istore_1
      1619: goto          1644
      1622: aload_0
      1623: getfield      #4                  // Field co_j:LCharacterObject;
      1626: getfield      #33                 // Field CharacterObject.vx:I
      1629: ifge          1644
      1632: aload_0
      1633: iload         5
      1635: bipush        32
      1637: isub
      1638: iload         6
      1640: invokevirtual #111                // Method getBGZ:(II)I
      1643: istore_1
      1644: iload_1
      1645: sipush        212
      1648: if_icmplt     1691
      1651: iload_1
      1652: sipush        215
      1655: if_icmpgt     1691
      1658: aload_0
      1659: getfield      #4                  // Field co_j:LCharacterObject;
      1662: iconst_0
      1663: putfield      #33                 // Field CharacterObject.vx:I
      1666: aload_0
      1667: getfield      #4                  // Field co_j:LCharacterObject;
      1670: iconst_0
      1671: putfield      #34                 // Field CharacterObject.vy:I
      1674: aload_0
      1675: getfield      #4                  // Field co_j:LCharacterObject;
      1678: bipush        100
      1680: putfield      #56                 // Field CharacterObject.pt:I
      1683: aload_0
      1684: getfield      #4                  // Field co_j:LCharacterObject;
      1687: iconst_0
      1688: putfield      #36                 // Field CharacterObject.ac:I
      1691: iload         5
      1693: bipush        -32
      1695: if_icmpgt     1729
      1698: bipush        -32
      1700: istore        5
      1702: aload_0
      1703: getfield      #4                  // Field co_j:LCharacterObject;
      1706: iconst_0
      1707: putfield      #33                 // Field CharacterObject.vx:I
      1710: aload_0
      1711: getfield      #4                  // Field co_j:LCharacterObject;
      1714: iconst_0
      1715: putfield      #34                 // Field CharacterObject.vy:I
      1718: aload_0
      1719: getfield      #4                  // Field co_j:LCharacterObject;
      1722: iconst_0
      1723: putfield      #36                 // Field CharacterObject.ac:I
      1726: goto          1766
      1729: iload         5
      1731: sipush        480
      1734: if_icmplt     1766
      1737: sipush        480
      1740: istore        5
      1742: aload_0
      1743: getfield      #4                  // Field co_j:LCharacterObject;
      1746: iconst_0
      1747: putfield      #33                 // Field CharacterObject.vx:I
      1750: aload_0
      1751: getfield      #4                  // Field co_j:LCharacterObject;
      1754: iconst_0
      1755: putfield      #34                 // Field CharacterObject.vy:I
      1758: aload_0
      1759: getfield      #4                  // Field co_j:LCharacterObject;
      1762: iconst_0
      1763: putfield      #36                 // Field CharacterObject.ac:I
      1766: iload         6
      1768: bipush        -32
      1770: if_icmpgt     1804
      1773: bipush        -32
      1775: istore        6
      1777: aload_0
      1778: getfield      #4                  // Field co_j:LCharacterObject;
      1781: iconst_0
      1782: putfield      #33                 // Field CharacterObject.vx:I
      1785: aload_0
      1786: getfield      #4                  // Field co_j:LCharacterObject;
      1789: iconst_0
      1790: putfield      #34                 // Field CharacterObject.vy:I
      1793: aload_0
      1794: getfield      #4                  // Field co_j:LCharacterObject;
      1797: iconst_0
      1798: putfield      #36                 // Field CharacterObject.ac:I
      1801: goto          1841
      1804: iload         6
      1806: sipush        288
      1809: if_icmplt     1841
      1812: sipush        288
      1815: istore        6
      1817: aload_0
      1818: getfield      #4                  // Field co_j:LCharacterObject;
      1821: iconst_0
      1822: putfield      #33                 // Field CharacterObject.vx:I
      1825: aload_0
      1826: getfield      #4                  // Field co_j:LCharacterObject;
      1829: iconst_0
      1830: putfield      #34                 // Field CharacterObject.vy:I
      1833: aload_0
      1834: getfield      #4                  // Field co_j:LCharacterObject;
      1837: iconst_0
      1838: putfield      #36                 // Field CharacterObject.ac:I
      1841: aload_0
      1842: getfield      #4                  // Field co_j:LCharacterObject;
      1845: iload         5
      1847: putfield      #31                 // Field CharacterObject.x:I
      1850: aload_0
      1851: getfield      #4                  // Field co_j:LCharacterObject;
      1854: iload         6
      1856: putfield      #32                 // Field CharacterObject.y:I
      1859: return
      LineNumberTable:
        line 15759: 0
        line 15760: 9
        line 15763: 18
        line 15765: 27
        line 15769: 47
        line 15770: 60
        line 15773: 80
        line 15774: 91
        line 15776: 101
        line 15777: 110
        line 15779: 138
        line 15783: 148
        line 15787: 159
        line 15789: 167
        line 15790: 173
        line 15791: 180
        line 15792: 188
        line 15795: 193
        line 15797: 205
        line 15799: 233
        line 15803: 244
        line 15804: 247
        line 15805: 253
        line 15806: 259
        line 15808: 279
        line 15810: 282
        line 15811: 293
        line 15813: 305
        line 15814: 312
        line 15815: 319
        line 15816: 327
        line 15817: 337
        line 15818: 340
        line 15805: 343
        line 15821: 353
        line 15804: 362
        line 15826: 375
        line 15827: 381
        line 15828: 388
        line 15829: 396
        line 15832: 412
        line 15835: 425
        line 15839: 439
        line 15840: 447
        line 15843: 465
        line 15844: 473
        line 15845: 488
        line 15846: 498
        line 15848: 517
        line 15851: 527
        line 15852: 537
        line 15854: 548
        line 15858: 562
        line 15859: 570
        line 15862: 588
        line 15863: 596
        line 15864: 611
        line 15865: 621
        line 15867: 640
        line 15870: 650
        line 15871: 660
        line 15873: 671
        line 15877: 685
        line 15879: 693
        line 15881: 711
        line 15885: 718
        line 15886: 726
        line 15887: 741
        line 15889: 751
        line 15891: 770
        line 15897: 783
        line 15898: 791
        line 15899: 806
        line 15901: 817
        line 15903: 836
        line 15907: 846
        line 15908: 856
        line 15910: 867
        line 15914: 881
        line 15916: 889
        line 15919: 907
        line 15920: 915
        line 15921: 930
        line 15922: 941
        line 15924: 960
        line 15927: 970
        line 15928: 980
        line 15931: 991
        line 15933: 1002
        line 15935: 1019
        line 15936: 1028
        line 15939: 1039
        line 15941: 1050
        line 15943: 1067
        line 15944: 1075
        line 15947: 1086
        line 15949: 1097
        line 15950: 1105
        line 15952: 1122
        line 15953: 1131
        line 15955: 1139
        line 15957: 1173
        line 15958: 1182
        line 15961: 1193
        line 15963: 1204
        line 15964: 1212
        line 15966: 1229
        line 15967: 1237
        line 15969: 1245
        line 15971: 1279
        line 15972: 1287
        line 15978: 1295
        line 15979: 1315
        line 15980: 1328
        line 15983: 1347
        line 15984: 1359
        line 15987: 1371
        line 15989: 1381
        line 15990: 1392
        line 15993: 1404
        line 15996: 1416
        line 15998: 1426
        line 15999: 1437
        line 16002: 1450
        line 16007: 1463
        line 16008: 1474
        line 16011: 1487
        line 16016: 1497
        line 16019: 1513
        line 16021: 1522
        line 16023: 1571
        line 16024: 1579
        line 16025: 1587
        line 16029: 1595
        line 16030: 1597
        line 16032: 1607
        line 16034: 1622
        line 16036: 1632
        line 16038: 1644
        line 16040: 1658
        line 16041: 1666
        line 16042: 1674
        line 16043: 1683
        line 16049: 1691
        line 16051: 1698
        line 16053: 1702
        line 16054: 1710
        line 16055: 1718
        line 16057: 1729
        line 16059: 1737
        line 16061: 1742
        line 16062: 1750
        line 16063: 1758
        line 16065: 1766
        line 16067: 1773
        line 16069: 1777
        line 16070: 1785
        line 16071: 1793
        line 16073: 1804
        line 16075: 1812
        line 16077: 1817
        line 16078: 1825
        line 16079: 1833
        line 16084: 1841
        line 16085: 1850
        line 16086: 1859

  void circleCLS(int);
    descriptor: (I)V
    flags: (0x0000)
    Code:
      stack=7, locals=7, args_size=2
         0: iconst_0
         1: istore        6
         3: goto          98
         6: iload         6
         8: i2f
         9: ldc           #118                // float 0.2617992f
        11: fmul
        12: f2d
        13: invokestatic  #119                // Method java/lang/Math.sin:(D)D
        16: dstore_2
        17: aload_0
        18: getfield      #20                 // Field cc_p1_y:[I
        21: iload         6
        23: sipush        160
        26: dload_2
        27: iload_1
        28: i2d
        29: dmul
        30: d2i
        31: iadd
        32: iastore
        33: iload         6
        35: i2f
        36: ldc           #118                // float 0.2617992f
        38: fmul
        39: f2d
        40: invokestatic  #120                // Method java/lang/Math.cos:(D)D
        43: dstore        4
        45: aload_0
        46: getfield      #19                 // Field cc_p1_x:[I
        49: iload         6
        51: sipush        256
        54: dload         4
        56: iload_1
        57: i2d
        58: dmul
        59: d2i
        60: iadd
        61: iastore
        62: aload_0
        63: getfield      #22                 // Field cc_p2_y:[I
        66: iload         6
        68: sipush        160
        71: dload_2
        72: iload_1
        73: i2d
        74: dmul
        75: d2i
        76: isub
        77: iastore
        78: aload_0
        79: getfield      #21                 // Field cc_p2_x:[I
        82: iload         6
        84: sipush        256
        87: dload         4
        89: iload_1
        90: i2d
        91: dmul
        92: d2i
        93: isub
        94: iastore
        95: iinc          6, 1
        98: iload         6
       100: bipush        12
       102: if_icmple     6
       105: aload_0
       106: getfield      #23                 // Field gg:LGameGraphics;
       109: getfield      #65                 // Field GameGraphics.os_g:Ljava/awt/Graphics;
       112: getstatic     #121                // Field java/awt/Color.black:Ljava/awt/Color;
       115: invokevirtual #122                // Method java/awt/Graphics.setColor:(Ljava/awt/Color;)V
       118: aload_0
       119: getfield      #23                 // Field gg:LGameGraphics;
       122: getfield      #65                 // Field GameGraphics.os_g:Ljava/awt/Graphics;
       125: aload_0
       126: getfield      #19                 // Field cc_p1_x:[I
       129: aload_0
       130: getfield      #20                 // Field cc_p1_y:[I
       133: bipush        17
       135: invokevirtual #123                // Method java/awt/Graphics.fillPolygon:([I[II)V
       138: aload_0
       139: getfield      #23                 // Field gg:LGameGraphics;
       142: getfield      #65                 // Field GameGraphics.os_g:Ljava/awt/Graphics;
       145: aload_0
       146: getfield      #21                 // Field cc_p2_x:[I
       149: aload_0
       150: getfield      #22                 // Field cc_p2_y:[I
       153: bipush        17
       155: invokevirtual #123                // Method java/awt/Graphics.fillPolygon:([I[II)V
       158: return
      LineNumberTable:
        line 16096: 0
        line 16100: 6
        line 16101: 17
        line 16105: 33
        line 16106: 45
        line 16115: 62
        line 16116: 78
        line 16096: 95
        line 16119: 105
        line 16120: 118
        line 16121: 138
        line 16122: 158

  void squareCLS(int, int);
    descriptor: (II)V
    flags: (0x0000)
    Code:
      stack=6, locals=10, args_size=3
         0: ldc2_w        #124                // double 0.017453292519943295d
         3: dstore        7
         5: aload_0
         6: getfield      #19                 // Field cc_p1_x:[I
         9: iconst_0
        10: aload_0
        11: getfield      #126                // Field cc_kakudo:I
        14: iconst_0
        15: iadd
        16: i2d
        17: dload         7
        19: dmul
        20: invokestatic  #120                // Method java/lang/Math.cos:(D)D
        23: iload_1
        24: i2d
        25: dmul
        26: d2i
        27: sipush        256
        30: iadd
        31: iastore
        32: aload_0
        33: getfield      #20                 // Field cc_p1_y:[I
        36: iconst_0
        37: aload_0
        38: getfield      #126                // Field cc_kakudo:I
        41: iconst_0
        42: iadd
        43: i2d
        44: dload         7
        46: dmul
        47: invokestatic  #119                // Method java/lang/Math.sin:(D)D
        50: iload_1
        51: i2d
        52: dmul
        53: d2i
        54: sipush        160
        57: iadd
        58: iastore
        59: aload_0
        60: getfield      #19                 // Field cc_p1_x:[I
        63: iconst_1
        64: aload_0
        65: getfield      #126                // Field cc_kakudo:I
        68: bipush        90
        70: iadd
        71: i2d
        72: dload         7
        74: dmul
        75: invokestatic  #120                // Method java/lang/Math.cos:(D)D
        78: iload_1
        79: i2d
        80: dmul
        81: d2i
        82: sipush        256
        85: iadd
        86: iastore
        87: aload_0
        88: getfield      #20                 // Field cc_p1_y:[I
        91: iconst_1
        92: aload_0
        93: getfield      #126                // Field cc_kakudo:I
        96: bipush        90
        98: iadd
        99: i2d
       100: dload         7
       102: dmul
       103: invokestatic  #119                // Method java/lang/Math.sin:(D)D
       106: iload_1
       107: i2d
       108: dmul
       109: d2i
       110: sipush        160
       113: iadd
       114: iastore
       115: aload_0
       116: getfield      #19                 // Field cc_p1_x:[I
       119: iconst_2
       120: aload_0
       121: getfield      #126                // Field cc_kakudo:I
       124: sipush        180
       127: iadd
       128: i2d
       129: dload         7
       131: dmul
       132: invokestatic  #120                // Method java/lang/Math.cos:(D)D
       135: iload_1
       136: i2d
       137: dmul
       138: d2i
       139: sipush        256
       142: iadd
       143: iastore
       144: aload_0
       145: getfield      #20                 // Field cc_p1_y:[I
       148: iconst_2
       149: aload_0
       150: getfield      #126                // Field cc_kakudo:I
       153: sipush        180
       156: iadd
       157: i2d
       158: dload         7
       160: dmul
       161: invokestatic  #119                // Method java/lang/Math.sin:(D)D
       164: iload_1
       165: i2d
       166: dmul
       167: d2i
       168: sipush        160
       171: iadd
       172: iastore
       173: aload_0
       174: getfield      #19                 // Field cc_p1_x:[I
       177: iconst_3
       178: aload_0
       179: getfield      #126                // Field cc_kakudo:I
       182: sipush        180
       185: iadd
       186: i2d
       187: dload         7
       189: dmul
       190: invokestatic  #120                // Method java/lang/Math.cos:(D)D
       193: ldc2_w        #127                // double 500.0d
       196: dmul
       197: d2i
       198: sipush        256
       201: iadd
       202: iastore
       203: aload_0
       204: getfield      #20                 // Field cc_p1_y:[I
       207: iconst_3
       208: aload_0
       209: getfield      #126                // Field cc_kakudo:I
       212: sipush        180
       215: iadd
       216: i2d
       217: dload         7
       219: dmul
       220: invokestatic  #119                // Method java/lang/Math.sin:(D)D
       223: ldc2_w        #127                // double 500.0d
       226: dmul
       227: d2i
       228: sipush        160
       231: iadd
       232: iastore
       233: aload_0
       234: getfield      #19                 // Field cc_p1_x:[I
       237: iconst_4
       238: aload_0
       239: getfield      #126                // Field cc_kakudo:I
       242: sipush        135
       245: iadd
       246: i2d
       247: dload         7
       249: dmul
       250: invokestatic  #120                // Method java/lang/Math.cos:(D)D
       253: ldc2_w        #129                // double 700.0d
       256: dmul
       257: d2i
       258: sipush        256
       261: iadd
       262: iastore
       263: aload_0
       264: getfield      #20                 // Field cc_p1_y:[I
       267: iconst_4
       268: aload_0
       269: getfield      #126                // Field cc_kakudo:I
       272: sipush        135
       275: iadd
       276: i2d
       277: dload         7
       279: dmul
       280: invokestatic  #119                // Method java/lang/Math.sin:(D)D
       283: ldc2_w        #129                // double 700.0d
       286: dmul
       287: d2i
       288: sipush        160
       291: iadd
       292: iastore
       293: aload_0
       294: getfield      #19                 // Field cc_p1_x:[I
       297: iconst_5
       298: aload_0
       299: getfield      #126                // Field cc_kakudo:I
       302: bipush        45
       304: iadd
       305: i2d
       306: dload         7
       308: dmul
       309: invokestatic  #120                // Method java/lang/Math.cos:(D)D
       312: ldc2_w        #129                // double 700.0d
       315: dmul
       316: d2i
       317: sipush        256
       320: iadd
       321: iastore
       322: aload_0
       323: getfield      #20                 // Field cc_p1_y:[I
       326: iconst_5
       327: aload_0
       328: getfield      #126                // Field cc_kakudo:I
       331: bipush        45
       333: iadd
       334: i2d
       335: dload         7
       337: dmul
       338: invokestatic  #119                // Method java/lang/Math.sin:(D)D
       341: ldc2_w        #129                // double 700.0d
       344: dmul
       345: d2i
       346: sipush        160
       349: iadd
       350: iastore
       351: aload_0
       352: getfield      #19                 // Field cc_p1_x:[I
       355: bipush        6
       357: aload_0
       358: getfield      #126                // Field cc_kakudo:I
       361: iconst_0
       362: iadd
       363: i2d
       364: dload         7
       366: dmul
       367: invokestatic  #120                // Method java/lang/Math.cos:(D)D
       370: ldc2_w        #127                // double 500.0d
       373: dmul
       374: d2i
       375: sipush        256
       378: iadd
       379: iastore
       380: aload_0
       381: getfield      #20                 // Field cc_p1_y:[I
       384: bipush        6
       386: aload_0
       387: getfield      #126                // Field cc_kakudo:I
       390: iconst_0
       391: iadd
       392: i2d
       393: dload         7
       395: dmul
       396: invokestatic  #119                // Method java/lang/Math.sin:(D)D
       399: ldc2_w        #127                // double 500.0d
       402: dmul
       403: d2i
       404: sipush        160
       407: iadd
       408: iastore
       409: aload_0
       410: getfield      #21                 // Field cc_p2_x:[I
       413: iconst_0
       414: aload_0
       415: getfield      #126                // Field cc_kakudo:I
       418: sipush        180
       421: iadd
       422: i2d
       423: dload         7
       425: dmul
       426: invokestatic  #120                // Method java/lang/Math.cos:(D)D
       429: iload_1
       430: i2d
       431: dmul
       432: d2i
       433: sipush        256
       436: iadd
       437: iastore
       438: aload_0
       439: getfield      #22                 // Field cc_p2_y:[I
       442: iconst_0
       443: aload_0
       444: getfield      #126                // Field cc_kakudo:I
       447: sipush        180
       450: iadd
       451: i2d
       452: dload         7
       454: dmul
       455: invokestatic  #119                // Method java/lang/Math.sin:(D)D
       458: iload_1
       459: i2d
       460: dmul
       461: d2i
       462: sipush        160
       465: iadd
       466: iastore
       467: aload_0
       468: getfield      #21                 // Field cc_p2_x:[I
       471: iconst_1
       472: aload_0
       473: getfield      #126                // Field cc_kakudo:I
       476: sipush        270
       479: iadd
       480: i2d
       481: dload         7
       483: dmul
       484: invokestatic  #120                // Method java/lang/Math.cos:(D)D
       487: iload_1
       488: i2d
       489: dmul
       490: d2i
       491: sipush        256
       494: iadd
       495: iastore
       496: aload_0
       497: getfield      #22                 // Field cc_p2_y:[I
       500: iconst_1
       501: aload_0
       502: getfield      #126                // Field cc_kakudo:I
       505: sipush        270
       508: iadd
       509: i2d
       510: dload         7
       512: dmul
       513: invokestatic  #119                // Method java/lang/Math.sin:(D)D
       516: iload_1
       517: i2d
       518: dmul
       519: d2i
       520: sipush        160
       523: iadd
       524: iastore
       525: aload_0
       526: getfield      #21                 // Field cc_p2_x:[I
       529: iconst_2
       530: aload_0
       531: getfield      #126                // Field cc_kakudo:I
       534: sipush        360
       537: iadd
       538: i2d
       539: dload         7
       541: dmul
       542: invokestatic  #120                // Method java/lang/Math.cos:(D)D
       545: iload_1
       546: i2d
       547: dmul
       548: d2i
       549: sipush        256
       552: iadd
       553: iastore
       554: aload_0
       555: getfield      #22                 // Field cc_p2_y:[I
       558: iconst_2
       559: aload_0
       560: getfield      #126                // Field cc_kakudo:I
       563: sipush        360
       566: iadd
       567: i2d
       568: dload         7
       570: dmul
       571: invokestatic  #119                // Method java/lang/Math.sin:(D)D
       574: iload_1
       575: i2d
       576: dmul
       577: d2i
       578: sipush        160
       581: iadd
       582: iastore
       583: aload_0
       584: getfield      #21                 // Field cc_p2_x:[I
       587: iconst_3
       588: aload_0
       589: getfield      #126                // Field cc_kakudo:I
       592: sipush        360
       595: iadd
       596: i2d
       597: dload         7
       599: dmul
       600: invokestatic  #120                // Method java/lang/Math.cos:(D)D
       603: ldc2_w        #127                // double 500.0d
       606: dmul
       607: d2i
       608: sipush        256
       611: iadd
       612: iastore
       613: aload_0
       614: getfield      #22                 // Field cc_p2_y:[I
       617: iconst_3
       618: aload_0
       619: getfield      #126                // Field cc_kakudo:I
       622: sipush        360
       625: iadd
       626: i2d
       627: dload         7
       629: dmul
       630: invokestatic  #119                // Method java/lang/Math.sin:(D)D
       633: ldc2_w        #127                // double 500.0d
       636: dmul
       637: d2i
       638: sipush        160
       641: iadd
       642: iastore
       643: aload_0
       644: getfield      #21                 // Field cc_p2_x:[I
       647: iconst_4
       648: aload_0
       649: getfield      #126                // Field cc_kakudo:I
       652: sipush        315
       655: iadd
       656: i2d
       657: dload         7
       659: dmul
       660: invokestatic  #120                // Method java/lang/Math.cos:(D)D
       663: ldc2_w        #129                // double 700.0d
       666: dmul
       667: d2i
       668: sipush        256
       671: iadd
       672: iastore
       673: aload_0
       674: getfield      #22                 // Field cc_p2_y:[I
       677: iconst_4
       678: aload_0
       679: getfield      #126                // Field cc_kakudo:I
       682: sipush        315
       685: iadd
       686: i2d
       687: dload         7
       689: dmul
       690: invokestatic  #119                // Method java/lang/Math.sin:(D)D
       693: ldc2_w        #129                // double 700.0d
       696: dmul
       697: d2i
       698: sipush        160
       701: iadd
       702: iastore
       703: aload_0
       704: getfield      #21                 // Field cc_p2_x:[I
       707: iconst_5
       708: aload_0
       709: getfield      #126                // Field cc_kakudo:I
       712: sipush        225
       715: iadd
       716: i2d
       717: dload         7
       719: dmul
       720: invokestatic  #120                // Method java/lang/Math.cos:(D)D
       723: ldc2_w        #129                // double 700.0d
       726: dmul
       727: d2i
       728: sipush        256
       731: iadd
       732: iastore
       733: aload_0
       734: getfield      #22                 // Field cc_p2_y:[I
       737: iconst_5
       738: aload_0
       739: getfield      #126                // Field cc_kakudo:I
       742: sipush        225
       745: iadd
       746: i2d
       747: dload         7
       749: dmul
       750: invokestatic  #119                // Method java/lang/Math.sin:(D)D
       753: ldc2_w        #129                // double 700.0d
       756: dmul
       757: d2i
       758: sipush        160
       761: iadd
       762: iastore
       763: aload_0
       764: getfield      #21                 // Field cc_p2_x:[I
       767: bipush        6
       769: aload_0
       770: getfield      #126                // Field cc_kakudo:I
       773: sipush        180
       776: iadd
       777: i2d
       778: dload         7
       780: dmul
       781: invokestatic  #120                // Method java/lang/Math.cos:(D)D
       784: ldc2_w        #127                // double 500.0d
       787: dmul
       788: d2i
       789: sipush        256
       792: iadd
       793: iastore
       794: aload_0
       795: getfield      #22                 // Field cc_p2_y:[I
       798: bipush        6
       800: aload_0
       801: getfield      #126                // Field cc_kakudo:I
       804: sipush        180
       807: iadd
       808: i2d
       809: dload         7
       811: dmul
       812: invokestatic  #119                // Method java/lang/Math.sin:(D)D
       815: ldc2_w        #127                // double 500.0d
       818: dmul
       819: d2i
       820: sipush        160
       823: iadd
       824: iastore
       825: aload_0
       826: getfield      #23                 // Field gg:LGameGraphics;
       829: getfield      #65                 // Field GameGraphics.os_g:Ljava/awt/Graphics;
       832: getstatic     #121                // Field java/awt/Color.black:Ljava/awt/Color;
       835: invokevirtual #122                // Method java/awt/Graphics.setColor:(Ljava/awt/Color;)V
       838: aload_0
       839: getfield      #23                 // Field gg:LGameGraphics;
       842: getfield      #65                 // Field GameGraphics.os_g:Ljava/awt/Graphics;
       845: aload_0
       846: getfield      #19                 // Field cc_p1_x:[I
       849: aload_0
       850: getfield      #20                 // Field cc_p1_y:[I
       853: bipush        7
       855: invokevirtual #123                // Method java/awt/Graphics.fillPolygon:([I[II)V
       858: aload_0
       859: getfield      #23                 // Field gg:LGameGraphics;
       862: getfield      #65                 // Field GameGraphics.os_g:Ljava/awt/Graphics;
       865: aload_0
       866: getfield      #21                 // Field cc_p2_x:[I
       869: aload_0
       870: getfield      #22                 // Field cc_p2_y:[I
       873: bipush        7
       875: invokevirtual #123                // Method java/awt/Graphics.fillPolygon:([I[II)V
       878: return
      LineNumberTable:
        line 16132: 0
        line 16133: 5
        line 16134: 32
        line 16135: 59
        line 16136: 87
        line 16137: 115
        line 16138: 144
        line 16139: 173
        line 16140: 203
        line 16141: 233
        line 16142: 263
        line 16143: 293
        line 16144: 322
        line 16145: 351
        line 16146: 380
        line 16148: 409
        line 16149: 438
        line 16150: 467
        line 16151: 496
        line 16152: 525
        line 16153: 554
        line 16154: 583
        line 16155: 613
        line 16156: 643
        line 16157: 673
        line 16158: 703
        line 16159: 733
        line 16160: 763
        line 16161: 794
        line 16163: 825
        line 16164: 838
        line 16165: 858
        line 16166: 878
}
SourceFile: "MasaoConstruction.java"
