Classfile /home/yappy/MasaoMakerSP/scripts/dis/mc2/KeyboardMenu.class
  Last modified Jun 30, 2003; size 14442 bytes
  SHA-256 checksum fc02cd469b40146b392848420fd03b82decef34169fa8bc2ab31f6caa730f8d0
  Compiled from "MasaoConstruction.java"
class KeyboardMenu
  minor version: 3
  major version: 45
  flags: (0x0020) ACC_SUPER
  this_class: #87                         // KeyboardMenu
  super_class: #88                        // java/lang/Object
  interfaces: 0, fields: 25, methods: 31, attributes: 1
Constant pool:
    #1 = Methodref          #88.#174      // java/lang/Object."<init>":()V
    #2 = Fieldref           #87.#175      // KeyboardMenu.c:[I
    #3 = Fieldref           #87.#176      // KeyboardMenu.x:[I
    #4 = Fieldref           #87.#177      // KeyboardMenu.y:[I
    #5 = Fieldref           #87.#178      // KeyboardMenu.width:[I
    #6 = Fieldref           #87.#179      // KeyboardMenu.selectedIndex:[I
    #7 = Fieldref           #87.#180      // KeyboardMenu.item_kazu:[I
    #8 = Class              #181          // java/lang/String
    #9 = Fieldref           #87.#182      // KeyboardMenu.message:[Ljava/lang/String;
   #10 = Class              #111          // "[[Ljava/lang/String;"
   #11 = Fieldref           #87.#183      // KeyboardMenu.item:[[Ljava/lang/String;
   #12 = Class              #113          // "[[I"
   #13 = Fieldref           #87.#184      // KeyboardMenu.item_int:[[I
   #14 = Class              #185          // java/awt/Color
   #15 = Fieldref           #87.#186      // KeyboardMenu.item_color:[Ljava/awt/Color;
   #16 = Fieldref           #87.#187      // KeyboardMenu.list_IDlist:[I
   #17 = Fieldref           #87.#188      // KeyboardMenu.aw:I
   #18 = Fieldref           #87.#189      // KeyboardMenu.mode:I
   #19 = Fieldref           #87.#190      // KeyboardMenu.kettei_c:I
   #20 = Fieldref           #87.#191      // KeyboardMenu.cancel_c:I
   #21 = Fieldref           #87.#192      // KeyboardMenu.gg:LGameGraphics;
   #22 = Fieldref           #87.#193      // KeyboardMenu.gk:LGameKey;
   #23 = Fieldref           #87.#194      // KeyboardMenu.name_crys:Ljava/lang/String;
   #24 = Fieldref           #195.#196     // GameGraphics.spt_img:[[Ljava/awt/Image;
   #25 = Fieldref           #87.#197      // KeyboardMenu.hi:[Ljava/awt/Image;
   #26 = Fieldref           #87.#198      // KeyboardMenu.hih:[[Ljava/awt/Image;
   #27 = Fieldref           #195.#199     // GameGraphics.os_g:Ljava/awt/Graphics;
   #28 = Fieldref           #87.#200      // KeyboardMenu.hg:Ljava/awt/Graphics;
   #29 = Fieldref           #195.#201     // GameGraphics.ap:Ljava/applet/Applet;
   #30 = Fieldref           #87.#201      // KeyboardMenu.ap:Ljava/applet/Applet;
   #31 = Methodref          #87.#202      // KeyboardMenu.initAll:()V
   #32 = Methodref          #87.#203      // KeyboardMenu.init1:(I)V
   #33 = Fieldref           #87.#204      // KeyboardMenu.c_fc:I
   #34 = Fieldref           #205.#206     // GameKey.up_c:I
   #35 = Fieldref           #205.#207     // GameKey.down_c:I
   #36 = Fieldref           #87.#208      // KeyboardMenu.list_kazu:I
   #37 = Fieldref           #87.#209      // KeyboardMenu.list_s:I
   #38 = String             #210          // どうしますか？
   #39 = String             #211          //
   #40 = Fieldref           #205.#212     // GameKey.up_f:Z
   #41 = Fieldref           #205.#213     // GameKey.down_f:Z
   #42 = Fieldref           #205.#214     // GameKey.tr1_f:Z
   #43 = Fieldref           #205.#215     // GameKey.x_f:Z
   #44 = Class              #216          // java/awt/Font
   #45 = String             #217          // Dialog
   #46 = Methodref          #44.#218      // java/awt/Font."<init>":(Ljava/lang/String;II)V
   #47 = Methodref          #219.#220     // java/awt/Graphics.setFont:(Ljava/awt/Font;)V
   #48 = Methodref          #87.#221      // KeyboardMenu.drawWindowbox:(IIII)V
   #49 = Fieldref           #14.#222      // java/awt/Color.white:Ljava/awt/Color;
   #50 = Methodref          #219.#223     // java/awt/Graphics.setColor:(Ljava/awt/Color;)V
   #51 = Methodref          #219.#224     // java/awt/Graphics.drawString:(Ljava/lang/String;II)V
   #52 = Methodref          #219.#225     // java/awt/Graphics.drawImage:(Ljava/awt/Image;IILjava/awt/image/ImageObserver;)Z
   #53 = Methodref          #219.#226     // java/awt/Graphics.fillRect:(IIII)V
   #54 = Fieldref           #14.#227      // java/awt/Color.black:Ljava/awt/Color;
   #55 = Fieldref           #14.#228      // java/awt/Color.cyan:Ljava/awt/Color;
   #56 = Fieldref           #14.#229      // java/awt/Color.red:Ljava/awt/Color;
   #57 = String             #230          // 戦闘不能
   #58 = Class              #231          // java/lang/StringBuffer
   #59 = Methodref          #58.#174      // java/lang/StringBuffer."<init>":()V
   #60 = String             #232          // HP
   #61 = Methodref          #58.#233      // java/lang/StringBuffer.append:(Ljava/lang/String;)Ljava/lang/StringBuffer;
   #62 = Methodref          #58.#234      // java/lang/StringBuffer.append:(I)Ljava/lang/StringBuffer;
   #63 = String             #235          //  /
   #64 = Methodref          #58.#236      // java/lang/StringBuffer.toString:()Ljava/lang/String;
   #65 = String             #237          // PP
   #66 = Fieldref           #14.#238      // java/awt/Color.green:Ljava/awt/Color;
   #67 = Methodref          #195.#239     // GameGraphics.drawPT:(IIII)V
   #68 = Fieldref           #14.#240      // java/awt/Color.magenta:Ljava/awt/Color;
   #69 = Methodref          #87.#241      // KeyboardMenu.off:(I)V
   #70 = Fieldref           #14.#242      // java/awt/Color.yellow:Ljava/awt/Color;
   #71 = String             #243          // のステータス
   #72 = String             #244          // おこづかい
   #73 = String             #245          // 円
   #74 = String             #246          // 得点
   #75 = String             #247          // 点
   #76 = Methodref          #14.#248      // java/awt/Color."<init>":(III)V
   #77 = String             #249          // これからも、よろしくね！
   #78 = String             #250          // 捕獲不可能
   #79 = String             #251          // 現在調査中
   #80 = String             #252          // 最大HP
   #81 = String             #253          // 最大PP
   #82 = String             #254          // モンスターずかん
   #83 = String             #255          // 見つけた数
   #84 = String             #256          // 捕まえた数
   #85 = String             #257          // おこづかい
   #86 = String             #258          // みんな、元気になった。
   #87 = Class              #259          // KeyboardMenu
   #88 = Class              #260          // java/lang/Object
   #89 = Utf8               gg
   #90 = Utf8               LGameGraphics;
   #91 = Utf8               gk
   #92 = Utf8               LGameKey;
   #93 = Utf8               hi
   #94 = Utf8               [Ljava/awt/Image;
   #95 = Utf8               hih
   #96 = Utf8               [[Ljava/awt/Image;
   #97 = Utf8               hg
   #98 = Utf8               Ljava/awt/Graphics;
   #99 = Utf8               ap
  #100 = Utf8               Ljava/applet/Applet;
  #101 = Utf8               c
  #102 = Utf8               [I
  #103 = Utf8               x
  #104 = Utf8               y
  #105 = Utf8               width
  #106 = Utf8               selectedIndex
  #107 = Utf8               item_kazu
  #108 = Utf8               message
  #109 = Utf8               [Ljava/lang/String;
  #110 = Utf8               item
  #111 = Utf8               [[Ljava/lang/String;
  #112 = Utf8               item_int
  #113 = Utf8               [[I
  #114 = Utf8               item_color
  #115 = Utf8               [Ljava/awt/Color;
  #116 = Utf8               list_IDlist
  #117 = Utf8               list_kazu
  #118 = Utf8               I
  #119 = Utf8               list_s
  #120 = Utf8               aw
  #121 = Utf8               mode
  #122 = Utf8               kettei_c
  #123 = Utf8               cancel_c
  #124 = Utf8               c_fc
  #125 = Utf8               name_crys
  #126 = Utf8               Ljava/lang/String;
  #127 = Utf8               <init>
  #128 = Utf8               (LGameGraphics;LGameKey;Ljava/lang/String;)V
  #129 = Utf8               Code
  #130 = Utf8               LineNumberTable
  #131 = Utf8               initAll
  #132 = Utf8               ()V
  #133 = Utf8               init1
  #134 = Utf8               (I)V
  #135 = Utf8               setMessage
  #136 = Utf8               (ILjava/lang/String;)V
  #137 = Utf8               addItem
  #138 = Utf8               addIntitem
  #139 = Utf8               (II)V
  #140 = Utf8               addItem2
  #141 = Utf8               (ILjava/lang/String;I)V
  #142 = Utf8               active
  #143 = Utf8               (III)V
  #144 = Utf8               (IIII)V
  #145 = Utf8               activeSerifutuki
  #146 = Utf8               (IIIILjava/lang/String;)V
  #147 = Utf8               activeKaimono
  #148 = Utf8               activeIchigyou
  #149 = Utf8               activeNigyou
  #150 = Utf8               (IIIILjava/awt/Color;)V
  #151 = Utf8               activeYongyou
  #152 = Utf8               activeYongyou2
  #153 = Utf8               activeSerifu
  #154 = Utf8               activeYasumu
  #155 = Utf8               onKao
  #156 = Utf8               (IIIII)V
  #157 = Utf8               onMituketa
  #158 = Utf8               onOkozukai
  #159 = Utf8               activeIchigyouTime
  #160 = Utf8               activeNigyouTime
  #161 = Utf8               activeJibun
  #162 = Utf8               (IIIIIIII)V
  #163 = Utf8               activeToujou
  #164 = Utf8               (IIIIILjava/lang/String;)V
  #165 = Utf8               initCS
  #166 = Utf8               activeCS
  #167 = Utf8               off
  #168 = Utf8               offActivewindow
  #169 = Utf8               move
  #170 = Utf8               drawMenus
  #171 = Utf8               drawWindowbox
  #172 = Utf8               SourceFile
  #173 = Utf8               MasaoConstruction.java
  #174 = NameAndType        #127:#132     // "<init>":()V
  #175 = NameAndType        #101:#102     // c:[I
  #176 = NameAndType        #103:#102     // x:[I
  #177 = NameAndType        #104:#102     // y:[I
  #178 = NameAndType        #105:#102     // width:[I
  #179 = NameAndType        #106:#102     // selectedIndex:[I
  #180 = NameAndType        #107:#102     // item_kazu:[I
  #181 = Utf8               java/lang/String
  #182 = NameAndType        #108:#109     // message:[Ljava/lang/String;
  #183 = NameAndType        #110:#111     // item:[[Ljava/lang/String;
  #184 = NameAndType        #112:#113     // item_int:[[I
  #185 = Utf8               java/awt/Color
  #186 = NameAndType        #114:#115     // item_color:[Ljava/awt/Color;
  #187 = NameAndType        #116:#102     // list_IDlist:[I
  #188 = NameAndType        #120:#118     // aw:I
  #189 = NameAndType        #121:#118     // mode:I
  #190 = NameAndType        #122:#118     // kettei_c:I
  #191 = NameAndType        #123:#118     // cancel_c:I
  #192 = NameAndType        #89:#90       // gg:LGameGraphics;
  #193 = NameAndType        #91:#92       // gk:LGameKey;
  #194 = NameAndType        #125:#126     // name_crys:Ljava/lang/String;
  #195 = Class              #261          // GameGraphics
  #196 = NameAndType        #262:#96      // spt_img:[[Ljava/awt/Image;
  #197 = NameAndType        #93:#94       // hi:[Ljava/awt/Image;
  #198 = NameAndType        #95:#96       // hih:[[Ljava/awt/Image;
  #199 = NameAndType        #263:#98      // os_g:Ljava/awt/Graphics;
  #200 = NameAndType        #97:#98       // hg:Ljava/awt/Graphics;
  #201 = NameAndType        #99:#100      // ap:Ljava/applet/Applet;
  #202 = NameAndType        #131:#132     // initAll:()V
  #203 = NameAndType        #133:#134     // init1:(I)V
  #204 = NameAndType        #124:#118     // c_fc:I
  #205 = Class              #264          // GameKey
  #206 = NameAndType        #265:#118     // up_c:I
  #207 = NameAndType        #266:#118     // down_c:I
  #208 = NameAndType        #117:#118     // list_kazu:I
  #209 = NameAndType        #119:#118     // list_s:I
  #210 = Utf8               どうしますか？
  #211 = Utf8
  #212 = NameAndType        #267:#268     // up_f:Z
  #213 = NameAndType        #269:#268     // down_f:Z
  #214 = NameAndType        #270:#268     // tr1_f:Z
  #215 = NameAndType        #271:#268     // x_f:Z
  #216 = Utf8               java/awt/Font
  #217 = Utf8               Dialog
  #218 = NameAndType        #127:#272     // "<init>":(Ljava/lang/String;II)V
  #219 = Class              #273          // java/awt/Graphics
  #220 = NameAndType        #274:#275     // setFont:(Ljava/awt/Font;)V
  #221 = NameAndType        #171:#144     // drawWindowbox:(IIII)V
  #222 = NameAndType        #276:#277     // white:Ljava/awt/Color;
  #223 = NameAndType        #278:#279     // setColor:(Ljava/awt/Color;)V
  #224 = NameAndType        #280:#272     // drawString:(Ljava/lang/String;II)V
  #225 = NameAndType        #281:#282     // drawImage:(Ljava/awt/Image;IILjava/awt/image/ImageObserver;)Z
  #226 = NameAndType        #283:#144     // fillRect:(IIII)V
  #227 = NameAndType        #284:#277     // black:Ljava/awt/Color;
  #228 = NameAndType        #285:#277     // cyan:Ljava/awt/Color;
  #229 = NameAndType        #286:#277     // red:Ljava/awt/Color;
  #230 = Utf8               戦闘不能
  #231 = Utf8               java/lang/StringBuffer
  #232 = Utf8               HP
  #233 = NameAndType        #287:#288     // append:(Ljava/lang/String;)Ljava/lang/StringBuffer;
  #234 = NameAndType        #287:#289     // append:(I)Ljava/lang/StringBuffer;
  #235 = Utf8                /
  #236 = NameAndType        #290:#291     // toString:()Ljava/lang/String;
  #237 = Utf8               PP
  #238 = NameAndType        #292:#277     // green:Ljava/awt/Color;
  #239 = NameAndType        #293:#144     // drawPT:(IIII)V
  #240 = NameAndType        #294:#277     // magenta:Ljava/awt/Color;
  #241 = NameAndType        #167:#134     // off:(I)V
  #242 = NameAndType        #295:#277     // yellow:Ljava/awt/Color;
  #243 = Utf8               のステータス
  #244 = Utf8               おこづかい
  #245 = Utf8               円
  #246 = Utf8               得点
  #247 = Utf8               点
  #248 = NameAndType        #127:#143     // "<init>":(III)V
  #249 = Utf8               これからも、よろしくね！
  #250 = Utf8               捕獲不可能
  #251 = Utf8               現在調査中
  #252 = Utf8               最大HP
  #253 = Utf8               最大PP
  #254 = Utf8               モンスターずかん
  #255 = Utf8               見つけた数
  #256 = Utf8               捕まえた数
  #257 = Utf8               おこづかい
  #258 = Utf8               みんな、元気になった。
  #259 = Utf8               KeyboardMenu
  #260 = Utf8               java/lang/Object
  #261 = Utf8               GameGraphics
  #262 = Utf8               spt_img
  #263 = Utf8               os_g
  #264 = Utf8               GameKey
  #265 = Utf8               up_c
  #266 = Utf8               down_c
  #267 = Utf8               up_f
  #268 = Utf8               Z
  #269 = Utf8               down_f
  #270 = Utf8               tr1_f
  #271 = Utf8               x_f
  #272 = Utf8               (Ljava/lang/String;II)V
  #273 = Utf8               java/awt/Graphics
  #274 = Utf8               setFont
  #275 = Utf8               (Ljava/awt/Font;)V
  #276 = Utf8               white
  #277 = Utf8               Ljava/awt/Color;
  #278 = Utf8               setColor
  #279 = Utf8               (Ljava/awt/Color;)V
  #280 = Utf8               drawString
  #281 = Utf8               drawImage
  #282 = Utf8               (Ljava/awt/Image;IILjava/awt/image/ImageObserver;)Z
  #283 = Utf8               fillRect
  #284 = Utf8               black
  #285 = Utf8               cyan
  #286 = Utf8               red
  #287 = Utf8               append
  #288 = Utf8               (Ljava/lang/String;)Ljava/lang/StringBuffer;
  #289 = Utf8               (I)Ljava/lang/StringBuffer;
  #290 = Utf8               toString
  #291 = Utf8               ()Ljava/lang/String;
  #292 = Utf8               green
  #293 = Utf8               drawPT
  #294 = Utf8               magenta
  #295 = Utf8               yellow
{
  GameGraphics gg;
    descriptor: LGameGraphics;
    flags: (0x0000)

  GameKey gk;
    descriptor: LGameKey;
    flags: (0x0000)

  java.awt.Image[] hi;
    descriptor: [Ljava/awt/Image;
    flags: (0x0000)

  java.awt.Image[][] hih;
    descriptor: [[Ljava/awt/Image;
    flags: (0x0000)

  java.awt.Graphics hg;
    descriptor: Ljava/awt/Graphics;
    flags: (0x0000)

  java.applet.Applet ap;
    descriptor: Ljava/applet/Applet;
    flags: (0x0000)

  int[] c;
    descriptor: [I
    flags: (0x0000)

  int[] x;
    descriptor: [I
    flags: (0x0000)

  int[] y;
    descriptor: [I
    flags: (0x0000)

  int[] width;
    descriptor: [I
    flags: (0x0000)

  int[] selectedIndex;
    descriptor: [I
    flags: (0x0000)

  int[] item_kazu;
    descriptor: [I
    flags: (0x0000)

  java.lang.String[] message;
    descriptor: [Ljava/lang/String;
    flags: (0x0000)

  java.lang.String[][] item;
    descriptor: [[Ljava/lang/String;
    flags: (0x0000)

  int[][] item_int;
    descriptor: [[I
    flags: (0x0000)

  java.awt.Color[] item_color;
    descriptor: [Ljava/awt/Color;
    flags: (0x0000)

  int[] list_IDlist;
    descriptor: [I
    flags: (0x0000)

  int list_kazu;
    descriptor: I
    flags: (0x0000)

  int list_s;
    descriptor: I
    flags: (0x0000)

  int aw;
    descriptor: I
    flags: (0x0000)

  int mode;
    descriptor: I
    flags: (0x0000)

  int kettei_c;
    descriptor: I
    flags: (0x0000)

  int cancel_c;
    descriptor: I
    flags: (0x0000)

  int c_fc;
    descriptor: I
    flags: (0x0000)

  java.lang.String name_crys;
    descriptor: Ljava/lang/String;
    flags: (0x0000)

  KeyboardMenu(GameGraphics, GameKey, java.lang.String);
    descriptor: (LGameGraphics;LGameKey;Ljava/lang/String;)V
    flags: (0x0000)
    Code:
      stack=3, locals=4, args_size=4
         0: aload_0
         1: invokespecial #1                  // Method java/lang/Object."<init>":()V
         4: aload_0
         5: bipush        16
         7: newarray       int
         9: putfield      #2                  // Field c:[I
        12: aload_0
        13: bipush        16
        15: newarray       int
        17: putfield      #3                  // Field x:[I
        20: aload_0
        21: bipush        16
        23: newarray       int
        25: putfield      #4                  // Field y:[I
        28: aload_0
        29: bipush        16
        31: newarray       int
        33: putfield      #5                  // Field width:[I
        36: aload_0
        37: bipush        16
        39: newarray       int
        41: putfield      #6                  // Field selectedIndex:[I
        44: aload_0
        45: bipush        16
        47: newarray       int
        49: putfield      #7                  // Field item_kazu:[I
        52: aload_0
        53: bipush        16
        55: anewarray     #8                  // class java/lang/String
        58: putfield      #9                  // Field message:[Ljava/lang/String;
        61: aload_0
        62: bipush        16
        64: bipush        16
        66: multianewarray #10,  2            // class "[[Ljava/lang/String;"
        70: putfield      #11                 // Field item:[[Ljava/lang/String;
        73: aload_0
        74: bipush        16
        76: bipush        16
        78: multianewarray #12,  2            // class "[[I"
        82: putfield      #13                 // Field item_int:[[I
        85: aload_0
        86: bipush        16
        88: anewarray     #14                 // class java/awt/Color
        91: putfield      #15                 // Field item_color:[Ljava/awt/Color;
        94: aload_0
        95: bipush        16
        97: newarray       int
        99: putfield      #16                 // Field list_IDlist:[I
       102: aload_0
       103: iconst_m1
       104: putfield      #17                 // Field aw:I
       107: aload_0
       108: iconst_0
       109: putfield      #18                 // Field mode:I
       112: aload_0
       113: iconst_0
       114: putfield      #19                 // Field kettei_c:I
       117: aload_0
       118: iconst_0
       119: putfield      #20                 // Field cancel_c:I
       122: aload_0
       123: aload_1
       124: putfield      #21                 // Field gg:LGameGraphics;
       127: aload_0
       128: aload_2
       129: putfield      #22                 // Field gk:LGameKey;
       132: aload_0
       133: aload_3
       134: putfield      #23                 // Field name_crys:Ljava/lang/String;
       137: aload_0
       138: aload_0
       139: getfield      #21                 // Field gg:LGameGraphics;
       142: getfield      #24                 // Field GameGraphics.spt_img:[[Ljava/awt/Image;
       145: iconst_0
       146: aaload
       147: putfield      #25                 // Field hi:[Ljava/awt/Image;
       150: aload_0
       151: aload_0
       152: getfield      #21                 // Field gg:LGameGraphics;
       155: getfield      #24                 // Field GameGraphics.spt_img:[[Ljava/awt/Image;
       158: putfield      #26                 // Field hih:[[Ljava/awt/Image;
       161: aload_0
       162: aload_0
       163: getfield      #21                 // Field gg:LGameGraphics;
       166: getfield      #27                 // Field GameGraphics.os_g:Ljava/awt/Graphics;
       169: putfield      #28                 // Field hg:Ljava/awt/Graphics;
       172: aload_0
       173: aload_0
       174: getfield      #21                 // Field gg:LGameGraphics;
       177: getfield      #29                 // Field GameGraphics.ap:Ljava/applet/Applet;
       180: putfield      #30                 // Field ap:Ljava/applet/Applet;
       183: aload_0
       184: invokevirtual #31                 // Method initAll:()V
       187: return
      LineNumberTable:
        line 13562: 0
        line 13523: 4
        line 13524: 12
        line 13525: 20
        line 13526: 28
        line 13527: 36
        line 13528: 44
        line 13529: 52
        line 13530: 61
        line 13531: 73
        line 13532: 85
        line 13533: 94
        line 13536: 102
        line 13539: 107
        line 13540: 112
        line 13544: 117
        line 13565: 122
        line 13566: 127
        line 13567: 132
        line 13570: 137
        line 13571: 150
        line 13572: 161
        line 13573: 172
        line 13575: 183
        line 13576: 187

  void initAll();
    descriptor: ()V
    flags: (0x0000)
    Code:
      stack=3, locals=2, args_size=1
         0: iconst_0
         1: istore_1
         2: goto          13
         5: aload_0
         6: iload_1
         7: invokevirtual #32                 // Method init1:(I)V
        10: iinc          1, 1
        13: iload_1
        14: bipush        15
        16: if_icmple     5
        19: aload_0
        20: iconst_0
        21: putfield      #33                 // Field c_fc:I
        24: aload_0
        25: getfield      #22                 // Field gk:LGameKey;
        28: iconst_0
        29: putfield      #34                 // Field GameKey.up_c:I
        32: aload_0
        33: getfield      #22                 // Field gk:LGameKey;
        36: iconst_0
        37: putfield      #35                 // Field GameKey.down_c:I
        40: aload_0
        41: iconst_m1
        42: putfield      #17                 // Field aw:I
        45: aload_0
        46: iconst_2
        47: putfield      #19                 // Field kettei_c:I
        50: aload_0
        51: iconst_2
        52: putfield      #20                 // Field cancel_c:I
        55: iconst_0
        56: istore_1
        57: goto          70
        60: aload_0
        61: getfield      #16                 // Field list_IDlist:[I
        64: iload_1
        65: iconst_0
        66: iastore
        67: iinc          1, 1
        70: iload_1
        71: bipush        15
        73: if_icmple     60
        76: aload_0
        77: iconst_0
        78: putfield      #36                 // Field list_kazu:I
        81: aload_0
        82: iconst_0
        83: putfield      #37                 // Field list_s:I
        86: return
      LineNumberTable:
        line 13584: 0
        line 13585: 5
        line 13584: 10
        line 13588: 19
        line 13589: 24
        line 13590: 32
        line 13591: 40
        line 13592: 45
        line 13593: 50
        line 13595: 55
        line 13596: 60
        line 13595: 67
        line 13598: 76
        line 13599: 81
        line 13600: 86

  void init1(int);
    descriptor: (I)V
    flags: (0x0000)
    Code:
      stack=3, locals=3, args_size=2
         0: aload_0
         1: getfield      #2                  // Field c:[I
         4: iload_1
         5: iconst_0
         6: iastore
         7: aload_0
         8: getfield      #3                  // Field x:[I
        11: iload_1
        12: iconst_0
        13: iastore
        14: aload_0
        15: getfield      #4                  // Field y:[I
        18: iload_1
        19: iconst_0
        20: iastore
        21: aload_0
        22: getfield      #5                  // Field width:[I
        25: iload_1
        26: sipush        180
        29: iastore
        30: aload_0
        31: getfield      #6                  // Field selectedIndex:[I
        34: iload_1
        35: iconst_0
        36: iastore
        37: aload_0
        38: getfield      #7                  // Field item_kazu:[I
        41: iload_1
        42: iconst_0
        43: iastore
        44: aload_0
        45: getfield      #9                  // Field message:[Ljava/lang/String;
        48: iload_1
        49: ldc           #38                 // String どうしますか？
        51: aastore
        52: iconst_0
        53: istore_2
        54: goto          70
        57: aload_0
        58: getfield      #11                 // Field item:[[Ljava/lang/String;
        61: iload_1
        62: aaload
        63: iload_2
        64: ldc           #39                 // String
        66: aastore
        67: iinc          2, 1
        70: iload_2
        71: bipush        15
        73: if_icmple     57
        76: iconst_0
        77: istore_2
        78: goto          93
        81: aload_0
        82: getfield      #13                 // Field item_int:[[I
        85: iload_1
        86: aaload
        87: iload_2
        88: iconst_0
        89: iastore
        90: iinc          2, 1
        93: iload_2
        94: bipush        15
        96: if_icmple     81
        99: return
      LineNumberTable:
        line 13609: 0
        line 13610: 7
        line 13611: 14
        line 13612: 21
        line 13613: 30
        line 13614: 37
        line 13615: 44
        line 13616: 52
        line 13617: 57
        line 13616: 67
        line 13619: 76
        line 13620: 81
        line 13619: 90
        line 13622: 99

  void setMessage(int, java.lang.String);
    descriptor: (ILjava/lang/String;)V
    flags: (0x0000)
    Code:
      stack=3, locals=3, args_size=3
         0: aload_0
         1: getfield      #9                  // Field message:[Ljava/lang/String;
         4: iload_1
         5: aload_2
         6: aastore
         7: return
      LineNumberTable:
        line 13631: 0
        line 13632: 7

  void addItem(int, java.lang.String);
    descriptor: (ILjava/lang/String;)V
    flags: (0x0000)
    Code:
      stack=4, locals=3, args_size=3
         0: aload_0
         1: getfield      #11                 // Field item:[[Ljava/lang/String;
         4: iload_1
         5: aaload
         6: aload_0
         7: getfield      #7                  // Field item_kazu:[I
        10: iload_1
        11: iaload
        12: aload_2
        13: aastore
        14: aload_0
        15: getfield      #7                  // Field item_kazu:[I
        18: iload_1
        19: dup2
        20: iaload
        21: iconst_1
        22: iadd
        23: iastore
        24: return
      LineNumberTable:
        line 13641: 0
        line 13642: 14
        line 13643: 24

  void addIntitem(int, int);
    descriptor: (II)V
    flags: (0x0000)
    Code:
      stack=4, locals=3, args_size=3
         0: aload_0
         1: getfield      #13                 // Field item_int:[[I
         4: iload_1
         5: aaload
         6: aload_0
         7: getfield      #7                  // Field item_kazu:[I
        10: iload_1
        11: iaload
        12: iload_2
        13: iastore
        14: aload_0
        15: getfield      #7                  // Field item_kazu:[I
        18: iload_1
        19: dup2
        20: iaload
        21: iconst_1
        22: iadd
        23: iastore
        24: return
      LineNumberTable:
        line 13652: 0
        line 13653: 14
        line 13654: 24

  void addItem2(int, java.lang.String, int);
    descriptor: (ILjava/lang/String;I)V
    flags: (0x0000)
    Code:
      stack=4, locals=4, args_size=4
         0: aload_0
         1: getfield      #11                 // Field item:[[Ljava/lang/String;
         4: iload_1
         5: aaload
         6: aload_0
         7: getfield      #7                  // Field item_kazu:[I
        10: iload_1
        11: iaload
        12: aload_2
        13: aastore
        14: aload_0
        15: getfield      #13                 // Field item_int:[[I
        18: iload_1
        19: aaload
        20: aload_0
        21: getfield      #7                  // Field item_kazu:[I
        24: iload_1
        25: iaload
        26: iload_3
        27: iastore
        28: aload_0
        29: getfield      #7                  // Field item_kazu:[I
        32: iload_1
        33: dup2
        34: iaload
        35: iconst_1
        36: iadd
        37: iastore
        38: return
      LineNumberTable:
        line 13664: 0
        line 13665: 14
        line 13666: 28
        line 13667: 38

  void active(int, int, int);
    descriptor: (III)V
    flags: (0x0000)
    Code:
      stack=3, locals=4, args_size=4
         0: aload_0
         1: getfield      #2                  // Field c:[I
         4: iload_1
         5: bipush        100
         7: iastore
         8: aload_0
         9: getfield      #3                  // Field x:[I
        12: iload_1
        13: iload_2
        14: iastore
        15: aload_0
        16: getfield      #4                  // Field y:[I
        19: iload_1
        20: iload_3
        21: iastore
        22: aload_0
        23: getfield      #5                  // Field width:[I
        26: iload_1
        27: sipush        180
        30: iastore
        31: aload_0
        32: iconst_m1
        33: putfield      #33                 // Field c_fc:I
        36: aload_0
        37: getfield      #22                 // Field gk:LGameKey;
        40: iconst_0
        41: putfield      #34                 // Field GameKey.up_c:I
        44: aload_0
        45: getfield      #22                 // Field gk:LGameKey;
        48: iconst_0
        49: putfield      #35                 // Field GameKey.down_c:I
        52: aload_0
        53: iload_1
        54: putfield      #17                 // Field aw:I
        57: aload_0
        58: iconst_2
        59: putfield      #19                 // Field kettei_c:I
        62: aload_0
        63: iconst_2
        64: putfield      #20                 // Field cancel_c:I
        67: return
      LineNumberTable:
        line 13677: 0
        line 13678: 8
        line 13679: 15
        line 13680: 22
        line 13681: 31
        line 13682: 36
        line 13683: 44
        line 13684: 52
        line 13685: 57
        line 13686: 62
        line 13687: 67

  void active(int, int, int, int);
    descriptor: (IIII)V
    flags: (0x0000)
    Code:
      stack=3, locals=5, args_size=5
         0: aload_0
         1: getfield      #2                  // Field c:[I
         4: iload_1
         5: bipush        100
         7: iastore
         8: aload_0
         9: getfield      #3                  // Field x:[I
        12: iload_1
        13: iload_2
        14: iastore
        15: aload_0
        16: getfield      #4                  // Field y:[I
        19: iload_1
        20: iload_3
        21: iastore
        22: aload_0
        23: getfield      #5                  // Field width:[I
        26: iload_1
        27: iload         4
        29: iastore
        30: aload_0
        31: iconst_m1
        32: putfield      #33                 // Field c_fc:I
        35: aload_0
        36: getfield      #22                 // Field gk:LGameKey;
        39: iconst_0
        40: putfield      #34                 // Field GameKey.up_c:I
        43: aload_0
        44: getfield      #22                 // Field gk:LGameKey;
        47: iconst_0
        48: putfield      #35                 // Field GameKey.down_c:I
        51: aload_0
        52: iload_1
        53: putfield      #17                 // Field aw:I
        56: aload_0
        57: iconst_2
        58: putfield      #19                 // Field kettei_c:I
        61: aload_0
        62: iconst_2
        63: putfield      #20                 // Field cancel_c:I
        66: return
      LineNumberTable:
        line 13698: 0
        line 13699: 8
        line 13700: 15
        line 13701: 22
        line 13702: 30
        line 13703: 35
        line 13704: 43
        line 13705: 51
        line 13706: 56
        line 13707: 61
        line 13708: 66

  void activeSerifutuki(int, int, int, int, java.lang.String);
    descriptor: (IIIILjava/lang/String;)V
    flags: (0x0000)
    Code:
      stack=3, locals=6, args_size=6
         0: aload_0
         1: getfield      #2                  // Field c:[I
         4: iload_1
         5: sipush        700
         8: iastore
         9: aload_0
        10: getfield      #3                  // Field x:[I
        13: iload_1
        14: iload_2
        15: iastore
        16: aload_0
        17: getfield      #4                  // Field y:[I
        20: iload_1
        21: iload_3
        22: iastore
        23: aload_0
        24: getfield      #5                  // Field width:[I
        27: iload_1
        28: iload         4
        30: iastore
        31: aload_0
        32: iconst_m1
        33: putfield      #33                 // Field c_fc:I
        36: aload_0
        37: getfield      #22                 // Field gk:LGameKey;
        40: iconst_0
        41: putfield      #34                 // Field GameKey.up_c:I
        44: aload_0
        45: getfield      #22                 // Field gk:LGameKey;
        48: iconst_0
        49: putfield      #35                 // Field GameKey.down_c:I
        52: aload_0
        53: iload_1
        54: putfield      #17                 // Field aw:I
        57: aload_0
        58: iconst_2
        59: putfield      #19                 // Field kettei_c:I
        62: aload_0
        63: iconst_2
        64: putfield      #20                 // Field cancel_c:I
        67: aload_0
        68: getfield      #11                 // Field item:[[Ljava/lang/String;
        71: iload_1
        72: aaload
        73: bipush        15
        75: aload         5
        77: aastore
        78: return
      LineNumberTable:
        line 13720: 0
        line 13721: 9
        line 13722: 16
        line 13723: 23
        line 13724: 31
        line 13725: 36
        line 13726: 44
        line 13727: 52
        line 13728: 57
        line 13729: 62
        line 13731: 67
        line 13732: 78

  void activeKaimono(int, int, int, int);
    descriptor: (IIII)V
    flags: (0x0000)
    Code:
      stack=3, locals=5, args_size=5
         0: aload_0
         1: getfield      #2                  // Field c:[I
         4: iload_1
         5: sipush        900
         8: iastore
         9: aload_0
        10: getfield      #3                  // Field x:[I
        13: iload_1
        14: iload_2
        15: iastore
        16: aload_0
        17: getfield      #4                  // Field y:[I
        20: iload_1
        21: iload_3
        22: iastore
        23: aload_0
        24: getfield      #5                  // Field width:[I
        27: iload_1
        28: iload         4
        30: iastore
        31: aload_0
        32: iconst_m1
        33: putfield      #33                 // Field c_fc:I
        36: aload_0
        37: getfield      #22                 // Field gk:LGameKey;
        40: iconst_0
        41: putfield      #34                 // Field GameKey.up_c:I
        44: aload_0
        45: getfield      #22                 // Field gk:LGameKey;
        48: iconst_0
        49: putfield      #35                 // Field GameKey.down_c:I
        52: aload_0
        53: iload_1
        54: putfield      #17                 // Field aw:I
        57: aload_0
        58: iconst_2
        59: putfield      #19                 // Field kettei_c:I
        62: aload_0
        63: iconst_2
        64: putfield      #20                 // Field cancel_c:I
        67: return
      LineNumberTable:
        line 13743: 0
        line 13744: 9
        line 13745: 16
        line 13746: 23
        line 13747: 31
        line 13748: 36
        line 13749: 44
        line 13750: 52
        line 13751: 57
        line 13752: 62
        line 13753: 67

  void activeIchigyou(int, int, int, int);
    descriptor: (IIII)V
    flags: (0x0000)
    Code:
      stack=3, locals=5, args_size=5
         0: aload_0
         1: getfield      #2                  // Field c:[I
         4: iload_1
         5: sipush        300
         8: iastore
         9: aload_0
        10: getfield      #3                  // Field x:[I
        13: iload_1
        14: iload_2
        15: iastore
        16: aload_0
        17: getfield      #4                  // Field y:[I
        20: iload_1
        21: iload_3
        22: iastore
        23: aload_0
        24: getfield      #5                  // Field width:[I
        27: iload_1
        28: iload         4
        30: iastore
        31: aload_0
        32: iconst_m1
        33: putfield      #33                 // Field c_fc:I
        36: aload_0
        37: getfield      #22                 // Field gk:LGameKey;
        40: iconst_0
        41: putfield      #34                 // Field GameKey.up_c:I
        44: aload_0
        45: getfield      #22                 // Field gk:LGameKey;
        48: iconst_0
        49: putfield      #35                 // Field GameKey.down_c:I
        52: aload_0
        53: iload_1
        54: putfield      #17                 // Field aw:I
        57: aload_0
        58: iconst_2
        59: putfield      #19                 // Field kettei_c:I
        62: aload_0
        63: iconst_2
        64: putfield      #20                 // Field cancel_c:I
        67: return
      LineNumberTable:
        line 13765: 0
        line 13766: 9
        line 13767: 16
        line 13768: 23
        line 13769: 31
        line 13770: 36
        line 13771: 44
        line 13772: 52
        line 13773: 57
        line 13774: 62
        line 13775: 67

  void activeNigyou(int, int, int, int, java.awt.Color);
    descriptor: (IIIILjava/awt/Color;)V
    flags: (0x0000)
    Code:
      stack=3, locals=6, args_size=6
         0: aload_0
         1: getfield      #2                  // Field c:[I
         4: iload_1
         5: sipush        310
         8: iastore
         9: aload_0
        10: getfield      #3                  // Field x:[I
        13: iload_1
        14: iload_2
        15: iastore
        16: aload_0
        17: getfield      #4                  // Field y:[I
        20: iload_1
        21: iload_3
        22: iastore
        23: aload_0
        24: getfield      #5                  // Field width:[I
        27: iload_1
        28: iload         4
        30: iastore
        31: aload_0
        32: getfield      #15                 // Field item_color:[Ljava/awt/Color;
        35: iload_1
        36: aload         5
        38: aastore
        39: aload_0
        40: iconst_m1
        41: putfield      #33                 // Field c_fc:I
        44: aload_0
        45: getfield      #22                 // Field gk:LGameKey;
        48: iconst_0
        49: putfield      #34                 // Field GameKey.up_c:I
        52: aload_0
        53: getfield      #22                 // Field gk:LGameKey;
        56: iconst_0
        57: putfield      #35                 // Field GameKey.down_c:I
        60: aload_0
        61: iload_1
        62: putfield      #17                 // Field aw:I
        65: aload_0
        66: iconst_2
        67: putfield      #19                 // Field kettei_c:I
        70: aload_0
        71: iconst_2
        72: putfield      #20                 // Field cancel_c:I
        75: return
      LineNumberTable:
        line 13788: 0
        line 13789: 9
        line 13790: 16
        line 13791: 23
        line 13792: 31
        line 13793: 39
        line 13794: 44
        line 13795: 52
        line 13796: 60
        line 13797: 65
        line 13798: 70
        line 13799: 75

  void activeYongyou(int, int, int, int);
    descriptor: (IIII)V
    flags: (0x0000)
    Code:
      stack=3, locals=5, args_size=5
         0: aload_0
         1: getfield      #2                  // Field c:[I
         4: iload_1
         5: sipush        320
         8: iastore
         9: aload_0
        10: getfield      #3                  // Field x:[I
        13: iload_1
        14: iload_2
        15: iastore
        16: aload_0
        17: getfield      #4                  // Field y:[I
        20: iload_1
        21: iload_3
        22: iastore
        23: aload_0
        24: getfield      #5                  // Field width:[I
        27: iload_1
        28: iload         4
        30: iastore
        31: aload_0
        32: iconst_m1
        33: putfield      #33                 // Field c_fc:I
        36: aload_0
        37: getfield      #22                 // Field gk:LGameKey;
        40: iconst_0
        41: putfield      #34                 // Field GameKey.up_c:I
        44: aload_0
        45: getfield      #22                 // Field gk:LGameKey;
        48: iconst_0
        49: putfield      #35                 // Field GameKey.down_c:I
        52: aload_0
        53: iload_1
        54: putfield      #17                 // Field aw:I
        57: aload_0
        58: iconst_2
        59: putfield      #19                 // Field kettei_c:I
        62: aload_0
        63: iconst_2
        64: putfield      #20                 // Field cancel_c:I
        67: return
      LineNumberTable:
        line 13811: 0
        line 13812: 9
        line 13813: 16
        line 13814: 23
        line 13815: 31
        line 13816: 36
        line 13817: 44
        line 13818: 52
        line 13819: 57
        line 13820: 62
        line 13821: 67

  void activeYongyou2(int, int, int, int);
    descriptor: (IIII)V
    flags: (0x0000)
    Code:
      stack=3, locals=5, args_size=5
         0: aload_0
         1: getfield      #2                  // Field c:[I
         4: iload_1
         5: sipush        321
         8: iastore
         9: aload_0
        10: getfield      #3                  // Field x:[I
        13: iload_1
        14: iload_2
        15: iastore
        16: aload_0
        17: getfield      #4                  // Field y:[I
        20: iload_1
        21: iload_3
        22: iastore
        23: aload_0
        24: getfield      #5                  // Field width:[I
        27: iload_1
        28: iload         4
        30: iastore
        31: aload_0
        32: iconst_m1
        33: putfield      #33                 // Field c_fc:I
        36: aload_0
        37: getfield      #22                 // Field gk:LGameKey;
        40: iconst_0
        41: putfield      #34                 // Field GameKey.up_c:I
        44: aload_0
        45: getfield      #22                 // Field gk:LGameKey;
        48: iconst_0
        49: putfield      #35                 // Field GameKey.down_c:I
        52: aload_0
        53: iload_1
        54: putfield      #17                 // Field aw:I
        57: aload_0
        58: iconst_2
        59: putfield      #19                 // Field kettei_c:I
        62: aload_0
        63: iconst_2
        64: putfield      #20                 // Field cancel_c:I
        67: return
      LineNumberTable:
        line 13833: 0
        line 13834: 9
        line 13835: 16
        line 13836: 23
        line 13837: 31
        line 13838: 36
        line 13839: 44
        line 13840: 52
        line 13841: 57
        line 13842: 62
        line 13843: 67

  void activeSerifu(int, int, int, int, java.awt.Color);
    descriptor: (IIIILjava/awt/Color;)V
    flags: (0x0000)
    Code:
      stack=3, locals=6, args_size=6
         0: aload_0
         1: getfield      #2                  // Field c:[I
         4: iload_1
         5: sipush        330
         8: iastore
         9: aload_0
        10: getfield      #3                  // Field x:[I
        13: iload_1
        14: iload_2
        15: iastore
        16: aload_0
        17: getfield      #4                  // Field y:[I
        20: iload_1
        21: iload_3
        22: iastore
        23: aload_0
        24: getfield      #5                  // Field width:[I
        27: iload_1
        28: iload         4
        30: iastore
        31: aload_0
        32: getfield      #15                 // Field item_color:[Ljava/awt/Color;
        35: iload_1
        36: aload         5
        38: aastore
        39: aload_0
        40: iconst_m1
        41: putfield      #33                 // Field c_fc:I
        44: aload_0
        45: getfield      #22                 // Field gk:LGameKey;
        48: iconst_0
        49: putfield      #34                 // Field GameKey.up_c:I
        52: aload_0
        53: getfield      #22                 // Field gk:LGameKey;
        56: iconst_0
        57: putfield      #35                 // Field GameKey.down_c:I
        60: aload_0
        61: iload_1
        62: putfield      #17                 // Field aw:I
        65: aload_0
        66: iconst_2
        67: putfield      #19                 // Field kettei_c:I
        70: aload_0
        71: iconst_2
        72: putfield      #20                 // Field cancel_c:I
        75: return
      LineNumberTable:
        line 13856: 0
        line 13857: 9
        line 13858: 16
        line 13859: 23
        line 13860: 31
        line 13861: 39
        line 13862: 44
        line 13863: 52
        line 13864: 60
        line 13865: 65
        line 13866: 70
        line 13867: 75

  void activeYasumu(int, int, int);
    descriptor: (III)V
    flags: (0x0000)
    Code:
      stack=3, locals=4, args_size=4
         0: aload_0
         1: getfield      #2                  // Field c:[I
         4: iload_1
         5: sipush        1000
         8: iastore
         9: aload_0
        10: getfield      #3                  // Field x:[I
        13: iload_1
        14: iload_2
        15: iastore
        16: aload_0
        17: getfield      #4                  // Field y:[I
        20: iload_1
        21: iload_3
        22: iastore
        23: aload_0
        24: getfield      #5                  // Field width:[I
        27: iload_1
        28: sipush        272
        31: iastore
        32: aload_0
        33: iconst_m1
        34: putfield      #33                 // Field c_fc:I
        37: aload_0
        38: getfield      #22                 // Field gk:LGameKey;
        41: iconst_0
        42: putfield      #34                 // Field GameKey.up_c:I
        45: aload_0
        46: getfield      #22                 // Field gk:LGameKey;
        49: iconst_0
        50: putfield      #35                 // Field GameKey.down_c:I
        53: aload_0
        54: iload_1
        55: putfield      #17                 // Field aw:I
        58: aload_0
        59: iconst_2
        60: putfield      #19                 // Field kettei_c:I
        63: aload_0
        64: iconst_2
        65: putfield      #20                 // Field cancel_c:I
        68: return
      LineNumberTable:
        line 13878: 0
        line 13879: 9
        line 13880: 16
        line 13881: 23
        line 13882: 32
        line 13883: 37
        line 13884: 45
        line 13885: 53
        line 13886: 58
        line 13887: 63
        line 13888: 68

  void onKao(int, int, int, int, int);
    descriptor: (IIIII)V
    flags: (0x0000)
    Code:
      stack=3, locals=6, args_size=6
         0: aload_0
         1: getfield      #2                  // Field c:[I
         4: iload_1
         5: sipush        600
         8: iastore
         9: aload_0
        10: getfield      #3                  // Field x:[I
        13: iload_1
        14: iload_2
        15: iastore
        16: aload_0
        17: getfield      #4                  // Field y:[I
        20: iload_1
        21: iload_3
        22: iastore
        23: aload_0
        24: getfield      #5                  // Field width:[I
        27: iload_1
        28: iload         4
        30: iastore
        31: aload_0
        32: getfield      #13                 // Field item_int:[[I
        35: iload_1
        36: aaload
        37: iconst_0
        38: iload         5
        40: iastore
        41: return
      LineNumberTable:
        line 13901: 0
        line 13902: 9
        line 13903: 16
        line 13904: 23
        line 13905: 31
        line 13906: 41

  void onMituketa(int, int, int);
    descriptor: (III)V
    flags: (0x0000)
    Code:
      stack=3, locals=4, args_size=4
         0: aload_0
         1: getfield      #2                  // Field c:[I
         4: iload_1
         5: sipush        610
         8: iastore
         9: aload_0
        10: getfield      #3                  // Field x:[I
        13: iload_1
        14: iload_2
        15: iastore
        16: aload_0
        17: getfield      #4                  // Field y:[I
        20: iload_1
        21: iload_3
        22: iastore
        23: aload_0
        24: getfield      #5                  // Field width:[I
        27: iload_1
        28: sipush        200
        31: iastore
        32: return
      LineNumberTable:
        line 13917: 0
        line 13918: 9
        line 13919: 16
        line 13920: 23
        line 13921: 32

  void onOkozukai(int, int, int, int, int);
    descriptor: (IIIII)V
    flags: (0x0000)
    Code:
      stack=3, locals=6, args_size=6
         0: aload_0
         1: getfield      #2                  // Field c:[I
         4: iload_1
         5: sipush        800
         8: iastore
         9: aload_0
        10: getfield      #3                  // Field x:[I
        13: iload_1
        14: iload_2
        15: iastore
        16: aload_0
        17: getfield      #4                  // Field y:[I
        20: iload_1
        21: iload_3
        22: iastore
        23: aload_0
        24: getfield      #5                  // Field width:[I
        27: iload_1
        28: iload         4
        30: iastore
        31: aload_0
        32: getfield      #13                 // Field item_int:[[I
        35: iload_1
        36: aaload
        37: iconst_0
        38: iload         5
        40: iastore
        41: return
      LineNumberTable:
        line 13934: 0
        line 13935: 9
        line 13936: 16
        line 13937: 23
        line 13938: 31
        line 13939: 41

  void activeIchigyouTime(int, int, int, int);
    descriptor: (IIII)V
    flags: (0x0000)
    Code:
      stack=3, locals=5, args_size=5
         0: aload_0
         1: getfield      #2                  // Field c:[I
         4: iload_1
         5: sipush        350
         8: iastore
         9: aload_0
        10: getfield      #3                  // Field x:[I
        13: iload_1
        14: iload_2
        15: iastore
        16: aload_0
        17: getfield      #4                  // Field y:[I
        20: iload_1
        21: iload_3
        22: iastore
        23: aload_0
        24: getfield      #5                  // Field width:[I
        27: iload_1
        28: iload         4
        30: iastore
        31: aload_0
        32: getfield      #13                 // Field item_int:[[I
        35: iload_1
        36: aaload
        37: iconst_0
        38: bipush        100
        40: iastore
        41: return
      LineNumberTable:
        line 13951: 0
        line 13952: 9
        line 13953: 16
        line 13954: 23
        line 13956: 31
        line 13957: 41

  void activeNigyouTime(int, int, int, int, java.awt.Color);
    descriptor: (IIIILjava/awt/Color;)V
    flags: (0x0000)
    Code:
      stack=3, locals=6, args_size=6
         0: aload_0
         1: getfield      #2                  // Field c:[I
         4: iload_1
         5: sipush        360
         8: iastore
         9: aload_0
        10: getfield      #3                  // Field x:[I
        13: iload_1
        14: iload_2
        15: iastore
        16: aload_0
        17: getfield      #4                  // Field y:[I
        20: iload_1
        21: iload_3
        22: iastore
        23: aload_0
        24: getfield      #5                  // Field width:[I
        27: iload_1
        28: iload         4
        30: iastore
        31: aload_0
        32: getfield      #15                 // Field item_color:[Ljava/awt/Color;
        35: iload_1
        36: aload         5
        38: aastore
        39: aload_0
        40: getfield      #13                 // Field item_int:[[I
        43: iload_1
        44: aaload
        45: iconst_0
        46: bipush        100
        48: iastore
        49: return
      LineNumberTable:
        line 13970: 0
        line 13971: 9
        line 13972: 16
        line 13973: 23
        line 13974: 31
        line 13976: 39
        line 13977: 49

  void activeJibun(int, int, int, int, int, int, int, int);
    descriptor: (IIIIIIII)V
    flags: (0x0000)
    Code:
      stack=3, locals=9, args_size=9
         0: aload_0
         1: getfield      #2                  // Field c:[I
         4: iload_1
         5: sipush        400
         8: iastore
         9: aload_0
        10: getfield      #3                  // Field x:[I
        13: iload_1
        14: iload_2
        15: iastore
        16: aload_0
        17: getfield      #4                  // Field y:[I
        20: iload_1
        21: iload_3
        22: iastore
        23: aload_0
        24: getfield      #13                 // Field item_int:[[I
        27: bipush        14
        29: aaload
        30: iconst_0
        31: iload         5
        33: iastore
        34: aload_0
        35: getfield      #13                 // Field item_int:[[I
        38: bipush        14
        40: aaload
        41: iconst_1
        42: iload         6
        44: iastore
        45: aload_0
        46: getfield      #13                 // Field item_int:[[I
        49: bipush        14
        51: aaload
        52: iconst_2
        53: iload         7
        55: iastore
        56: aload_0
        57: getfield      #13                 // Field item_int:[[I
        60: bipush        14
        62: aaload
        63: iconst_3
        64: iload         8
        66: iastore
        67: aload_0
        68: getfield      #5                  // Field width:[I
        71: iload_1
        72: iload         4
        74: iastore
        75: aload_0
        76: iconst_m1
        77: putfield      #33                 // Field c_fc:I
        80: aload_0
        81: getfield      #22                 // Field gk:LGameKey;
        84: iconst_0
        85: putfield      #34                 // Field GameKey.up_c:I
        88: aload_0
        89: getfield      #22                 // Field gk:LGameKey;
        92: iconst_0
        93: putfield      #35                 // Field GameKey.down_c:I
        96: aload_0
        97: iload_1
        98: putfield      #17                 // Field aw:I
       101: aload_0
       102: iconst_2
       103: putfield      #19                 // Field kettei_c:I
       106: aload_0
       107: iconst_2
       108: putfield      #20                 // Field cancel_c:I
       111: return
      LineNumberTable:
        line 13989: 0
        line 13990: 9
        line 13991: 16
        line 13992: 23
        line 13993: 34
        line 13994: 45
        line 13995: 56
        line 13997: 67
        line 13998: 75
        line 13999: 80
        line 14000: 88
        line 14001: 96
        line 14002: 101
        line 14003: 106
        line 14004: 111

  void activeToujou(int, int, int, int, int, java.lang.String);
    descriptor: (IIIIILjava/lang/String;)V
    flags: (0x0000)
    Code:
      stack=3, locals=7, args_size=7
         0: aload_0
         1: getfield      #2                  // Field c:[I
         4: iload_1
         5: sipush        420
         8: iastore
         9: aload_0
        10: getfield      #3                  // Field x:[I
        13: iload_1
        14: iload_2
        15: iastore
        16: aload_0
        17: getfield      #4                  // Field y:[I
        20: iload_1
        21: iload_3
        22: iastore
        23: aload_0
        24: getfield      #13                 // Field item_int:[[I
        27: iload_1
        28: aaload
        29: iconst_2
        30: iload         5
        32: iastore
        33: aload_0
        34: getfield      #11                 // Field item:[[Ljava/lang/String;
        37: iload_1
        38: aaload
        39: iconst_0
        40: aload         6
        42: aastore
        43: aload_0
        44: getfield      #5                  // Field width:[I
        47: iload_1
        48: iload         4
        50: iastore
        51: aload_0
        52: iconst_m1
        53: putfield      #33                 // Field c_fc:I
        56: aload_0
        57: getfield      #22                 // Field gk:LGameKey;
        60: iconst_0
        61: putfield      #34                 // Field GameKey.up_c:I
        64: aload_0
        65: getfield      #22                 // Field gk:LGameKey;
        68: iconst_0
        69: putfield      #35                 // Field GameKey.down_c:I
        72: aload_0
        73: iload_1
        74: putfield      #17                 // Field aw:I
        77: aload_0
        78: iconst_2
        79: putfield      #19                 // Field kettei_c:I
        82: aload_0
        83: iconst_2
        84: putfield      #20                 // Field cancel_c:I
        87: return
      LineNumberTable:
        line 14016: 0
        line 14017: 9
        line 14018: 16
        line 14019: 23
        line 14020: 33
        line 14022: 43
        line 14023: 51
        line 14024: 56
        line 14025: 64
        line 14026: 72
        line 14027: 77
        line 14028: 82
        line 14029: 87

  void initCS();
    descriptor: ()V
    flags: (0x0000)
    Code:
      stack=3, locals=1, args_size=1
         0: aload_0
         1: getfield      #7                  // Field item_kazu:[I
         4: iconst_0
         5: bipush        8
         7: iastore
         8: aload_0
         9: getfield      #6                  // Field selectedIndex:[I
        12: iconst_0
        13: iconst_0
        14: iastore
        15: return
      LineNumberTable:
        line 14035: 0
        line 14036: 8
        line 14037: 15

  void activeCS();
    descriptor: ()V
    flags: (0x0000)
    Code:
      stack=3, locals=1, args_size=1
         0: aload_0
         1: getfield      #2                  // Field c:[I
         4: iconst_0
         5: sipush        500
         8: iastore
         9: aload_0
        10: getfield      #3                  // Field x:[I
        13: iconst_0
        14: iconst_0
        15: iastore
        16: aload_0
        17: getfield      #4                  // Field y:[I
        20: iconst_0
        21: iconst_0
        22: iastore
        23: aload_0
        24: getfield      #5                  // Field width:[I
        27: iconst_0
        28: iconst_0
        29: iastore
        30: aload_0
        31: iconst_m1
        32: putfield      #33                 // Field c_fc:I
        35: aload_0
        36: getfield      #22                 // Field gk:LGameKey;
        39: iconst_0
        40: putfield      #34                 // Field GameKey.up_c:I
        43: aload_0
        44: getfield      #22                 // Field gk:LGameKey;
        47: iconst_0
        48: putfield      #35                 // Field GameKey.down_c:I
        51: aload_0
        52: iconst_0
        53: putfield      #17                 // Field aw:I
        56: aload_0
        57: iconst_2
        58: putfield      #19                 // Field kettei_c:I
        61: return
      LineNumberTable:
        line 14043: 0
        line 14044: 9
        line 14045: 16
        line 14046: 23
        line 14047: 30
        line 14048: 35
        line 14049: 43
        line 14050: 51
        line 14051: 56
        line 14052: 61

  void off(int);
    descriptor: (I)V
    flags: (0x0000)
    Code:
      stack=3, locals=2, args_size=2
         0: aload_0
         1: getfield      #2                  // Field c:[I
         4: iload_1
         5: iconst_0
         6: iastore
         7: return
      LineNumberTable:
        line 14060: 0
        line 14061: 7

  void offActivewindow(int, int);
    descriptor: (II)V
    flags: (0x0000)
    Code:
      stack=3, locals=3, args_size=3
         0: aload_0
         1: getfield      #2                  // Field c:[I
         4: iload_1
         5: iconst_0
         6: iastore
         7: aload_0
         8: iconst_m1
         9: putfield      #33                 // Field c_fc:I
        12: aload_0
        13: getfield      #22                 // Field gk:LGameKey;
        16: iconst_0
        17: putfield      #34                 // Field GameKey.up_c:I
        20: aload_0
        21: getfield      #22                 // Field gk:LGameKey;
        24: iconst_0
        25: putfield      #35                 // Field GameKey.down_c:I
        28: aload_0
        29: iload_2
        30: putfield      #17                 // Field aw:I
        33: aload_0
        34: iconst_2
        35: putfield      #19                 // Field kettei_c:I
        38: aload_0
        39: iconst_2
        40: putfield      #20                 // Field cancel_c:I
        43: return
      LineNumberTable:
        line 14070: 0
        line 14071: 7
        line 14072: 12
        line 14073: 20
        line 14074: 28
        line 14075: 33
        line 14076: 38
        line 14077: 43

  void move();
    descriptor: ()V
    flags: (0x0000)
    Code:
      stack=4, locals=1, args_size=1
         0: aload_0
         1: dup
         2: getfield      #33                 // Field c_fc:I
         5: iconst_1
         6: iadd
         7: putfield      #33                 // Field c_fc:I
        10: aload_0
        11: getfield      #33                 // Field c_fc:I
        14: bipush        6
        16: if_icmple     24
        19: aload_0
        20: iconst_0
        21: putfield      #33                 // Field c_fc:I
        24: aload_0
        25: getfield      #17                 // Field aw:I
        28: iflt          265
        31: aload_0
        32: getfield      #22                 // Field gk:LGameKey;
        35: getfield      #40                 // Field GameKey.up_f:Z
        38: iconst_1
        39: if_icmpne     77
        42: aload_0
        43: getfield      #22                 // Field gk:LGameKey;
        46: dup
        47: getfield      #34                 // Field GameKey.up_c:I
        50: iconst_1
        51: iadd
        52: putfield      #34                 // Field GameKey.up_c:I
        55: aload_0
        56: getfield      #22                 // Field gk:LGameKey;
        59: getfield      #34                 // Field GameKey.up_c:I
        62: iconst_3
        63: if_icmple     85
        66: aload_0
        67: getfield      #22                 // Field gk:LGameKey;
        70: iconst_1
        71: putfield      #34                 // Field GameKey.up_c:I
        74: goto          85
        77: aload_0
        78: getfield      #22                 // Field gk:LGameKey;
        81: iconst_0
        82: putfield      #34                 // Field GameKey.up_c:I
        85: aload_0
        86: getfield      #22                 // Field gk:LGameKey;
        89: getfield      #41                 // Field GameKey.down_f:Z
        92: iconst_1
        93: if_icmpne     131
        96: aload_0
        97: getfield      #22                 // Field gk:LGameKey;
       100: dup
       101: getfield      #35                 // Field GameKey.down_c:I
       104: iconst_1
       105: iadd
       106: putfield      #35                 // Field GameKey.down_c:I
       109: aload_0
       110: getfield      #22                 // Field gk:LGameKey;
       113: getfield      #35                 // Field GameKey.down_c:I
       116: iconst_3
       117: if_icmple     139
       120: aload_0
       121: getfield      #22                 // Field gk:LGameKey;
       124: iconst_1
       125: putfield      #35                 // Field GameKey.down_c:I
       128: goto          139
       131: aload_0
       132: getfield      #22                 // Field gk:LGameKey;
       135: iconst_0
       136: putfield      #35                 // Field GameKey.down_c:I
       139: aload_0
       140: getfield      #22                 // Field gk:LGameKey;
       143: getfield      #34                 // Field GameKey.up_c:I
       146: iconst_1
       147: if_icmpne     203
       150: aload_0
       151: getfield      #6                  // Field selectedIndex:[I
       154: aload_0
       155: getfield      #17                 // Field aw:I
       158: dup2
       159: iaload
       160: iconst_1
       161: isub
       162: iastore
       163: aload_0
       164: iconst_m1
       165: putfield      #33                 // Field c_fc:I
       168: aload_0
       169: getfield      #6                  // Field selectedIndex:[I
       172: aload_0
       173: getfield      #17                 // Field aw:I
       176: iaload
       177: ifge          265
       180: aload_0
       181: getfield      #6                  // Field selectedIndex:[I
       184: aload_0
       185: getfield      #17                 // Field aw:I
       188: aload_0
       189: getfield      #7                  // Field item_kazu:[I
       192: aload_0
       193: getfield      #17                 // Field aw:I
       196: iaload
       197: iconst_1
       198: isub
       199: iastore
       200: goto          265
       203: aload_0
       204: getfield      #22                 // Field gk:LGameKey;
       207: getfield      #35                 // Field GameKey.down_c:I
       210: iconst_1
       211: if_icmpne     265
       214: aload_0
       215: getfield      #6                  // Field selectedIndex:[I
       218: aload_0
       219: getfield      #17                 // Field aw:I
       222: dup2
       223: iaload
       224: iconst_1
       225: iadd
       226: iastore
       227: aload_0
       228: iconst_m1
       229: putfield      #33                 // Field c_fc:I
       232: aload_0
       233: getfield      #6                  // Field selectedIndex:[I
       236: aload_0
       237: getfield      #17                 // Field aw:I
       240: iaload
       241: aload_0
       242: getfield      #7                  // Field item_kazu:[I
       245: aload_0
       246: getfield      #17                 // Field aw:I
       249: iaload
       250: iconst_1
       251: isub
       252: if_icmple     265
       255: aload_0
       256: getfield      #6                  // Field selectedIndex:[I
       259: aload_0
       260: getfield      #17                 // Field aw:I
       263: iconst_0
       264: iastore
       265: aload_0
       266: getfield      #22                 // Field gk:LGameKey;
       269: getfield      #42                 // Field GameKey.tr1_f:Z
       272: ifne          283
       275: aload_0
       276: iconst_0
       277: putfield      #19                 // Field kettei_c:I
       280: goto          295
       283: aload_0
       284: getfield      #19                 // Field kettei_c:I
       287: ifne          295
       290: aload_0
       291: iconst_1
       292: putfield      #19                 // Field kettei_c:I
       295: aload_0
       296: getfield      #22                 // Field gk:LGameKey;
       299: getfield      #43                 // Field GameKey.x_f:Z
       302: ifne          313
       305: aload_0
       306: iconst_0
       307: putfield      #20                 // Field cancel_c:I
       310: goto          325
       313: aload_0
       314: getfield      #20                 // Field cancel_c:I
       317: ifne          325
       320: aload_0
       321: iconst_1
       322: putfield      #20                 // Field cancel_c:I
       325: return
      LineNumberTable:
        line 14085: 0
        line 14086: 10
        line 14089: 24
        line 14091: 31
        line 14092: 42
        line 14093: 55
        line 14094: 66
        line 14098: 77
        line 14100: 85
        line 14101: 96
        line 14102: 109
        line 14103: 120
        line 14107: 131
        line 14109: 139
        line 14110: 150
        line 14111: 163
        line 14112: 168
        line 14113: 180
        line 14116: 203
        line 14117: 214
        line 14118: 227
        line 14119: 232
        line 14120: 255
        line 14125: 265
        line 14126: 275
        line 14130: 283
        line 14131: 290
        line 14135: 295
        line 14136: 305
        line 14140: 313
        line 14141: 320
        line 14144: 325

  void drawMenus();
    descriptor: ()V
    flags: (0x0000)
    Code:
      stack=7, locals=6, args_size=1
         0: aload_0
         1: getfield      #28                 // Field hg:Ljava/awt/Graphics;
         4: new           #44                 // class java/awt/Font
         7: dup
         8: ldc           #45                 // String Dialog
        10: iconst_0
        11: bipush        12
        13: invokespecial #46                 // Method java/awt/Font."<init>":(Ljava/lang/String;II)V
        16: invokevirtual #47                 // Method java/awt/Graphics.setFont:(Ljava/awt/Font;)V
        19: iconst_0
        20: istore_1
        21: goto          6097
        24: aload_0
        25: getfield      #2                  // Field c:[I
        28: iload_1
        29: iaload
        30: istore_3
        31: iload_3
        32: ifne          38
        35: goto          6094
        38: iload_3
        39: lookupswitch  { // 21
                     100: 216
                     200: 484
                     210: 735
                     220: 980
                     300: 1237
                     310: 1363
                     320: 1541
                     321: 1868
                     330: 2199
                     350: 2494
                     360: 2621
                     400: 2939
                     410: 3651
                     420: 3377
                     500: 4645
                     600: 4734
                     610: 4873
                     700: 5079
                     800: 5399
                     900: 5538
                    1000: 5861
                 default: 6094
            }
       216: aload_0
       217: aload_0
       218: getfield      #3                  // Field x:[I
       221: iload_1
       222: iaload
       223: aload_0
       224: getfield      #4                  // Field y:[I
       227: iload_1
       228: iaload
       229: aload_0
       230: getfield      #5                  // Field width:[I
       233: iload_1
       234: iaload
       235: bipush        30
       237: aload_0
       238: getfield      #7                  // Field item_kazu:[I
       241: iload_1
       242: iaload
       243: bipush        14
       245: imul
       246: iadd
       247: invokevirtual #48                 // Method drawWindowbox:(IIII)V
       250: aload_0
       251: getfield      #28                 // Field hg:Ljava/awt/Graphics;
       254: getstatic     #49                 // Field java/awt/Color.white:Ljava/awt/Color;
       257: invokevirtual #50                 // Method java/awt/Graphics.setColor:(Ljava/awt/Color;)V
       260: aload_0
       261: getfield      #28                 // Field hg:Ljava/awt/Graphics;
       264: aload_0
       265: getfield      #9                  // Field message:[Ljava/lang/String;
       268: iload_1
       269: aaload
       270: aload_0
       271: getfield      #3                  // Field x:[I
       274: iload_1
       275: iaload
       276: bipush        24
       278: iadd
       279: aload_0
       280: getfield      #4                  // Field y:[I
       283: iload_1
       284: iaload
       285: bipush        6
       287: iadd
       288: bipush        12
       290: iadd
       291: invokevirtual #51                 // Method java/awt/Graphics.drawString:(Ljava/lang/String;II)V
       294: aload_0
       295: getfield      #7                  // Field item_kazu:[I
       298: iload_1
       299: iaload
       300: iconst_1
       301: if_icmplt     368
       304: iconst_0
       305: istore_2
       306: goto          356
       309: aload_0
       310: getfield      #28                 // Field hg:Ljava/awt/Graphics;
       313: aload_0
       314: getfield      #11                 // Field item:[[Ljava/lang/String;
       317: iload_1
       318: aaload
       319: iload_2
       320: aaload
       321: aload_0
       322: getfield      #3                  // Field x:[I
       325: iload_1
       326: iaload
       327: bipush        24
       329: iadd
       330: aload_0
       331: getfield      #4                  // Field y:[I
       334: iload_1
       335: iaload
       336: bipush        6
       338: iadd
       339: bipush        18
       341: iadd
       342: iload_2
       343: bipush        14
       345: imul
       346: iadd
       347: bipush        12
       349: iadd
       350: invokevirtual #51                 // Method java/awt/Graphics.drawString:(Ljava/lang/String;II)V
       353: iinc          2, 1
       356: iload_2
       357: aload_0
       358: getfield      #7                  // Field item_kazu:[I
       361: iload_1
       362: iaload
       363: iconst_1
       364: isub
       365: if_icmple     309
       368: iload_1
       369: aload_0
       370: getfield      #17                 // Field aw:I
       373: if_icmpne     434
       376: aload_0
       377: getfield      #33                 // Field c_fc:I
       380: iconst_3
       381: if_icmpgt     6094
       384: aload_0
       385: getfield      #28                 // Field hg:Ljava/awt/Graphics;
       388: aload_0
       389: getfield      #25                 // Field hi:[Ljava/awt/Image;
       392: bipush        70
       394: aaload
       395: aload_0
       396: getfield      #3                  // Field x:[I
       399: iload_1
       400: iaload
       401: bipush        6
       403: iadd
       404: aload_0
       405: getfield      #4                  // Field y:[I
       408: iload_1
       409: iaload
       410: bipush        24
       412: iadd
       413: aload_0
       414: getfield      #6                  // Field selectedIndex:[I
       417: iload_1
       418: iaload
       419: bipush        14
       421: imul
       422: iadd
       423: aload_0
       424: getfield      #30                 // Field ap:Ljava/applet/Applet;
       427: invokevirtual #52                 // Method java/awt/Graphics.drawImage:(Ljava/awt/Image;IILjava/awt/image/ImageObserver;)Z
       430: pop
       431: goto          6094
       434: aload_0
       435: getfield      #28                 // Field hg:Ljava/awt/Graphics;
       438: aload_0
       439: getfield      #25                 // Field hi:[Ljava/awt/Image;
       442: bipush        70
       444: aaload
       445: aload_0
       446: getfield      #3                  // Field x:[I
       449: iload_1
       450: iaload
       451: bipush        6
       453: iadd
       454: aload_0
       455: getfield      #4                  // Field y:[I
       458: iload_1
       459: iaload
       460: bipush        24
       462: iadd
       463: aload_0
       464: getfield      #6                  // Field selectedIndex:[I
       467: iload_1
       468: iaload
       469: bipush        14
       471: imul
       472: iadd
       473: aload_0
       474: getfield      #30                 // Field ap:Ljava/applet/Applet;
       477: invokevirtual #52                 // Method java/awt/Graphics.drawImage:(Ljava/awt/Image;IILjava/awt/image/ImageObserver;)Z
       480: pop
       481: goto          6094
       484: aload_0
       485: getfield      #28                 // Field hg:Ljava/awt/Graphics;
       488: getstatic     #49                 // Field java/awt/Color.white:Ljava/awt/Color;
       491: invokevirtual #50                 // Method java/awt/Graphics.setColor:(Ljava/awt/Color;)V
       494: aload_0
       495: getfield      #28                 // Field hg:Ljava/awt/Graphics;
       498: bipush        12
       500: bipush        12
       502: sipush        128
       505: bipush        58
       507: invokevirtual #53                 // Method java/awt/Graphics.fillRect:(IIII)V
       510: aload_0
       511: getfield      #28                 // Field hg:Ljava/awt/Graphics;
       514: getstatic     #54                 // Field java/awt/Color.black:Ljava/awt/Color;
       517: invokevirtual #50                 // Method java/awt/Graphics.setColor:(Ljava/awt/Color;)V
       520: aload_0
       521: getfield      #28                 // Field hg:Ljava/awt/Graphics;
       524: bipush        14
       526: bipush        14
       528: bipush        124
       530: bipush        54
       532: invokevirtual #53                 // Method java/awt/Graphics.fillRect:(IIII)V
       535: aload_0
       536: getfield      #28                 // Field hg:Ljava/awt/Graphics;
       539: getstatic     #55                 // Field java/awt/Color.cyan:Ljava/awt/Color;
       542: invokevirtual #50                 // Method java/awt/Graphics.setColor:(Ljava/awt/Color;)V
       545: aload_0
       546: getfield      #28                 // Field hg:Ljava/awt/Graphics;
       549: aload_0
       550: getfield      #11                 // Field item:[[Ljava/lang/String;
       553: bipush        14
       555: aaload
       556: iconst_0
       557: aaload
       558: bipush        18
       560: bipush        30
       562: invokevirtual #51                 // Method java/awt/Graphics.drawString:(Ljava/lang/String;II)V
       565: aload_0
       566: getfield      #13                 // Field item_int:[[I
       569: bipush        14
       571: aaload
       572: iconst_0
       573: iaload
       574: ifle          589
       577: aload_0
       578: getfield      #13                 // Field item_int:[[I
       581: bipush        14
       583: aaload
       584: iconst_2
       585: iaload
       586: ifgt          612
       589: aload_0
       590: getfield      #28                 // Field hg:Ljava/awt/Graphics;
       593: getstatic     #56                 // Field java/awt/Color.red:Ljava/awt/Color;
       596: invokevirtual #50                 // Method java/awt/Graphics.setColor:(Ljava/awt/Color;)V
       599: aload_0
       600: getfield      #28                 // Field hg:Ljava/awt/Graphics;
       603: ldc           #57                 // String 戦闘不能
       605: bipush        82
       607: bipush        30
       609: invokevirtual #51                 // Method java/awt/Graphics.drawString:(Ljava/lang/String;II)V
       612: aload_0
       613: getfield      #28                 // Field hg:Ljava/awt/Graphics;
       616: getstatic     #49                 // Field java/awt/Color.white:Ljava/awt/Color;
       619: invokevirtual #50                 // Method java/awt/Graphics.setColor:(Ljava/awt/Color;)V
       622: aload_0
       623: getfield      #28                 // Field hg:Ljava/awt/Graphics;
       626: new           #58                 // class java/lang/StringBuffer
       629: dup
       630: invokespecial #59                 // Method java/lang/StringBuffer."<init>":()V
       633: ldc           #60                 // String HP
       635: invokevirtual #61                 // Method java/lang/StringBuffer.append:(Ljava/lang/String;)Ljava/lang/StringBuffer;
       638: aload_0
       639: getfield      #13                 // Field item_int:[[I
       642: bipush        14
       644: aaload
       645: iconst_0
       646: iaload
       647: invokevirtual #62                 // Method java/lang/StringBuffer.append:(I)Ljava/lang/StringBuffer;
       650: ldc           #63                 // String  /
       652: invokevirtual #61                 // Method java/lang/StringBuffer.append:(Ljava/lang/String;)Ljava/lang/StringBuffer;
       655: aload_0
       656: getfield      #13                 // Field item_int:[[I
       659: bipush        14
       661: aaload
       662: iconst_1
       663: iaload
       664: invokevirtual #62                 // Method java/lang/StringBuffer.append:(I)Ljava/lang/StringBuffer;
       667: invokevirtual #64                 // Method java/lang/StringBuffer.toString:()Ljava/lang/String;
       670: bipush        18
       672: bipush        48
       674: invokevirtual #51                 // Method java/awt/Graphics.drawString:(Ljava/lang/String;II)V
       677: aload_0
       678: getfield      #28                 // Field hg:Ljava/awt/Graphics;
       681: new           #58                 // class java/lang/StringBuffer
       684: dup
       685: invokespecial #59                 // Method java/lang/StringBuffer."<init>":()V
       688: ldc           #65                 // String PP
       690: invokevirtual #61                 // Method java/lang/StringBuffer.append:(Ljava/lang/String;)Ljava/lang/StringBuffer;
       693: aload_0
       694: getfield      #13                 // Field item_int:[[I
       697: bipush        14
       699: aaload
       700: iconst_2
       701: iaload
       702: invokevirtual #62                 // Method java/lang/StringBuffer.append:(I)Ljava/lang/StringBuffer;
       705: ldc           #63                 // String  /
       707: invokevirtual #61                 // Method java/lang/StringBuffer.append:(Ljava/lang/String;)Ljava/lang/StringBuffer;
       710: aload_0
       711: getfield      #13                 // Field item_int:[[I
       714: bipush        14
       716: aaload
       717: iconst_3
       718: iaload
       719: invokevirtual #62                 // Method java/lang/StringBuffer.append:(I)Ljava/lang/StringBuffer;
       722: invokevirtual #64                 // Method java/lang/StringBuffer.toString:()Ljava/lang/String;
       725: bipush        18
       727: bipush        62
       729: invokevirtual #51                 // Method java/awt/Graphics.drawString:(Ljava/lang/String;II)V
       732: goto          6094
       735: aload_0
       736: getfield      #28                 // Field hg:Ljava/awt/Graphics;
       739: getstatic     #49                 // Field java/awt/Color.white:Ljava/awt/Color;
       742: invokevirtual #50                 // Method java/awt/Graphics.setColor:(Ljava/awt/Color;)V
       745: aload_0
       746: getfield      #28                 // Field hg:Ljava/awt/Graphics;
       749: sipush        160
       752: bipush        12
       754: sipush        128
       757: bipush        58
       759: invokevirtual #53                 // Method java/awt/Graphics.fillRect:(IIII)V
       762: aload_0
       763: getfield      #28                 // Field hg:Ljava/awt/Graphics;
       766: getstatic     #54                 // Field java/awt/Color.black:Ljava/awt/Color;
       769: invokevirtual #50                 // Method java/awt/Graphics.setColor:(Ljava/awt/Color;)V
       772: aload_0
       773: getfield      #28                 // Field hg:Ljava/awt/Graphics;
       776: sipush        162
       779: bipush        14
       781: bipush        124
       783: bipush        54
       785: invokevirtual #53                 // Method java/awt/Graphics.fillRect:(IIII)V
       788: aload_0
       789: getfield      #28                 // Field hg:Ljava/awt/Graphics;
       792: getstatic     #66                 // Field java/awt/Color.green:Ljava/awt/Color;
       795: invokevirtual #50                 // Method java/awt/Graphics.setColor:(Ljava/awt/Color;)V
       798: aload_0
       799: getfield      #28                 // Field hg:Ljava/awt/Graphics;
       802: aload_0
       803: getfield      #11                 // Field item:[[Ljava/lang/String;
       806: bipush        15
       808: aaload
       809: iconst_0
       810: aaload
       811: sipush        166
       814: bipush        30
       816: invokevirtual #51                 // Method java/awt/Graphics.drawString:(Ljava/lang/String;II)V
       819: aload_0
       820: getfield      #13                 // Field item_int:[[I
       823: bipush        15
       825: aaload
       826: iconst_0
       827: iaload
       828: ifgt          855
       831: aload_0
       832: getfield      #28                 // Field hg:Ljava/awt/Graphics;
       835: getstatic     #56                 // Field java/awt/Color.red:Ljava/awt/Color;
       838: invokevirtual #50                 // Method java/awt/Graphics.setColor:(Ljava/awt/Color;)V
       841: aload_0
       842: getfield      #28                 // Field hg:Ljava/awt/Graphics;
       845: ldc           #57                 // String 戦闘不能
       847: sipush        230
       850: bipush        30
       852: invokevirtual #51                 // Method java/awt/Graphics.drawString:(Ljava/lang/String;II)V
       855: aload_0
       856: getfield      #28                 // Field hg:Ljava/awt/Graphics;
       859: getstatic     #49                 // Field java/awt/Color.white:Ljava/awt/Color;
       862: invokevirtual #50                 // Method java/awt/Graphics.setColor:(Ljava/awt/Color;)V
       865: aload_0
       866: getfield      #28                 // Field hg:Ljava/awt/Graphics;
       869: new           #58                 // class java/lang/StringBuffer
       872: dup
       873: invokespecial #59                 // Method java/lang/StringBuffer."<init>":()V
       876: ldc           #60                 // String HP
       878: invokevirtual #61                 // Method java/lang/StringBuffer.append:(Ljava/lang/String;)Ljava/lang/StringBuffer;
       881: aload_0
       882: getfield      #13                 // Field item_int:[[I
       885: bipush        15
       887: aaload
       888: iconst_0
       889: iaload
       890: invokevirtual #62                 // Method java/lang/StringBuffer.append:(I)Ljava/lang/StringBuffer;
       893: ldc           #63                 // String  /
       895: invokevirtual #61                 // Method java/lang/StringBuffer.append:(Ljava/lang/String;)Ljava/lang/StringBuffer;
       898: aload_0
       899: getfield      #13                 // Field item_int:[[I
       902: bipush        15
       904: aaload
       905: iconst_1
       906: iaload
       907: invokevirtual #62                 // Method java/lang/StringBuffer.append:(I)Ljava/lang/StringBuffer;
       910: invokevirtual #64                 // Method java/lang/StringBuffer.toString:()Ljava/lang/String;
       913: sipush        166
       916: bipush        48
       918: invokevirtual #51                 // Method java/awt/Graphics.drawString:(Ljava/lang/String;II)V
       921: aload_0
       922: getfield      #28                 // Field hg:Ljava/awt/Graphics;
       925: new           #58                 // class java/lang/StringBuffer
       928: dup
       929: invokespecial #59                 // Method java/lang/StringBuffer."<init>":()V
       932: ldc           #65                 // String PP
       934: invokevirtual #61                 // Method java/lang/StringBuffer.append:(Ljava/lang/String;)Ljava/lang/StringBuffer;
       937: aload_0
       938: getfield      #13                 // Field item_int:[[I
       941: bipush        15
       943: aaload
       944: iconst_2
       945: iaload
       946: invokevirtual #62                 // Method java/lang/StringBuffer.append:(I)Ljava/lang/StringBuffer;
       949: ldc           #63                 // String  /
       951: invokevirtual #61                 // Method java/lang/StringBuffer.append:(Ljava/lang/String;)Ljava/lang/StringBuffer;
       954: aload_0
       955: getfield      #13                 // Field item_int:[[I
       958: bipush        15
       960: aaload
       961: iconst_3
       962: iaload
       963: invokevirtual #62                 // Method java/lang/StringBuffer.append:(I)Ljava/lang/StringBuffer;
       966: invokevirtual #64                 // Method java/lang/StringBuffer.toString:()Ljava/lang/String;
       969: sipush        166
       972: bipush        62
       974: invokevirtual #51                 // Method java/awt/Graphics.drawString:(Ljava/lang/String;II)V
       977: goto          6094
       980: aload_0
       981: getfield      #28                 // Field hg:Ljava/awt/Graphics;
       984: getstatic     #49                 // Field java/awt/Color.white:Ljava/awt/Color;
       987: invokevirtual #50                 // Method java/awt/Graphics.setColor:(Ljava/awt/Color;)V
       990: aload_0
       991: getfield      #28                 // Field hg:Ljava/awt/Graphics;
       994: sipush        372
       997: bipush        12
       999: sipush        128
      1002: bipush        58
      1004: invokevirtual #53                 // Method java/awt/Graphics.fillRect:(IIII)V
      1007: aload_0
      1008: getfield      #28                 // Field hg:Ljava/awt/Graphics;
      1011: getstatic     #54                 // Field java/awt/Color.black:Ljava/awt/Color;
      1014: invokevirtual #50                 // Method java/awt/Graphics.setColor:(Ljava/awt/Color;)V
      1017: aload_0
      1018: getfield      #28                 // Field hg:Ljava/awt/Graphics;
      1021: sipush        374
      1024: bipush        14
      1026: bipush        124
      1028: bipush        54
      1030: invokevirtual #53                 // Method java/awt/Graphics.fillRect:(IIII)V
      1033: aload_0
      1034: getfield      #28                 // Field hg:Ljava/awt/Graphics;
      1037: getstatic     #55                 // Field java/awt/Color.cyan:Ljava/awt/Color;
      1040: invokevirtual #50                 // Method java/awt/Graphics.setColor:(Ljava/awt/Color;)V
      1043: aload_0
      1044: getfield      #28                 // Field hg:Ljava/awt/Graphics;
      1047: aload_0
      1048: getfield      #11                 // Field item:[[Ljava/lang/String;
      1051: bipush        15
      1053: aaload
      1054: iconst_0
      1055: aaload
      1056: sipush        378
      1059: bipush        30
      1061: invokevirtual #51                 // Method java/awt/Graphics.drawString:(Ljava/lang/String;II)V
      1064: aload_0
      1065: getfield      #13                 // Field item_int:[[I
      1068: bipush        15
      1070: aaload
      1071: iconst_0
      1072: iaload
      1073: ifle          1088
      1076: aload_0
      1077: getfield      #13                 // Field item_int:[[I
      1080: bipush        15
      1082: aaload
      1083: iconst_2
      1084: iaload
      1085: ifgt          1112
      1088: aload_0
      1089: getfield      #28                 // Field hg:Ljava/awt/Graphics;
      1092: getstatic     #56                 // Field java/awt/Color.red:Ljava/awt/Color;
      1095: invokevirtual #50                 // Method java/awt/Graphics.setColor:(Ljava/awt/Color;)V
      1098: aload_0
      1099: getfield      #28                 // Field hg:Ljava/awt/Graphics;
      1102: ldc           #57                 // String 戦闘不能
      1104: sipush        442
      1107: bipush        30
      1109: invokevirtual #51                 // Method java/awt/Graphics.drawString:(Ljava/lang/String;II)V
      1112: aload_0
      1113: getfield      #28                 // Field hg:Ljava/awt/Graphics;
      1116: getstatic     #49                 // Field java/awt/Color.white:Ljava/awt/Color;
      1119: invokevirtual #50                 // Method java/awt/Graphics.setColor:(Ljava/awt/Color;)V
      1122: aload_0
      1123: getfield      #28                 // Field hg:Ljava/awt/Graphics;
      1126: new           #58                 // class java/lang/StringBuffer
      1129: dup
      1130: invokespecial #59                 // Method java/lang/StringBuffer."<init>":()V
      1133: ldc           #60                 // String HP
      1135: invokevirtual #61                 // Method java/lang/StringBuffer.append:(Ljava/lang/String;)Ljava/lang/StringBuffer;
      1138: aload_0
      1139: getfield      #13                 // Field item_int:[[I
      1142: bipush        15
      1144: aaload
      1145: iconst_0
      1146: iaload
      1147: invokevirtual #62                 // Method java/lang/StringBuffer.append:(I)Ljava/lang/StringBuffer;
      1150: ldc           #63                 // String  /
      1152: invokevirtual #61                 // Method java/lang/StringBuffer.append:(Ljava/lang/String;)Ljava/lang/StringBuffer;
      1155: aload_0
      1156: getfield      #13                 // Field item_int:[[I
      1159: bipush        15
      1161: aaload
      1162: iconst_1
      1163: iaload
      1164: invokevirtual #62                 // Method java/lang/StringBuffer.append:(I)Ljava/lang/StringBuffer;
      1167: invokevirtual #64                 // Method java/lang/StringBuffer.toString:()Ljava/lang/String;
      1170: sipush        378
      1173: bipush        48
      1175: invokevirtual #51                 // Method java/awt/Graphics.drawString:(Ljava/lang/String;II)V
      1178: aload_0
      1179: getfield      #28                 // Field hg:Ljava/awt/Graphics;
      1182: new           #58                 // class java/lang/StringBuffer
      1185: dup
      1186: invokespecial #59                 // Method java/lang/StringBuffer."<init>":()V
      1189: ldc           #65                 // String PP
      1191: invokevirtual #61                 // Method java/lang/StringBuffer.append:(Ljava/lang/String;)Ljava/lang/StringBuffer;
      1194: aload_0
      1195: getfield      #13                 // Field item_int:[[I
      1198: bipush        15
      1200: aaload
      1201: iconst_2
      1202: iaload
      1203: invokevirtual #62                 // Method java/lang/StringBuffer.append:(I)Ljava/lang/StringBuffer;
      1206: ldc           #63                 // String  /
      1208: invokevirtual #61                 // Method java/lang/StringBuffer.append:(Ljava/lang/String;)Ljava/lang/StringBuffer;
      1211: aload_0
      1212: getfield      #13                 // Field item_int:[[I
      1215: bipush        15
      1217: aaload
      1218: iconst_3
      1219: iaload
      1220: invokevirtual #62                 // Method java/lang/StringBuffer.append:(I)Ljava/lang/StringBuffer;
      1223: invokevirtual #64                 // Method java/lang/StringBuffer.toString:()Ljava/lang/String;
      1226: sipush        378
      1229: bipush        62
      1231: invokevirtual #51                 // Method java/awt/Graphics.drawString:(Ljava/lang/String;II)V
      1234: goto          6094
      1237: aload_0
      1238: aload_0
      1239: getfield      #3                  // Field x:[I
      1242: iload_1
      1243: iaload
      1244: aload_0
      1245: getfield      #4                  // Field y:[I
      1248: iload_1
      1249: iaload
      1250: aload_0
      1251: getfield      #5                  // Field width:[I
      1254: iload_1
      1255: iaload
      1256: bipush        40
      1258: invokevirtual #48                 // Method drawWindowbox:(IIII)V
      1261: aload_0
      1262: getfield      #28                 // Field hg:Ljava/awt/Graphics;
      1265: getstatic     #49                 // Field java/awt/Color.white:Ljava/awt/Color;
      1268: invokevirtual #50                 // Method java/awt/Graphics.setColor:(Ljava/awt/Color;)V
      1271: aload_0
      1272: getfield      #28                 // Field hg:Ljava/awt/Graphics;
      1275: aload_0
      1276: getfield      #11                 // Field item:[[Ljava/lang/String;
      1279: iload_1
      1280: aaload
      1281: iconst_0
      1282: aaload
      1283: aload_0
      1284: getfield      #3                  // Field x:[I
      1287: iload_1
      1288: iaload
      1289: bipush        6
      1291: iadd
      1292: aload_0
      1293: getfield      #4                  // Field y:[I
      1296: iload_1
      1297: iaload
      1298: bipush        6
      1300: iadd
      1301: bipush        12
      1303: iadd
      1304: invokevirtual #51                 // Method java/awt/Graphics.drawString:(Ljava/lang/String;II)V
      1307: aload_0
      1308: getfield      #33                 // Field c_fc:I
      1311: iconst_3
      1312: if_icmpgt     6094
      1315: aload_0
      1316: getfield      #21                 // Field gg:LGameGraphics;
      1319: aload_0
      1320: getfield      #3                  // Field x:[I
      1323: iload_1
      1324: iaload
      1325: aload_0
      1326: getfield      #5                  // Field width:[I
      1329: iload_1
      1330: iaload
      1331: bipush        14
      1333: isub
      1334: iconst_2
      1335: idiv
      1336: iadd
      1337: aload_0
      1338: getfield      #4                  // Field y:[I
      1341: iload_1
      1342: iaload
      1343: bipush        6
      1345: iadd
      1346: bipush        14
      1348: iadd
      1349: iconst_0
      1350: iadd
      1351: iconst_2
      1352: iadd
      1353: sipush        201
      1356: iconst_0
      1357: invokevirtual #67                 // Method GameGraphics.drawPT:(IIII)V
      1360: goto          6094
      1363: aload_0
      1364: aload_0
      1365: getfield      #3                  // Field x:[I
      1368: iload_1
      1369: iaload
      1370: aload_0
      1371: getfield      #4                  // Field y:[I
      1374: iload_1
      1375: iaload
      1376: aload_0
      1377: getfield      #5                  // Field width:[I
      1380: iload_1
      1381: iaload
      1382: bipush        58
      1384: invokevirtual #48                 // Method drawWindowbox:(IIII)V
      1387: aload_0
      1388: getfield      #28                 // Field hg:Ljava/awt/Graphics;
      1391: aload_0
      1392: getfield      #15                 // Field item_color:[Ljava/awt/Color;
      1395: iload_1
      1396: aaload
      1397: invokevirtual #50                 // Method java/awt/Graphics.setColor:(Ljava/awt/Color;)V
      1400: aload_0
      1401: getfield      #28                 // Field hg:Ljava/awt/Graphics;
      1404: aload_0
      1405: getfield      #11                 // Field item:[[Ljava/lang/String;
      1408: iload_1
      1409: aaload
      1410: iconst_0
      1411: aaload
      1412: aload_0
      1413: getfield      #3                  // Field x:[I
      1416: iload_1
      1417: iaload
      1418: bipush        6
      1420: iadd
      1421: aload_0
      1422: getfield      #4                  // Field y:[I
      1425: iload_1
      1426: iaload
      1427: bipush        6
      1429: iadd
      1430: bipush        12
      1432: iadd
      1433: invokevirtual #51                 // Method java/awt/Graphics.drawString:(Ljava/lang/String;II)V
      1436: aload_0
      1437: getfield      #28                 // Field hg:Ljava/awt/Graphics;
      1440: getstatic     #49                 // Field java/awt/Color.white:Ljava/awt/Color;
      1443: invokevirtual #50                 // Method java/awt/Graphics.setColor:(Ljava/awt/Color;)V
      1446: aload_0
      1447: getfield      #28                 // Field hg:Ljava/awt/Graphics;
      1450: aload_0
      1451: getfield      #11                 // Field item:[[Ljava/lang/String;
      1454: iload_1
      1455: aaload
      1456: iconst_1
      1457: aaload
      1458: aload_0
      1459: getfield      #3                  // Field x:[I
      1462: iload_1
      1463: iaload
      1464: bipush        6
      1466: iadd
      1467: aload_0
      1468: getfield      #4                  // Field y:[I
      1471: iload_1
      1472: iaload
      1473: bipush        6
      1475: iadd
      1476: bipush        18
      1478: iadd
      1479: bipush        12
      1481: iadd
      1482: invokevirtual #51                 // Method java/awt/Graphics.drawString:(Ljava/lang/String;II)V
      1485: aload_0
      1486: getfield      #33                 // Field c_fc:I
      1489: iconst_3
      1490: if_icmpgt     6094
      1493: aload_0
      1494: getfield      #21                 // Field gg:LGameGraphics;
      1497: aload_0
      1498: getfield      #3                  // Field x:[I
      1501: iload_1
      1502: iaload
      1503: aload_0
      1504: getfield      #5                  // Field width:[I
      1507: iload_1
      1508: iaload
      1509: bipush        14
      1511: isub
      1512: iconst_2
      1513: idiv
      1514: iadd
      1515: aload_0
      1516: getfield      #4                  // Field y:[I
      1519: iload_1
      1520: iaload
      1521: bipush        6
      1523: iadd
      1524: bipush        18
      1526: iadd
      1527: bipush        14
      1529: iadd
      1530: iconst_2
      1531: iadd
      1532: bipush        71
      1534: iconst_0
      1535: invokevirtual #67                 // Method GameGraphics.drawPT:(IIII)V
      1538: goto          6094
      1541: aload_0
      1542: aload_0
      1543: getfield      #3                  // Field x:[I
      1546: iload_1
      1547: iaload
      1548: aload_0
      1549: getfield      #4                  // Field y:[I
      1552: iload_1
      1553: iaload
      1554: aload_0
      1555: getfield      #5                  // Field width:[I
      1558: iload_1
      1559: iaload
      1560: bipush        66
      1562: aload_0
      1563: getfield      #7                  // Field item_kazu:[I
      1566: iload_1
      1567: iaload
      1568: iconst_3
      1569: isub
      1570: bipush        14
      1572: imul
      1573: iadd
      1574: bipush        14
      1576: iadd
      1577: invokevirtual #48                 // Method drawWindowbox:(IIII)V
      1580: aload_0
      1581: getfield      #28                 // Field hg:Ljava/awt/Graphics;
      1584: getstatic     #68                 // Field java/awt/Color.magenta:Ljava/awt/Color;
      1587: invokevirtual #50                 // Method java/awt/Graphics.setColor:(Ljava/awt/Color;)V
      1590: aload_0
      1591: getfield      #28                 // Field hg:Ljava/awt/Graphics;
      1594: aload_0
      1595: getfield      #11                 // Field item:[[Ljava/lang/String;
      1598: iload_1
      1599: aaload
      1600: iconst_0
      1601: aaload
      1602: aload_0
      1603: getfield      #3                  // Field x:[I
      1606: iload_1
      1607: iaload
      1608: bipush        6
      1610: iadd
      1611: aload_0
      1612: getfield      #4                  // Field y:[I
      1615: iload_1
      1616: iaload
      1617: bipush        6
      1619: iadd
      1620: bipush        12
      1622: iadd
      1623: invokevirtual #51                 // Method java/awt/Graphics.drawString:(Ljava/lang/String;II)V
      1626: aload_0
      1627: getfield      #28                 // Field hg:Ljava/awt/Graphics;
      1630: getstatic     #49                 // Field java/awt/Color.white:Ljava/awt/Color;
      1633: invokevirtual #50                 // Method java/awt/Graphics.setColor:(Ljava/awt/Color;)V
      1636: aload_0
      1637: getfield      #28                 // Field hg:Ljava/awt/Graphics;
      1640: aload_0
      1641: getfield      #11                 // Field item:[[Ljava/lang/String;
      1644: iload_1
      1645: aaload
      1646: iconst_1
      1647: aaload
      1648: aload_0
      1649: getfield      #3                  // Field x:[I
      1652: iload_1
      1653: iaload
      1654: bipush        6
      1656: iadd
      1657: aload_0
      1658: getfield      #4                  // Field y:[I
      1661: iload_1
      1662: iaload
      1663: bipush        6
      1665: iadd
      1666: bipush        18
      1668: iadd
      1669: bipush        12
      1671: iadd
      1672: invokevirtual #51                 // Method java/awt/Graphics.drawString:(Ljava/lang/String;II)V
      1675: aload_0
      1676: getfield      #28                 // Field hg:Ljava/awt/Graphics;
      1679: getstatic     #55                 // Field java/awt/Color.cyan:Ljava/awt/Color;
      1682: invokevirtual #50                 // Method java/awt/Graphics.setColor:(Ljava/awt/Color;)V
      1685: aload_0
      1686: getfield      #28                 // Field hg:Ljava/awt/Graphics;
      1689: aload_0
      1690: getfield      #11                 // Field item:[[Ljava/lang/String;
      1693: iload_1
      1694: aaload
      1695: iconst_2
      1696: aaload
      1697: aload_0
      1698: getfield      #3                  // Field x:[I
      1701: iload_1
      1702: iaload
      1703: bipush        6
      1705: iadd
      1706: aload_0
      1707: getfield      #4                  // Field y:[I
      1710: iload_1
      1711: iaload
      1712: bipush        6
      1714: iadd
      1715: bipush        36
      1717: iadd
      1718: bipush        12
      1720: iadd
      1721: invokevirtual #51                 // Method java/awt/Graphics.drawString:(Ljava/lang/String;II)V
      1724: aload_0
      1725: getfield      #28                 // Field hg:Ljava/awt/Graphics;
      1728: getstatic     #49                 // Field java/awt/Color.white:Ljava/awt/Color;
      1731: invokevirtual #50                 // Method java/awt/Graphics.setColor:(Ljava/awt/Color;)V
      1734: iconst_0
      1735: istore_2
      1736: goto          1788
      1739: aload_0
      1740: getfield      #28                 // Field hg:Ljava/awt/Graphics;
      1743: aload_0
      1744: getfield      #11                 // Field item:[[Ljava/lang/String;
      1747: iconst_3
      1748: aaload
      1749: iload_2
      1750: iconst_3
      1751: iadd
      1752: aaload
      1753: aload_0
      1754: getfield      #3                  // Field x:[I
      1757: iconst_3
      1758: iaload
      1759: bipush        6
      1761: iadd
      1762: aload_0
      1763: getfield      #4                  // Field y:[I
      1766: iconst_3
      1767: iaload
      1768: bipush        6
      1770: iadd
      1771: bipush        54
      1773: iadd
      1774: iload_2
      1775: bipush        14
      1777: imul
      1778: iadd
      1779: bipush        12
      1781: iadd
      1782: invokevirtual #51                 // Method java/awt/Graphics.drawString:(Ljava/lang/String;II)V
      1785: iinc          2, 1
      1788: iload_2
      1789: aload_0
      1790: getfield      #7                  // Field item_kazu:[I
      1793: iconst_3
      1794: iaload
      1795: iconst_4
      1796: isub
      1797: if_icmple     1739
      1800: aload_0
      1801: getfield      #33                 // Field c_fc:I
      1804: iconst_3
      1805: if_icmpgt     6094
      1808: aload_0
      1809: getfield      #21                 // Field gg:LGameGraphics;
      1812: aload_0
      1813: getfield      #3                  // Field x:[I
      1816: iload_1
      1817: iaload
      1818: aload_0
      1819: getfield      #5                  // Field width:[I
      1822: iload_1
      1823: iaload
      1824: bipush        14
      1826: isub
      1827: iconst_2
      1828: idiv
      1829: iadd
      1830: aload_0
      1831: getfield      #4                  // Field y:[I
      1834: iload_1
      1835: iaload
      1836: bipush        6
      1838: iadd
      1839: bipush        18
      1841: iadd
      1842: bipush        36
      1844: iadd
      1845: aload_0
      1846: getfield      #7                  // Field item_kazu:[I
      1849: iload_1
      1850: iaload
      1851: iconst_3
      1852: isub
      1853: bipush        14
      1855: imul
      1856: iadd
      1857: iconst_2
      1858: iadd
      1859: bipush        71
      1861: iconst_0
      1862: invokevirtual #67                 // Method GameGraphics.drawPT:(IIII)V
      1865: goto          6094
      1868: aload_0
      1869: aload_0
      1870: getfield      #3                  // Field x:[I
      1873: iload_1
      1874: iaload
      1875: aload_0
      1876: getfield      #4                  // Field y:[I
      1879: iload_1
      1880: iaload
      1881: aload_0
      1882: getfield      #5                  // Field width:[I
      1885: iload_1
      1886: iaload
      1887: bipush        108
      1889: invokevirtual #48                 // Method drawWindowbox:(IIII)V
      1892: aload_0
      1893: getfield      #28                 // Field hg:Ljava/awt/Graphics;
      1896: getstatic     #55                 // Field java/awt/Color.cyan:Ljava/awt/Color;
      1899: invokevirtual #50                 // Method java/awt/Graphics.setColor:(Ljava/awt/Color;)V
      1902: aload_0
      1903: getfield      #28                 // Field hg:Ljava/awt/Graphics;
      1906: aload_0
      1907: getfield      #11                 // Field item:[[Ljava/lang/String;
      1910: iload_1
      1911: aaload
      1912: iconst_0
      1913: aaload
      1914: aload_0
      1915: getfield      #3                  // Field x:[I
      1918: iload_1
      1919: iaload
      1920: bipush        6
      1922: iadd
      1923: aload_0
      1924: getfield      #4                  // Field y:[I
      1927: iload_1
      1928: iaload
      1929: bipush        6
      1931: iadd
      1932: bipush        12
      1934: iadd
      1935: invokevirtual #51                 // Method java/awt/Graphics.drawString:(Ljava/lang/String;II)V
      1938: aload_0
      1939: getfield      #28                 // Field hg:Ljava/awt/Graphics;
      1942: getstatic     #49                 // Field java/awt/Color.white:Ljava/awt/Color;
      1945: invokevirtual #50                 // Method java/awt/Graphics.setColor:(Ljava/awt/Color;)V
      1948: aload_0
      1949: getfield      #28                 // Field hg:Ljava/awt/Graphics;
      1952: aload_0
      1953: getfield      #11                 // Field item:[[Ljava/lang/String;
      1956: iload_1
      1957: aaload
      1958: iconst_1
      1959: aaload
      1960: aload_0
      1961: getfield      #3                  // Field x:[I
      1964: iload_1
      1965: iaload
      1966: bipush        6
      1968: iadd
      1969: aload_0
      1970: getfield      #4                  // Field y:[I
      1973: iload_1
      1974: iaload
      1975: bipush        6
      1977: iadd
      1978: bipush        18
      1980: iadd
      1981: bipush        12
      1983: iadd
      1984: invokevirtual #51                 // Method java/awt/Graphics.drawString:(Ljava/lang/String;II)V
      1987: aload_0
      1988: getfield      #28                 // Field hg:Ljava/awt/Graphics;
      1991: getstatic     #68                 // Field java/awt/Color.magenta:Ljava/awt/Color;
      1994: invokevirtual #50                 // Method java/awt/Graphics.setColor:(Ljava/awt/Color;)V
      1997: aload_0
      1998: getfield      #28                 // Field hg:Ljava/awt/Graphics;
      2001: aload_0
      2002: getfield      #11                 // Field item:[[Ljava/lang/String;
      2005: iload_1
      2006: aaload
      2007: iconst_2
      2008: aaload
      2009: aload_0
      2010: getfield      #3                  // Field x:[I
      2013: iload_1
      2014: iaload
      2015: bipush        6
      2017: iadd
      2018: aload_0
      2019: getfield      #4                  // Field y:[I
      2022: iload_1
      2023: iaload
      2024: bipush        6
      2026: iadd
      2027: bipush        36
      2029: iadd
      2030: bipush        12
      2032: iadd
      2033: invokevirtual #51                 // Method java/awt/Graphics.drawString:(Ljava/lang/String;II)V
      2036: aload_0
      2037: getfield      #28                 // Field hg:Ljava/awt/Graphics;
      2040: getstatic     #49                 // Field java/awt/Color.white:Ljava/awt/Color;
      2043: invokevirtual #50                 // Method java/awt/Graphics.setColor:(Ljava/awt/Color;)V
      2046: aload_0
      2047: getfield      #28                 // Field hg:Ljava/awt/Graphics;
      2050: aload_0
      2051: getfield      #11                 // Field item:[[Ljava/lang/String;
      2054: iload_1
      2055: aaload
      2056: iconst_3
      2057: aaload
      2058: aload_0
      2059: getfield      #3                  // Field x:[I
      2062: iload_1
      2063: iaload
      2064: bipush        6
      2066: iadd
      2067: aload_0
      2068: getfield      #4                  // Field y:[I
      2071: iload_1
      2072: iaload
      2073: bipush        6
      2075: iadd
      2076: bipush        54
      2078: iadd
      2079: bipush        12
      2081: iadd
      2082: invokevirtual #51                 // Method java/awt/Graphics.drawString:(Ljava/lang/String;II)V
      2085: aload_0
      2086: getfield      #28                 // Field hg:Ljava/awt/Graphics;
      2089: getstatic     #49                 // Field java/awt/Color.white:Ljava/awt/Color;
      2092: invokevirtual #50                 // Method java/awt/Graphics.setColor:(Ljava/awt/Color;)V
      2095: aload_0
      2096: getfield      #28                 // Field hg:Ljava/awt/Graphics;
      2099: aload_0
      2100: getfield      #11                 // Field item:[[Ljava/lang/String;
      2103: iload_1
      2104: aaload
      2105: iconst_4
      2106: aaload
      2107: aload_0
      2108: getfield      #3                  // Field x:[I
      2111: iload_1
      2112: iaload
      2113: bipush        6
      2115: iadd
      2116: aload_0
      2117: getfield      #4                  // Field y:[I
      2120: iload_1
      2121: iaload
      2122: bipush        6
      2124: iadd
      2125: bipush        54
      2127: iadd
      2128: bipush        14
      2130: iadd
      2131: bipush        12
      2133: iadd
      2134: invokevirtual #51                 // Method java/awt/Graphics.drawString:(Ljava/lang/String;II)V
      2137: aload_0
      2138: getfield      #33                 // Field c_fc:I
      2141: iconst_3
      2142: if_icmpgt     6094
      2145: aload_0
      2146: getfield      #21                 // Field gg:LGameGraphics;
      2149: aload_0
      2150: getfield      #3                  // Field x:[I
      2153: iload_1
      2154: iaload
      2155: aload_0
      2156: getfield      #5                  // Field width:[I
      2159: iload_1
      2160: iaload
      2161: bipush        14
      2163: isub
      2164: iconst_2
      2165: idiv
      2166: iadd
      2167: aload_0
      2168: getfield      #4                  // Field y:[I
      2171: iload_1
      2172: iaload
      2173: bipush        6
      2175: iadd
      2176: bipush        18
      2178: iadd
      2179: bipush        36
      2181: iadd
      2182: bipush        14
      2184: iadd
      2185: bipush        14
      2187: iadd
      2188: iconst_2
      2189: iadd
      2190: bipush        71
      2192: iconst_0
      2193: invokevirtual #67                 // Method GameGraphics.drawPT:(IIII)V
      2196: goto          6094
      2199: aload_0
      2200: aload_0
      2201: getfield      #3                  // Field x:[I
      2204: iload_1
      2205: iaload
      2206: aload_0
      2207: getfield      #4                  // Field y:[I
      2210: iload_1
      2211: iaload
      2212: aload_0
      2213: getfield      #5                  // Field width:[I
      2216: iload_1
      2217: iaload
      2218: bipush        30
      2220: aload_0
      2221: getfield      #7                  // Field item_kazu:[I
      2224: iload_1
      2225: iaload
      2226: iconst_1
      2227: iadd
      2228: bipush        14
      2230: imul
      2231: iadd
      2232: invokevirtual #48                 // Method drawWindowbox:(IIII)V
      2235: aload_0
      2236: getfield      #28                 // Field hg:Ljava/awt/Graphics;
      2239: aload_0
      2240: getfield      #15                 // Field item_color:[Ljava/awt/Color;
      2243: iload_1
      2244: aaload
      2245: invokevirtual #50                 // Method java/awt/Graphics.setColor:(Ljava/awt/Color;)V
      2248: aload_0
      2249: getfield      #28                 // Field hg:Ljava/awt/Graphics;
      2252: aload_0
      2253: getfield      #9                  // Field message:[Ljava/lang/String;
      2256: iload_1
      2257: aaload
      2258: aload_0
      2259: getfield      #3                  // Field x:[I
      2262: iload_1
      2263: iaload
      2264: bipush        6
      2266: iadd
      2267: aload_0
      2268: getfield      #4                  // Field y:[I
      2271: iload_1
      2272: iaload
      2273: bipush        6
      2275: iadd
      2276: bipush        12
      2278: iadd
      2279: invokevirtual #51                 // Method java/awt/Graphics.drawString:(Ljava/lang/String;II)V
      2282: aload_0
      2283: getfield      #28                 // Field hg:Ljava/awt/Graphics;
      2286: getstatic     #49                 // Field java/awt/Color.white:Ljava/awt/Color;
      2289: invokevirtual #50                 // Method java/awt/Graphics.setColor:(Ljava/awt/Color;)V
      2292: aload_0
      2293: getfield      #7                  // Field item_kazu:[I
      2296: iload_1
      2297: iaload
      2298: iconst_1
      2299: if_icmplt     2366
      2302: iconst_0
      2303: istore_2
      2304: goto          2354
      2307: aload_0
      2308: getfield      #28                 // Field hg:Ljava/awt/Graphics;
      2311: aload_0
      2312: getfield      #11                 // Field item:[[Ljava/lang/String;
      2315: iload_1
      2316: aaload
      2317: iload_2
      2318: aaload
      2319: aload_0
      2320: getfield      #3                  // Field x:[I
      2323: iload_1
      2324: iaload
      2325: bipush        6
      2327: iadd
      2328: aload_0
      2329: getfield      #4                  // Field y:[I
      2332: iload_1
      2333: iaload
      2334: bipush        6
      2336: iadd
      2337: bipush        18
      2339: iadd
      2340: iload_2
      2341: bipush        14
      2343: imul
      2344: iadd
      2345: bipush        12
      2347: iadd
      2348: invokevirtual #51                 // Method java/awt/Graphics.drawString:(Ljava/lang/String;II)V
      2351: iinc          2, 1
      2354: iload_2
      2355: aload_0
      2356: getfield      #7                  // Field item_kazu:[I
      2359: iload_1
      2360: iaload
      2361: iconst_1
      2362: isub
      2363: if_icmple     2307
      2366: iload_1
      2367: aload_0
      2368: getfield      #17                 // Field aw:I
      2371: if_icmpne     2438
      2374: aload_0
      2375: getfield      #33                 // Field c_fc:I
      2378: iconst_3
      2379: if_icmpgt     6094
      2382: aload_0
      2383: getfield      #21                 // Field gg:LGameGraphics;
      2386: aload_0
      2387: getfield      #3                  // Field x:[I
      2390: iload_1
      2391: iaload
      2392: aload_0
      2393: getfield      #5                  // Field width:[I
      2396: iload_1
      2397: iaload
      2398: bipush        14
      2400: isub
      2401: iconst_2
      2402: idiv
      2403: iadd
      2404: aload_0
      2405: getfield      #4                  // Field y:[I
      2408: iload_1
      2409: iaload
      2410: bipush        6
      2412: iadd
      2413: bipush        18
      2415: iadd
      2416: aload_0
      2417: getfield      #7                  // Field item_kazu:[I
      2420: iload_1
      2421: iaload
      2422: bipush        14
      2424: imul
      2425: iadd
      2426: iconst_2
      2427: iadd
      2428: sipush        201
      2431: iconst_0
      2432: invokevirtual #67                 // Method GameGraphics.drawPT:(IIII)V
      2435: goto          6094
      2438: aload_0
      2439: getfield      #21                 // Field gg:LGameGraphics;
      2442: aload_0
      2443: getfield      #3                  // Field x:[I
      2446: iload_1
      2447: iaload
      2448: aload_0
      2449: getfield      #5                  // Field width:[I
      2452: iload_1
      2453: iaload
      2454: bipush        14
      2456: isub
      2457: iconst_2
      2458: idiv
      2459: iadd
      2460: aload_0
      2461: getfield      #4                  // Field y:[I
      2464: iload_1
      2465: iaload
      2466: bipush        6
      2468: iadd
      2469: bipush        18
      2471: iadd
      2472: aload_0
      2473: getfield      #7                  // Field item_kazu:[I
      2476: iload_1
      2477: iaload
      2478: bipush        14
      2480: imul
      2481: iadd
      2482: iconst_2
      2483: iadd
      2484: sipush        201
      2487: iconst_0
      2488: invokevirtual #67                 // Method GameGraphics.drawPT:(IIII)V
      2491: goto          6094
      2494: aload_0
      2495: getfield      #13                 // Field item_int:[[I
      2498: iload_1
      2499: aaload
      2500: iconst_0
      2501: iaload
      2502: bipush        100
      2504: if_icmpne     2520
      2507: aload_0
      2508: getfield      #13                 // Field item_int:[[I
      2511: iload_1
      2512: aaload
      2513: iconst_0
      2514: bipush        55
      2516: iastore
      2517: goto          6094
      2520: aload_0
      2521: aload_0
      2522: getfield      #3                  // Field x:[I
      2525: iload_1
      2526: iaload
      2527: aload_0
      2528: getfield      #4                  // Field y:[I
      2531: iload_1
      2532: iaload
      2533: aload_0
      2534: getfield      #5                  // Field width:[I
      2537: iload_1
      2538: iaload
      2539: bipush        26
      2541: invokevirtual #48                 // Method drawWindowbox:(IIII)V
      2544: aload_0
      2545: getfield      #28                 // Field hg:Ljava/awt/Graphics;
      2548: getstatic     #49                 // Field java/awt/Color.white:Ljava/awt/Color;
      2551: invokevirtual #50                 // Method java/awt/Graphics.setColor:(Ljava/awt/Color;)V
      2554: aload_0
      2555: getfield      #28                 // Field hg:Ljava/awt/Graphics;
      2558: aload_0
      2559: getfield      #11                 // Field item:[[Ljava/lang/String;
      2562: iload_1
      2563: aaload
      2564: iconst_0
      2565: aaload
      2566: aload_0
      2567: getfield      #3                  // Field x:[I
      2570: iload_1
      2571: iaload
      2572: bipush        6
      2574: iadd
      2575: aload_0
      2576: getfield      #4                  // Field y:[I
      2579: iload_1
      2580: iaload
      2581: bipush        6
      2583: iadd
      2584: bipush        12
      2586: iadd
      2587: invokevirtual #51                 // Method java/awt/Graphics.drawString:(Ljava/lang/String;II)V
      2590: aload_0
      2591: getfield      #13                 // Field item_int:[[I
      2594: iload_1
      2595: aaload
      2596: iconst_0
      2597: dup2
      2598: iaload
      2599: iconst_1
      2600: isub
      2601: iastore
      2602: aload_0
      2603: getfield      #13                 // Field item_int:[[I
      2606: iload_1
      2607: aaload
      2608: iconst_0
      2609: iaload
      2610: ifgt          6094
      2613: aload_0
      2614: iload_1
      2615: invokevirtual #69                 // Method off:(I)V
      2618: goto          6094
      2621: aload_0
      2622: getfield      #13                 // Field item_int:[[I
      2625: iload_1
      2626: aaload
      2627: iconst_0
      2628: iaload
      2629: sipush        200
      2632: if_icmpne     2760
      2635: aload_0
      2636: aload_0
      2637: getfield      #3                  // Field x:[I
      2640: iload_1
      2641: iaload
      2642: aload_0
      2643: getfield      #4                  // Field y:[I
      2646: iload_1
      2647: iaload
      2648: aload_0
      2649: getfield      #5                  // Field width:[I
      2652: iload_1
      2653: iaload
      2654: bipush        44
      2656: invokevirtual #48                 // Method drawWindowbox:(IIII)V
      2659: aload_0
      2660: getfield      #28                 // Field hg:Ljava/awt/Graphics;
      2663: aload_0
      2664: getfield      #15                 // Field item_color:[Ljava/awt/Color;
      2667: iload_1
      2668: aaload
      2669: invokevirtual #50                 // Method java/awt/Graphics.setColor:(Ljava/awt/Color;)V
      2672: aload_0
      2673: getfield      #28                 // Field hg:Ljava/awt/Graphics;
      2676: aload_0
      2677: getfield      #11                 // Field item:[[Ljava/lang/String;
      2680: iload_1
      2681: aaload
      2682: iconst_0
      2683: aaload
      2684: aload_0
      2685: getfield      #3                  // Field x:[I
      2688: iload_1
      2689: iaload
      2690: bipush        6
      2692: iadd
      2693: aload_0
      2694: getfield      #4                  // Field y:[I
      2697: iload_1
      2698: iaload
      2699: bipush        6
      2701: iadd
      2702: bipush        12
      2704: iadd
      2705: invokevirtual #51                 // Method java/awt/Graphics.drawString:(Ljava/lang/String;II)V
      2708: aload_0
      2709: getfield      #28                 // Field hg:Ljava/awt/Graphics;
      2712: getstatic     #49                 // Field java/awt/Color.white:Ljava/awt/Color;
      2715: invokevirtual #50                 // Method java/awt/Graphics.setColor:(Ljava/awt/Color;)V
      2718: aload_0
      2719: getfield      #28                 // Field hg:Ljava/awt/Graphics;
      2722: aload_0
      2723: getfield      #11                 // Field item:[[Ljava/lang/String;
      2726: iload_1
      2727: aaload
      2728: iconst_1
      2729: aaload
      2730: aload_0
      2731: getfield      #3                  // Field x:[I
      2734: iload_1
      2735: iaload
      2736: bipush        6
      2738: iadd
      2739: aload_0
      2740: getfield      #4                  // Field y:[I
      2743: iload_1
      2744: iaload
      2745: bipush        6
      2747: iadd
      2748: bipush        18
      2750: iadd
      2751: bipush        12
      2753: iadd
      2754: invokevirtual #51                 // Method java/awt/Graphics.drawString:(Ljava/lang/String;II)V
      2757: goto          6094
      2760: aload_0
      2761: getfield      #13                 // Field item_int:[[I
      2764: iload_1
      2765: aaload
      2766: iconst_0
      2767: iaload
      2768: bipush        100
      2770: if_icmpne     2786
      2773: aload_0
      2774: getfield      #13                 // Field item_int:[[I
      2777: iload_1
      2778: aaload
      2779: iconst_0
      2780: bipush        55
      2782: iastore
      2783: goto          6094
      2786: aload_0
      2787: aload_0
      2788: getfield      #3                  // Field x:[I
      2791: iload_1
      2792: iaload
      2793: aload_0
      2794: getfield      #4                  // Field y:[I
      2797: iload_1
      2798: iaload
      2799: aload_0
      2800: getfield      #5                  // Field width:[I
      2803: iload_1
      2804: iaload
      2805: bipush        44
      2807: invokevirtual #48                 // Method drawWindowbox:(IIII)V
      2810: aload_0
      2811: getfield      #28                 // Field hg:Ljava/awt/Graphics;
      2814: aload_0
      2815: getfield      #15                 // Field item_color:[Ljava/awt/Color;
      2818: iload_1
      2819: aaload
      2820: invokevirtual #50                 // Method java/awt/Graphics.setColor:(Ljava/awt/Color;)V
      2823: aload_0
      2824: getfield      #28                 // Field hg:Ljava/awt/Graphics;
      2827: aload_0
      2828: getfield      #11                 // Field item:[[Ljava/lang/String;
      2831: iload_1
      2832: aaload
      2833: iconst_0
      2834: aaload
      2835: aload_0
      2836: getfield      #3                  // Field x:[I
      2839: iload_1
      2840: iaload
      2841: bipush        6
      2843: iadd
      2844: aload_0
      2845: getfield      #4                  // Field y:[I
      2848: iload_1
      2849: iaload
      2850: bipush        6
      2852: iadd
      2853: bipush        12
      2855: iadd
      2856: invokevirtual #51                 // Method java/awt/Graphics.drawString:(Ljava/lang/String;II)V
      2859: aload_0
      2860: getfield      #28                 // Field hg:Ljava/awt/Graphics;
      2863: getstatic     #49                 // Field java/awt/Color.white:Ljava/awt/Color;
      2866: invokevirtual #50                 // Method java/awt/Graphics.setColor:(Ljava/awt/Color;)V
      2869: aload_0
      2870: getfield      #28                 // Field hg:Ljava/awt/Graphics;
      2873: aload_0
      2874: getfield      #11                 // Field item:[[Ljava/lang/String;
      2877: iload_1
      2878: aaload
      2879: iconst_1
      2880: aaload
      2881: aload_0
      2882: getfield      #3                  // Field x:[I
      2885: iload_1
      2886: iaload
      2887: bipush        6
      2889: iadd
      2890: aload_0
      2891: getfield      #4                  // Field y:[I
      2894: iload_1
      2895: iaload
      2896: bipush        6
      2898: iadd
      2899: bipush        18
      2901: iadd
      2902: bipush        12
      2904: iadd
      2905: invokevirtual #51                 // Method java/awt/Graphics.drawString:(Ljava/lang/String;II)V
      2908: aload_0
      2909: getfield      #13                 // Field item_int:[[I
      2912: iload_1
      2913: aaload
      2914: iconst_0
      2915: dup2
      2916: iaload
      2917: iconst_1
      2918: isub
      2919: iastore
      2920: aload_0
      2921: getfield      #13                 // Field item_int:[[I
      2924: iload_1
      2925: aaload
      2926: iconst_0
      2927: iaload
      2928: ifgt          6094
      2931: aload_0
      2932: iload_1
      2933: invokevirtual #69                 // Method off:(I)V
      2936: goto          6094
      2939: aload_0
      2940: aload_0
      2941: getfield      #3                  // Field x:[I
      2944: iload_1
      2945: iaload
      2946: aload_0
      2947: getfield      #4                  // Field y:[I
      2950: iload_1
      2951: iaload
      2952: aload_0
      2953: getfield      #5                  // Field width:[I
      2956: iload_1
      2957: iaload
      2958: sipush        128
      2961: invokevirtual #48                 // Method drawWindowbox:(IIII)V
      2964: aload_0
      2965: getfield      #28                 // Field hg:Ljava/awt/Graphics;
      2968: getstatic     #70                 // Field java/awt/Color.yellow:Ljava/awt/Color;
      2971: invokevirtual #50                 // Method java/awt/Graphics.setColor:(Ljava/awt/Color;)V
      2974: aload_0
      2975: getfield      #28                 // Field hg:Ljava/awt/Graphics;
      2978: new           #58                 // class java/lang/StringBuffer
      2981: dup
      2982: invokespecial #59                 // Method java/lang/StringBuffer."<init>":()V
      2985: aload_0
      2986: getfield      #23                 // Field name_crys:Ljava/lang/String;
      2989: invokevirtual #61                 // Method java/lang/StringBuffer.append:(Ljava/lang/String;)Ljava/lang/StringBuffer;
      2992: ldc           #71                 // String のステータス
      2994: invokevirtual #61                 // Method java/lang/StringBuffer.append:(Ljava/lang/String;)Ljava/lang/StringBuffer;
      2997: invokevirtual #64                 // Method java/lang/StringBuffer.toString:()Ljava/lang/String;
      3000: aload_0
      3001: getfield      #3                  // Field x:[I
      3004: iload_1
      3005: iaload
      3006: bipush        6
      3008: iadd
      3009: aload_0
      3010: getfield      #4                  // Field y:[I
      3013: iload_1
      3014: iaload
      3015: bipush        6
      3017: iadd
      3018: bipush        12
      3020: iadd
      3021: invokevirtual #51                 // Method java/awt/Graphics.drawString:(Ljava/lang/String;II)V
      3024: aload_0
      3025: getfield      #28                 // Field hg:Ljava/awt/Graphics;
      3028: getstatic     #49                 // Field java/awt/Color.white:Ljava/awt/Color;
      3031: invokevirtual #50                 // Method java/awt/Graphics.setColor:(Ljava/awt/Color;)V
      3034: aload_0
      3035: getfield      #28                 // Field hg:Ljava/awt/Graphics;
      3038: new           #58                 // class java/lang/StringBuffer
      3041: dup
      3042: invokespecial #59                 // Method java/lang/StringBuffer."<init>":()V
      3045: ldc           #60                 // String HP
      3047: invokevirtual #61                 // Method java/lang/StringBuffer.append:(Ljava/lang/String;)Ljava/lang/StringBuffer;
      3050: aload_0
      3051: getfield      #13                 // Field item_int:[[I
      3054: bipush        14
      3056: aaload
      3057: iconst_0
      3058: iaload
      3059: invokevirtual #62                 // Method java/lang/StringBuffer.append:(I)Ljava/lang/StringBuffer;
      3062: ldc           #63                 // String  /
      3064: invokevirtual #61                 // Method java/lang/StringBuffer.append:(Ljava/lang/String;)Ljava/lang/StringBuffer;
      3067: aload_0
      3068: getfield      #13                 // Field item_int:[[I
      3071: bipush        14
      3073: aaload
      3074: iconst_1
      3075: iaload
      3076: invokevirtual #62                 // Method java/lang/StringBuffer.append:(I)Ljava/lang/StringBuffer;
      3079: invokevirtual #64                 // Method java/lang/StringBuffer.toString:()Ljava/lang/String;
      3082: aload_0
      3083: getfield      #3                  // Field x:[I
      3086: iload_1
      3087: iaload
      3088: bipush        6
      3090: iadd
      3091: aload_0
      3092: getfield      #4                  // Field y:[I
      3095: iload_1
      3096: iaload
      3097: bipush        6
      3099: iadd
      3100: bipush        18
      3102: iadd
      3103: iconst_0
      3104: iadd
      3105: bipush        12
      3107: iadd
      3108: invokevirtual #51                 // Method java/awt/Graphics.drawString:(Ljava/lang/String;II)V
      3111: aload_0
      3112: getfield      #28                 // Field hg:Ljava/awt/Graphics;
      3115: ldc           #72                 // String おこづかい
      3117: aload_0
      3118: getfield      #3                  // Field x:[I
      3121: iload_1
      3122: iaload
      3123: bipush        6
      3125: iadd
      3126: aload_0
      3127: getfield      #4                  // Field y:[I
      3130: iload_1
      3131: iaload
      3132: bipush        6
      3134: iadd
      3135: bipush        18
      3137: iadd
      3138: bipush        28
      3140: iadd
      3141: bipush        12
      3143: iadd
      3144: invokevirtual #51                 // Method java/awt/Graphics.drawString:(Ljava/lang/String;II)V
      3147: aload_0
      3148: getfield      #28                 // Field hg:Ljava/awt/Graphics;
      3151: new           #58                 // class java/lang/StringBuffer
      3154: dup
      3155: invokespecial #59                 // Method java/lang/StringBuffer."<init>":()V
      3158: ldc           #39                 // String
      3160: invokevirtual #61                 // Method java/lang/StringBuffer.append:(Ljava/lang/String;)Ljava/lang/StringBuffer;
      3163: aload_0
      3164: getfield      #13                 // Field item_int:[[I
      3167: bipush        14
      3169: aaload
      3170: iconst_2
      3171: iaload
      3172: invokevirtual #62                 // Method java/lang/StringBuffer.append:(I)Ljava/lang/StringBuffer;
      3175: ldc           #73                 // String 円
      3177: invokevirtual #61                 // Method java/lang/StringBuffer.append:(Ljava/lang/String;)Ljava/lang/StringBuffer;
      3180: invokevirtual #64                 // Method java/lang/StringBuffer.toString:()Ljava/lang/String;
      3183: aload_0
      3184: getfield      #3                  // Field x:[I
      3187: iload_1
      3188: iaload
      3189: bipush        6
      3191: iadd
      3192: bipush        72
      3194: iadd
      3195: aload_0
      3196: getfield      #4                  // Field y:[I
      3199: iload_1
      3200: iaload
      3201: bipush        6
      3203: iadd
      3204: bipush        18
      3206: iadd
      3207: bipush        42
      3209: iadd
      3210: bipush        12
      3212: iadd
      3213: invokevirtual #51                 // Method java/awt/Graphics.drawString:(Ljava/lang/String;II)V
      3216: aload_0
      3217: getfield      #28                 // Field hg:Ljava/awt/Graphics;
      3220: ldc           #74                 // String 得点
      3222: aload_0
      3223: getfield      #3                  // Field x:[I
      3226: iload_1
      3227: iaload
      3228: bipush        6
      3230: iadd
      3231: aload_0
      3232: getfield      #4                  // Field y:[I
      3235: iload_1
      3236: iaload
      3237: bipush        6
      3239: iadd
      3240: bipush        18
      3242: iadd
      3243: bipush        56
      3245: iadd
      3246: bipush        12
      3248: iadd
      3249: invokevirtual #51                 // Method java/awt/Graphics.drawString:(Ljava/lang/String;II)V
      3252: aload_0
      3253: getfield      #28                 // Field hg:Ljava/awt/Graphics;
      3256: new           #58                 // class java/lang/StringBuffer
      3259: dup
      3260: invokespecial #59                 // Method java/lang/StringBuffer."<init>":()V
      3263: ldc           #39                 // String
      3265: invokevirtual #61                 // Method java/lang/StringBuffer.append:(Ljava/lang/String;)Ljava/lang/StringBuffer;
      3268: aload_0
      3269: getfield      #13                 // Field item_int:[[I
      3272: bipush        14
      3274: aaload
      3275: iconst_3
      3276: iaload
      3277: invokevirtual #62                 // Method java/lang/StringBuffer.append:(I)Ljava/lang/StringBuffer;
      3280: ldc           #75                 // String 点
      3282: invokevirtual #61                 // Method java/lang/StringBuffer.append:(Ljava/lang/String;)Ljava/lang/StringBuffer;
      3285: invokevirtual #64                 // Method java/lang/StringBuffer.toString:()Ljava/lang/String;
      3288: aload_0
      3289: getfield      #3                  // Field x:[I
      3292: iload_1
      3293: iaload
      3294: bipush        6
      3296: iadd
      3297: bipush        72
      3299: iadd
      3300: aload_0
      3301: getfield      #4                  // Field y:[I
      3304: iload_1
      3305: iaload
      3306: bipush        6
      3308: iadd
      3309: bipush        18
      3311: iadd
      3312: bipush        70
      3314: iadd
      3315: bipush        12
      3317: iadd
      3318: invokevirtual #51                 // Method java/awt/Graphics.drawString:(Ljava/lang/String;II)V
      3321: aload_0
      3322: getfield      #33                 // Field c_fc:I
      3325: iconst_3
      3326: if_icmpgt     6094
      3329: aload_0
      3330: getfield      #21                 // Field gg:LGameGraphics;
      3333: aload_0
      3334: getfield      #3                  // Field x:[I
      3337: iload_1
      3338: iaload
      3339: aload_0
      3340: getfield      #5                  // Field width:[I
      3343: iload_1
      3344: iaload
      3345: bipush        14
      3347: isub
      3348: iconst_2
      3349: idiv
      3350: iadd
      3351: aload_0
      3352: getfield      #4                  // Field y:[I
      3355: iload_1
      3356: iaload
      3357: bipush        6
      3359: iadd
      3360: bipush        18
      3362: iadd
      3363: bipush        84
      3365: iadd
      3366: iconst_2
      3367: iadd
      3368: bipush        71
      3370: iconst_0
      3371: invokevirtual #67                 // Method GameGraphics.drawPT:(IIII)V
      3374: goto          6094
      3377: aload_0
      3378: aload_0
      3379: getfield      #3                  // Field x:[I
      3382: iload_1
      3383: iaload
      3384: aload_0
      3385: getfield      #4                  // Field y:[I
      3388: iload_1
      3389: iaload
      3390: aload_0
      3391: getfield      #5                  // Field width:[I
      3394: iload_1
      3395: iaload
      3396: bipush        116
      3398: invokevirtual #48                 // Method drawWindowbox:(IIII)V
      3401: aload_0
      3402: getfield      #28                 // Field hg:Ljava/awt/Graphics;
      3405: new           #14                 // class java/awt/Color
      3408: dup
      3409: bipush        96
      3411: bipush        96
      3413: bipush        96
      3415: invokespecial #76                 // Method java/awt/Color."<init>":(III)V
      3418: invokevirtual #50                 // Method java/awt/Graphics.setColor:(Ljava/awt/Color;)V
      3421: aload_0
      3422: getfield      #28                 // Field hg:Ljava/awt/Graphics;
      3425: aload_0
      3426: getfield      #3                  // Field x:[I
      3429: iload_1
      3430: iaload
      3431: bipush        12
      3433: iadd
      3434: aload_0
      3435: getfield      #4                  // Field y:[I
      3438: iload_1
      3439: iaload
      3440: bipush        12
      3442: iadd
      3443: aload_0
      3444: getfield      #5                  // Field width:[I
      3447: iload_1
      3448: iaload
      3449: bipush        24
      3451: isub
      3452: bipush        48
      3454: invokevirtual #53                 // Method java/awt/Graphics.fillRect:(IIII)V
      3457: aload_0
      3458: getfield      #21                 // Field gg:LGameGraphics;
      3461: aload_0
      3462: getfield      #3                  // Field x:[I
      3465: iload_1
      3466: iaload
      3467: bipush        12
      3469: iadd
      3470: aload_0
      3471: getfield      #5                  // Field width:[I
      3474: iload_1
      3475: iaload
      3476: bipush        24
      3478: isub
      3479: bipush        32
      3481: isub
      3482: iconst_2
      3483: idiv
      3484: iadd
      3485: aload_0
      3486: getfield      #4                  // Field y:[I
      3489: iload_1
      3490: iaload
      3491: bipush        12
      3493: iadd
      3494: bipush        8
      3496: iadd
      3497: aload_0
      3498: getfield      #13                 // Field item_int:[[I
      3501: iload_1
      3502: aaload
      3503: iconst_2
      3504: iaload
      3505: iconst_0
      3506: invokevirtual #67                 // Method GameGraphics.drawPT:(IIII)V
      3509: aload_0
      3510: getfield      #28                 // Field hg:Ljava/awt/Graphics;
      3513: getstatic     #55                 // Field java/awt/Color.cyan:Ljava/awt/Color;
      3516: invokevirtual #50                 // Method java/awt/Graphics.setColor:(Ljava/awt/Color;)V
      3519: aload_0
      3520: getfield      #28                 // Field hg:Ljava/awt/Graphics;
      3523: aload_0
      3524: getfield      #11                 // Field item:[[Ljava/lang/String;
      3527: iload_1
      3528: aaload
      3529: iconst_0
      3530: aaload
      3531: aload_0
      3532: getfield      #3                  // Field x:[I
      3535: iload_1
      3536: iaload
      3537: bipush        12
      3539: iadd
      3540: aload_0
      3541: getfield      #4                  // Field y:[I
      3544: iload_1
      3545: iaload
      3546: bipush        64
      3548: iadd
      3549: bipush        12
      3551: iadd
      3552: invokevirtual #51                 // Method java/awt/Graphics.drawString:(Ljava/lang/String;II)V
      3555: aload_0
      3556: getfield      #28                 // Field hg:Ljava/awt/Graphics;
      3559: getstatic     #49                 // Field java/awt/Color.white:Ljava/awt/Color;
      3562: invokevirtual #50                 // Method java/awt/Graphics.setColor:(Ljava/awt/Color;)V
      3565: aload_0
      3566: getfield      #28                 // Field hg:Ljava/awt/Graphics;
      3569: ldc           #77                 // String これからも、よろしくね！
      3571: aload_0
      3572: getfield      #3                  // Field x:[I
      3575: iload_1
      3576: iaload
      3577: bipush        12
      3579: iadd
      3580: aload_0
      3581: getfield      #4                  // Field y:[I
      3584: iload_1
      3585: iaload
      3586: bipush        68
      3588: iadd
      3589: bipush        14
      3591: iadd
      3592: bipush        12
      3594: iadd
      3595: invokevirtual #51                 // Method java/awt/Graphics.drawString:(Ljava/lang/String;II)V
      3598: aload_0
      3599: getfield      #33                 // Field c_fc:I
      3602: iconst_3
      3603: if_icmpgt     6094
      3606: aload_0
      3607: getfield      #21                 // Field gg:LGameGraphics;
      3610: aload_0
      3611: getfield      #3                  // Field x:[I
      3614: iload_1
      3615: iaload
      3616: aload_0
      3617: getfield      #5                  // Field width:[I
      3620: iload_1
      3621: iaload
      3622: bipush        14
      3624: isub
      3625: iconst_2
      3626: idiv
      3627: iadd
      3628: aload_0
      3629: getfield      #4                  // Field y:[I
      3632: iload_1
      3633: iaload
      3634: bipush        68
      3636: iadd
      3637: bipush        28
      3639: iadd
      3640: iconst_2
      3641: iadd
      3642: bipush        71
      3644: iconst_0
      3645: invokevirtual #67                 // Method GameGraphics.drawPT:(IIII)V
      3648: goto          6094
      3651: aload_0
      3652: getfield      #13                 // Field item_int:[[I
      3655: iload_1
      3656: aaload
      3657: iconst_0
      3658: iaload
      3659: bipush        -2
      3661: if_icmpne     3938
      3664: aload_0
      3665: aload_0
      3666: getfield      #3                  // Field x:[I
      3669: iload_1
      3670: iaload
      3671: aload_0
      3672: getfield      #4                  // Field y:[I
      3675: iload_1
      3676: iaload
      3677: aload_0
      3678: getfield      #5                  // Field width:[I
      3681: iload_1
      3682: iaload
      3683: bipush        116
      3685: invokevirtual #48                 // Method drawWindowbox:(IIII)V
      3688: aload_0
      3689: getfield      #28                 // Field hg:Ljava/awt/Graphics;
      3692: new           #14                 // class java/awt/Color
      3695: dup
      3696: bipush        96
      3698: bipush        96
      3700: bipush        96
      3702: invokespecial #76                 // Method java/awt/Color."<init>":(III)V
      3705: invokevirtual #50                 // Method java/awt/Graphics.setColor:(Ljava/awt/Color;)V
      3708: aload_0
      3709: getfield      #28                 // Field hg:Ljava/awt/Graphics;
      3712: aload_0
      3713: getfield      #3                  // Field x:[I
      3716: iload_1
      3717: iaload
      3718: bipush        12
      3720: iadd
      3721: aload_0
      3722: getfield      #4                  // Field y:[I
      3725: iload_1
      3726: iaload
      3727: bipush        12
      3729: iadd
      3730: aload_0
      3731: getfield      #5                  // Field width:[I
      3734: iload_1
      3735: iaload
      3736: bipush        24
      3738: isub
      3739: bipush        48
      3741: invokevirtual #53                 // Method java/awt/Graphics.fillRect:(IIII)V
      3744: aload_0
      3745: getfield      #21                 // Field gg:LGameGraphics;
      3748: aload_0
      3749: getfield      #3                  // Field x:[I
      3752: iload_1
      3753: iaload
      3754: bipush        12
      3756: iadd
      3757: aload_0
      3758: getfield      #5                  // Field width:[I
      3761: iload_1
      3762: iaload
      3763: bipush        24
      3765: isub
      3766: bipush        32
      3768: isub
      3769: iconst_2
      3770: idiv
      3771: iadd
      3772: aload_0
      3773: getfield      #4                  // Field y:[I
      3776: iload_1
      3777: iaload
      3778: bipush        12
      3780: iadd
      3781: bipush        8
      3783: iadd
      3784: aload_0
      3785: getfield      #13                 // Field item_int:[[I
      3788: iload_1
      3789: aaload
      3790: iconst_2
      3791: iaload
      3792: iconst_0
      3793: invokevirtual #67                 // Method GameGraphics.drawPT:(IIII)V
      3796: aload_0
      3797: getfield      #28                 // Field hg:Ljava/awt/Graphics;
      3800: getstatic     #70                 // Field java/awt/Color.yellow:Ljava/awt/Color;
      3803: invokevirtual #50                 // Method java/awt/Graphics.setColor:(Ljava/awt/Color;)V
      3806: aload_0
      3807: getfield      #28                 // Field hg:Ljava/awt/Graphics;
      3810: aload_0
      3811: getfield      #11                 // Field item:[[Ljava/lang/String;
      3814: iload_1
      3815: aaload
      3816: iconst_0
      3817: aaload
      3818: aload_0
      3819: getfield      #3                  // Field x:[I
      3822: iload_1
      3823: iaload
      3824: bipush        12
      3826: iadd
      3827: aload_0
      3828: getfield      #4                  // Field y:[I
      3831: iload_1
      3832: iaload
      3833: bipush        64
      3835: iadd
      3836: bipush        12
      3838: iadd
      3839: invokevirtual #51                 // Method java/awt/Graphics.drawString:(Ljava/lang/String;II)V
      3842: aload_0
      3843: getfield      #28                 // Field hg:Ljava/awt/Graphics;
      3846: getstatic     #49                 // Field java/awt/Color.white:Ljava/awt/Color;
      3849: invokevirtual #50                 // Method java/awt/Graphics.setColor:(Ljava/awt/Color;)V
      3852: aload_0
      3853: getfield      #28                 // Field hg:Ljava/awt/Graphics;
      3856: ldc           #78                 // String 捕獲不可能
      3858: aload_0
      3859: getfield      #3                  // Field x:[I
      3862: iload_1
      3863: iaload
      3864: bipush        12
      3866: iadd
      3867: aload_0
      3868: getfield      #4                  // Field y:[I
      3871: iload_1
      3872: iaload
      3873: bipush        68
      3875: iadd
      3876: bipush        14
      3878: iadd
      3879: bipush        12
      3881: iadd
      3882: invokevirtual #51                 // Method java/awt/Graphics.drawString:(Ljava/lang/String;II)V
      3885: aload_0
      3886: getfield      #33                 // Field c_fc:I
      3889: iconst_3
      3890: if_icmpgt     6094
      3893: aload_0
      3894: getfield      #21                 // Field gg:LGameGraphics;
      3897: aload_0
      3898: getfield      #3                  // Field x:[I
      3901: iload_1
      3902: iaload
      3903: aload_0
      3904: getfield      #5                  // Field width:[I
      3907: iload_1
      3908: iaload
      3909: bipush        14
      3911: isub
      3912: iconst_2
      3913: idiv
      3914: iadd
      3915: aload_0
      3916: getfield      #4                  // Field y:[I
      3919: iload_1
      3920: iaload
      3921: bipush        68
      3923: iadd
      3924: bipush        28
      3926: iadd
      3927: iconst_2
      3928: iadd
      3929: bipush        71
      3931: iconst_0
      3932: invokevirtual #67                 // Method GameGraphics.drawPT:(IIII)V
      3935: goto          6094
      3938: aload_0
      3939: getfield      #13                 // Field item_int:[[I
      3942: iload_1
      3943: aaload
      3944: iconst_0
      3945: iaload
      3946: ifge          4223
      3949: aload_0
      3950: aload_0
      3951: getfield      #3                  // Field x:[I
      3954: iload_1
      3955: iaload
      3956: aload_0
      3957: getfield      #4                  // Field y:[I
      3960: iload_1
      3961: iaload
      3962: aload_0
      3963: getfield      #5                  // Field width:[I
      3966: iload_1
      3967: iaload
      3968: bipush        116
      3970: invokevirtual #48                 // Method drawWindowbox:(IIII)V
      3973: aload_0
      3974: getfield      #28                 // Field hg:Ljava/awt/Graphics;
      3977: new           #14                 // class java/awt/Color
      3980: dup
      3981: bipush        96
      3983: bipush        96
      3985: bipush        96
      3987: invokespecial #76                 // Method java/awt/Color."<init>":(III)V
      3990: invokevirtual #50                 // Method java/awt/Graphics.setColor:(Ljava/awt/Color;)V
      3993: aload_0
      3994: getfield      #28                 // Field hg:Ljava/awt/Graphics;
      3997: aload_0
      3998: getfield      #3                  // Field x:[I
      4001: iload_1
      4002: iaload
      4003: bipush        12
      4005: iadd
      4006: aload_0
      4007: getfield      #4                  // Field y:[I
      4010: iload_1
      4011: iaload
      4012: bipush        12
      4014: iadd
      4015: aload_0
      4016: getfield      #5                  // Field width:[I
      4019: iload_1
      4020: iaload
      4021: bipush        24
      4023: isub
      4024: bipush        48
      4026: invokevirtual #53                 // Method java/awt/Graphics.fillRect:(IIII)V
      4029: aload_0
      4030: getfield      #21                 // Field gg:LGameGraphics;
      4033: aload_0
      4034: getfield      #3                  // Field x:[I
      4037: iload_1
      4038: iaload
      4039: bipush        12
      4041: iadd
      4042: aload_0
      4043: getfield      #5                  // Field width:[I
      4046: iload_1
      4047: iaload
      4048: bipush        24
      4050: isub
      4051: bipush        32
      4053: isub
      4054: iconst_2
      4055: idiv
      4056: iadd
      4057: aload_0
      4058: getfield      #4                  // Field y:[I
      4061: iload_1
      4062: iaload
      4063: bipush        12
      4065: iadd
      4066: bipush        8
      4068: iadd
      4069: aload_0
      4070: getfield      #13                 // Field item_int:[[I
      4073: iload_1
      4074: aaload
      4075: iconst_2
      4076: iaload
      4077: iconst_0
      4078: invokevirtual #67                 // Method GameGraphics.drawPT:(IIII)V
      4081: aload_0
      4082: getfield      #28                 // Field hg:Ljava/awt/Graphics;
      4085: getstatic     #70                 // Field java/awt/Color.yellow:Ljava/awt/Color;
      4088: invokevirtual #50                 // Method java/awt/Graphics.setColor:(Ljava/awt/Color;)V
      4091: aload_0
      4092: getfield      #28                 // Field hg:Ljava/awt/Graphics;
      4095: aload_0
      4096: getfield      #11                 // Field item:[[Ljava/lang/String;
      4099: iload_1
      4100: aaload
      4101: iconst_0
      4102: aaload
      4103: aload_0
      4104: getfield      #3                  // Field x:[I
      4107: iload_1
      4108: iaload
      4109: bipush        12
      4111: iadd
      4112: aload_0
      4113: getfield      #4                  // Field y:[I
      4116: iload_1
      4117: iaload
      4118: bipush        64
      4120: iadd
      4121: bipush        12
      4123: iadd
      4124: invokevirtual #51                 // Method java/awt/Graphics.drawString:(Ljava/lang/String;II)V
      4127: aload_0
      4128: getfield      #28                 // Field hg:Ljava/awt/Graphics;
      4131: getstatic     #49                 // Field java/awt/Color.white:Ljava/awt/Color;
      4134: invokevirtual #50                 // Method java/awt/Graphics.setColor:(Ljava/awt/Color;)V
      4137: aload_0
      4138: getfield      #28                 // Field hg:Ljava/awt/Graphics;
      4141: ldc           #79                 // String 現在調査中
      4143: aload_0
      4144: getfield      #3                  // Field x:[I
      4147: iload_1
      4148: iaload
      4149: bipush        12
      4151: iadd
      4152: aload_0
      4153: getfield      #4                  // Field y:[I
      4156: iload_1
      4157: iaload
      4158: bipush        68
      4160: iadd
      4161: bipush        14
      4163: iadd
      4164: bipush        12
      4166: iadd
      4167: invokevirtual #51                 // Method java/awt/Graphics.drawString:(Ljava/lang/String;II)V
      4170: aload_0
      4171: getfield      #33                 // Field c_fc:I
      4174: iconst_3
      4175: if_icmpgt     6094
      4178: aload_0
      4179: getfield      #21                 // Field gg:LGameGraphics;
      4182: aload_0
      4183: getfield      #3                  // Field x:[I
      4186: iload_1
      4187: iaload
      4188: aload_0
      4189: getfield      #5                  // Field width:[I
      4192: iload_1
      4193: iaload
      4194: bipush        14
      4196: isub
      4197: iconst_2
      4198: idiv
      4199: iadd
      4200: aload_0
      4201: getfield      #4                  // Field y:[I
      4204: iload_1
      4205: iaload
      4206: bipush        68
      4208: iadd
      4209: bipush        28
      4211: iadd
      4212: iconst_2
      4213: iadd
      4214: bipush        71
      4216: iconst_0
      4217: invokevirtual #67                 // Method GameGraphics.drawPT:(IIII)V
      4220: goto          6094
      4223: aload_0
      4224: aload_0
      4225: getfield      #3                  // Field x:[I
      4228: iload_1
      4229: iaload
      4230: aload_0
      4231: getfield      #4                  // Field y:[I
      4234: iload_1
      4235: iaload
      4236: aload_0
      4237: getfield      #5                  // Field width:[I
      4240: iload_1
      4241: iaload
      4242: sipush        158
      4245: invokevirtual #48                 // Method drawWindowbox:(IIII)V
      4248: aload_0
      4249: getfield      #28                 // Field hg:Ljava/awt/Graphics;
      4252: new           #14                 // class java/awt/Color
      4255: dup
      4256: bipush        96
      4258: bipush        96
      4260: bipush        96
      4262: invokespecial #76                 // Method java/awt/Color."<init>":(III)V
      4265: invokevirtual #50                 // Method java/awt/Graphics.setColor:(Ljava/awt/Color;)V
      4268: aload_0
      4269: getfield      #28                 // Field hg:Ljava/awt/Graphics;
      4272: aload_0
      4273: getfield      #3                  // Field x:[I
      4276: iload_1
      4277: iaload
      4278: bipush        12
      4280: iadd
      4281: aload_0
      4282: getfield      #4                  // Field y:[I
      4285: iload_1
      4286: iaload
      4287: bipush        12
      4289: iadd
      4290: aload_0
      4291: getfield      #5                  // Field width:[I
      4294: iload_1
      4295: iaload
      4296: bipush        24
      4298: isub
      4299: bipush        48
      4301: invokevirtual #53                 // Method java/awt/Graphics.fillRect:(IIII)V
      4304: aload_0
      4305: getfield      #21                 // Field gg:LGameGraphics;
      4308: aload_0
      4309: getfield      #3                  // Field x:[I
      4312: iload_1
      4313: iaload
      4314: bipush        12
      4316: iadd
      4317: aload_0
      4318: getfield      #5                  // Field width:[I
      4321: iload_1
      4322: iaload
      4323: bipush        24
      4325: isub
      4326: bipush        32
      4328: isub
      4329: iconst_2
      4330: idiv
      4331: iadd
      4332: aload_0
      4333: getfield      #4                  // Field y:[I
      4336: iload_1
      4337: iaload
      4338: bipush        12
      4340: iadd
      4341: bipush        8
      4343: iadd
      4344: aload_0
      4345: getfield      #13                 // Field item_int:[[I
      4348: iload_1
      4349: aaload
      4350: iconst_2
      4351: iaload
      4352: iconst_0
      4353: invokevirtual #67                 // Method GameGraphics.drawPT:(IIII)V
      4356: aload_0
      4357: getfield      #28                 // Field hg:Ljava/awt/Graphics;
      4360: getstatic     #70                 // Field java/awt/Color.yellow:Ljava/awt/Color;
      4363: invokevirtual #50                 // Method java/awt/Graphics.setColor:(Ljava/awt/Color;)V
      4366: aload_0
      4367: getfield      #28                 // Field hg:Ljava/awt/Graphics;
      4370: aload_0
      4371: getfield      #11                 // Field item:[[Ljava/lang/String;
      4374: iload_1
      4375: aaload
      4376: iconst_0
      4377: aaload
      4378: aload_0
      4379: getfield      #3                  // Field x:[I
      4382: iload_1
      4383: iaload
      4384: bipush        12
      4386: iadd
      4387: aload_0
      4388: getfield      #4                  // Field y:[I
      4391: iload_1
      4392: iaload
      4393: bipush        64
      4395: iadd
      4396: bipush        12
      4398: iadd
      4399: invokevirtual #51                 // Method java/awt/Graphics.drawString:(Ljava/lang/String;II)V
      4402: aload_0
      4403: getfield      #28                 // Field hg:Ljava/awt/Graphics;
      4406: getstatic     #49                 // Field java/awt/Color.white:Ljava/awt/Color;
      4409: invokevirtual #50                 // Method java/awt/Graphics.setColor:(Ljava/awt/Color;)V
      4412: aload_0
      4413: getfield      #28                 // Field hg:Ljava/awt/Graphics;
      4416: ldc           #80                 // String 最大HP
      4418: aload_0
      4419: getfield      #3                  // Field x:[I
      4422: iload_1
      4423: iaload
      4424: bipush        12
      4426: iadd
      4427: aload_0
      4428: getfield      #4                  // Field y:[I
      4431: iload_1
      4432: iaload
      4433: bipush        68
      4435: iadd
      4436: bipush        14
      4438: iadd
      4439: bipush        12
      4441: iadd
      4442: invokevirtual #51                 // Method java/awt/Graphics.drawString:(Ljava/lang/String;II)V
      4445: aload_0
      4446: getfield      #28                 // Field hg:Ljava/awt/Graphics;
      4449: new           #58                 // class java/lang/StringBuffer
      4452: dup
      4453: invokespecial #59                 // Method java/lang/StringBuffer."<init>":()V
      4456: ldc           #39                 // String
      4458: invokevirtual #61                 // Method java/lang/StringBuffer.append:(Ljava/lang/String;)Ljava/lang/StringBuffer;
      4461: aload_0
      4462: getfield      #13                 // Field item_int:[[I
      4465: iload_1
      4466: aaload
      4467: iconst_0
      4468: iaload
      4469: invokevirtual #62                 // Method java/lang/StringBuffer.append:(I)Ljava/lang/StringBuffer;
      4472: invokevirtual #64                 // Method java/lang/StringBuffer.toString:()Ljava/lang/String;
      4475: aload_0
      4476: getfield      #3                  // Field x:[I
      4479: iload_1
      4480: iaload
      4481: bipush        56
      4483: iadd
      4484: aload_0
      4485: getfield      #4                  // Field y:[I
      4488: iload_1
      4489: iaload
      4490: bipush        68
      4492: iadd
      4493: bipush        28
      4495: iadd
      4496: bipush        12
      4498: iadd
      4499: invokevirtual #51                 // Method java/awt/Graphics.drawString:(Ljava/lang/String;II)V
      4502: aload_0
      4503: getfield      #28                 // Field hg:Ljava/awt/Graphics;
      4506: ldc           #81                 // String 最大PP
      4508: aload_0
      4509: getfield      #3                  // Field x:[I
      4512: iload_1
      4513: iaload
      4514: bipush        12
      4516: iadd
      4517: aload_0
      4518: getfield      #4                  // Field y:[I
      4521: iload_1
      4522: iaload
      4523: bipush        68
      4525: iadd
      4526: bipush        42
      4528: iadd
      4529: bipush        12
      4531: iadd
      4532: invokevirtual #51                 // Method java/awt/Graphics.drawString:(Ljava/lang/String;II)V
      4535: aload_0
      4536: getfield      #28                 // Field hg:Ljava/awt/Graphics;
      4539: new           #58                 // class java/lang/StringBuffer
      4542: dup
      4543: invokespecial #59                 // Method java/lang/StringBuffer."<init>":()V
      4546: ldc           #39                 // String
      4548: invokevirtual #61                 // Method java/lang/StringBuffer.append:(Ljava/lang/String;)Ljava/lang/StringBuffer;
      4551: aload_0
      4552: getfield      #13                 // Field item_int:[[I
      4555: iload_1
      4556: aaload
      4557: iconst_1
      4558: iaload
      4559: invokevirtual #62                 // Method java/lang/StringBuffer.append:(I)Ljava/lang/StringBuffer;
      4562: invokevirtual #64                 // Method java/lang/StringBuffer.toString:()Ljava/lang/String;
      4565: aload_0
      4566: getfield      #3                  // Field x:[I
      4569: iload_1
      4570: iaload
      4571: bipush        56
      4573: iadd
      4574: aload_0
      4575: getfield      #4                  // Field y:[I
      4578: iload_1
      4579: iaload
      4580: bipush        68
      4582: iadd
      4583: bipush        56
      4585: iadd
      4586: bipush        12
      4588: iadd
      4589: invokevirtual #51                 // Method java/awt/Graphics.drawString:(Ljava/lang/String;II)V
      4592: aload_0
      4593: getfield      #33                 // Field c_fc:I
      4596: iconst_3
      4597: if_icmpgt     6094
      4600: aload_0
      4601: getfield      #21                 // Field gg:LGameGraphics;
      4604: aload_0
      4605: getfield      #3                  // Field x:[I
      4608: iload_1
      4609: iaload
      4610: aload_0
      4611: getfield      #5                  // Field width:[I
      4614: iload_1
      4615: iaload
      4616: bipush        14
      4618: isub
      4619: iconst_2
      4620: idiv
      4621: iadd
      4622: aload_0
      4623: getfield      #4                  // Field y:[I
      4626: iload_1
      4627: iaload
      4628: bipush        68
      4630: iadd
      4631: bipush        70
      4633: iadd
      4634: iconst_2
      4635: iadd
      4636: bipush        71
      4638: iconst_0
      4639: invokevirtual #67                 // Method GameGraphics.drawPT:(IIII)V
      4642: goto          6094
      4645: aload_0
      4646: getfield      #33                 // Field c_fc:I
      4649: iconst_3
      4650: if_icmple     4660
      4653: aload_0
      4654: getfield      #17                 // Field aw:I
      4657: ifeq          4697
      4660: aload_0
      4661: getfield      #28                 // Field hg:Ljava/awt/Graphics;
      4664: aload_0
      4665: getfield      #25                 // Field hi:[Ljava/awt/Image;
      4668: bipush        72
      4670: aaload
      4671: bipush        12
      4673: bipush        28
      4675: aload_0
      4676: getfield      #6                  // Field selectedIndex:[I
      4679: iload_1
      4680: iaload
      4681: imul
      4682: iadd
      4683: sipush        288
      4686: aload_0
      4687: getfield      #30                 // Field ap:Ljava/applet/Applet;
      4690: invokevirtual #52                 // Method java/awt/Graphics.drawImage:(Ljava/awt/Image;IILjava/awt/image/ImageObserver;)Z
      4693: pop
      4694: goto          6094
      4697: aload_0
      4698: getfield      #28                 // Field hg:Ljava/awt/Graphics;
      4701: aload_0
      4702: getfield      #25                 // Field hi:[Ljava/awt/Image;
      4705: bipush        73
      4707: aaload
      4708: bipush        12
      4710: bipush        28
      4712: aload_0
      4713: getfield      #6                  // Field selectedIndex:[I
      4716: iload_1
      4717: iaload
      4718: imul
      4719: iadd
      4720: sipush        288
      4723: aload_0
      4724: getfield      #30                 // Field ap:Ljava/applet/Applet;
      4727: invokevirtual #52                 // Method java/awt/Graphics.drawImage:(Ljava/awt/Image;IILjava/awt/image/ImageObserver;)Z
      4730: pop
      4731: goto          6094
      4734: aload_0
      4735: aload_0
      4736: getfield      #3                  // Field x:[I
      4739: iload_1
      4740: iaload
      4741: aload_0
      4742: getfield      #4                  // Field y:[I
      4745: iload_1
      4746: iaload
      4747: aload_0
      4748: getfield      #5                  // Field width:[I
      4751: iload_1
      4752: iaload
      4753: bipush        96
      4755: invokevirtual #48                 // Method drawWindowbox:(IIII)V
      4758: aload_0
      4759: getfield      #13                 // Field item_int:[[I
      4762: iload_1
      4763: aaload
      4764: iconst_0
      4765: iaload
      4766: istore_3
      4767: aload_0
      4768: getfield      #3                  // Field x:[I
      4771: iload_1
      4772: iaload
      4773: aload_0
      4774: getfield      #5                  // Field width:[I
      4777: iload_1
      4778: iaload
      4779: bipush        64
      4781: isub
      4782: iconst_2
      4783: idiv
      4784: iadd
      4785: istore        4
      4787: aload_0
      4788: getfield      #4                  // Field y:[I
      4791: iload_1
      4792: iaload
      4793: bipush        16
      4795: iadd
      4796: istore        5
      4798: aload_0
      4799: getfield      #21                 // Field gg:LGameGraphics;
      4802: iload         4
      4804: iload         5
      4806: iload_3
      4807: iconst_0
      4808: invokevirtual #67                 // Method GameGraphics.drawPT:(IIII)V
      4811: aload_0
      4812: getfield      #21                 // Field gg:LGameGraphics;
      4815: iload         4
      4817: bipush        32
      4819: iadd
      4820: iload         5
      4822: iload_3
      4823: iconst_1
      4824: iadd
      4825: iconst_0
      4826: invokevirtual #67                 // Method GameGraphics.drawPT:(IIII)V
      4829: aload_0
      4830: getfield      #21                 // Field gg:LGameGraphics;
      4833: iload         4
      4835: iload         5
      4837: bipush        32
      4839: iadd
      4840: iload_3
      4841: bipush        10
      4843: iadd
      4844: iconst_0
      4845: invokevirtual #67                 // Method GameGraphics.drawPT:(IIII)V
      4848: aload_0
      4849: getfield      #21                 // Field gg:LGameGraphics;
      4852: iload         4
      4854: bipush        32
      4856: iadd
      4857: iload         5
      4859: bipush        32
      4861: iadd
      4862: iload_3
      4863: bipush        11
      4865: iadd
      4866: iconst_0
      4867: invokevirtual #67                 // Method GameGraphics.drawPT:(IIII)V
      4870: goto          6094
      4873: aload_0
      4874: aload_0
      4875: getfield      #3                  // Field x:[I
      4878: iload_1
      4879: iaload
      4880: aload_0
      4881: getfield      #4                  // Field y:[I
      4884: iload_1
      4885: iaload
      4886: aload_0
      4887: getfield      #5                  // Field width:[I
      4890: iload_1
      4891: iaload
      4892: bipush        30
      4894: aload_0
      4895: getfield      #7                  // Field item_kazu:[I
      4898: iload_1
      4899: iaload
      4900: bipush        14
      4902: imul
      4903: iadd
      4904: invokevirtual #48                 // Method drawWindowbox:(IIII)V
      4907: aload_0
      4908: getfield      #28                 // Field hg:Ljava/awt/Graphics;
      4911: getstatic     #70                 // Field java/awt/Color.yellow:Ljava/awt/Color;
      4914: invokevirtual #50                 // Method java/awt/Graphics.setColor:(Ljava/awt/Color;)V
      4917: aload_0
      4918: getfield      #28                 // Field hg:Ljava/awt/Graphics;
      4921: ldc           #82                 // String モンスターずかん
      4923: aload_0
      4924: getfield      #3                  // Field x:[I
      4927: iload_1
      4928: iaload
      4929: bipush        6
      4931: iadd
      4932: aload_0
      4933: getfield      #4                  // Field y:[I
      4936: iload_1
      4937: iaload
      4938: bipush        6
      4940: iadd
      4941: bipush        12
      4943: iadd
      4944: invokevirtual #51                 // Method java/awt/Graphics.drawString:(Ljava/lang/String;II)V
      4947: aload_0
      4948: getfield      #28                 // Field hg:Ljava/awt/Graphics;
      4951: getstatic     #49                 // Field java/awt/Color.white:Ljava/awt/Color;
      4954: invokevirtual #50                 // Method java/awt/Graphics.setColor:(Ljava/awt/Color;)V
      4957: aload_0
      4958: getfield      #28                 // Field hg:Ljava/awt/Graphics;
      4961: new           #58                 // class java/lang/StringBuffer
      4964: dup
      4965: invokespecial #59                 // Method java/lang/StringBuffer."<init>":()V
      4968: ldc           #83                 // String 見つけた数
      4970: invokevirtual #61                 // Method java/lang/StringBuffer.append:(Ljava/lang/String;)Ljava/lang/StringBuffer;
      4973: aload_0
      4974: getfield      #13                 // Field item_int:[[I
      4977: iload_1
      4978: aaload
      4979: iconst_0
      4980: iaload
      4981: invokevirtual #62                 // Method java/lang/StringBuffer.append:(I)Ljava/lang/StringBuffer;
      4984: invokevirtual #64                 // Method java/lang/StringBuffer.toString:()Ljava/lang/String;
      4987: aload_0
      4988: getfield      #3                  // Field x:[I
      4991: iload_1
      4992: iaload
      4993: bipush        6
      4995: iadd
      4996: aload_0
      4997: getfield      #4                  // Field y:[I
      5000: iload_1
      5001: iaload
      5002: bipush        6
      5004: iadd
      5005: bipush        18
      5007: iadd
      5008: iconst_0
      5009: iadd
      5010: bipush        12
      5012: iadd
      5013: invokevirtual #51                 // Method java/awt/Graphics.drawString:(Ljava/lang/String;II)V
      5016: aload_0
      5017: getfield      #28                 // Field hg:Ljava/awt/Graphics;
      5020: new           #58                 // class java/lang/StringBuffer
      5023: dup
      5024: invokespecial #59                 // Method java/lang/StringBuffer."<init>":()V
      5027: ldc           #84                 // String 捕まえた数
      5029: invokevirtual #61                 // Method java/lang/StringBuffer.append:(Ljava/lang/String;)Ljava/lang/StringBuffer;
      5032: aload_0
      5033: getfield      #13                 // Field item_int:[[I
      5036: iload_1
      5037: aaload
      5038: iconst_1
      5039: iaload
      5040: invokevirtual #62                 // Method java/lang/StringBuffer.append:(I)Ljava/lang/StringBuffer;
      5043: invokevirtual #64                 // Method java/lang/StringBuffer.toString:()Ljava/lang/String;
      5046: aload_0
      5047: getfield      #3                  // Field x:[I
      5050: iload_1
      5051: iaload
      5052: bipush        6
      5054: iadd
      5055: aload_0
      5056: getfield      #4                  // Field y:[I
      5059: iload_1
      5060: iaload
      5061: bipush        6
      5063: iadd
      5064: bipush        18
      5066: iadd
      5067: bipush        14
      5069: iadd
      5070: bipush        12
      5072: iadd
      5073: invokevirtual #51                 // Method java/awt/Graphics.drawString:(Ljava/lang/String;II)V
      5076: goto          6094
      5079: aload_0
      5080: aload_0
      5081: getfield      #3                  // Field x:[I
      5084: iload_1
      5085: iaload
      5086: aload_0
      5087: getfield      #4                  // Field y:[I
      5090: iload_1
      5091: iaload
      5092: aload_0
      5093: getfield      #5                  // Field width:[I
      5096: iload_1
      5097: iaload
      5098: bipush        30
      5100: aload_0
      5101: getfield      #7                  // Field item_kazu:[I
      5104: iload_1
      5105: iaload
      5106: bipush        14
      5108: imul
      5109: iadd
      5110: bipush        18
      5112: iadd
      5113: invokevirtual #48                 // Method drawWindowbox:(IIII)V
      5116: aload_0
      5117: getfield      #28                 // Field hg:Ljava/awt/Graphics;
      5120: getstatic     #55                 // Field java/awt/Color.cyan:Ljava/awt/Color;
      5123: invokevirtual #50                 // Method java/awt/Graphics.setColor:(Ljava/awt/Color;)V
      5126: aload_0
      5127: getfield      #28                 // Field hg:Ljava/awt/Graphics;
      5130: aload_0
      5131: getfield      #11                 // Field item:[[Ljava/lang/String;
      5134: iload_1
      5135: aaload
      5136: bipush        15
      5138: aaload
      5139: aload_0
      5140: getfield      #3                  // Field x:[I
      5143: iload_1
      5144: iaload
      5145: bipush        24
      5147: iadd
      5148: aload_0
      5149: getfield      #4                  // Field y:[I
      5152: iload_1
      5153: iaload
      5154: bipush        6
      5156: iadd
      5157: bipush        12
      5159: iadd
      5160: invokevirtual #51                 // Method java/awt/Graphics.drawString:(Ljava/lang/String;II)V
      5163: aload_0
      5164: getfield      #28                 // Field hg:Ljava/awt/Graphics;
      5167: getstatic     #49                 // Field java/awt/Color.white:Ljava/awt/Color;
      5170: invokevirtual #50                 // Method java/awt/Graphics.setColor:(Ljava/awt/Color;)V
      5173: aload_0
      5174: getfield      #28                 // Field hg:Ljava/awt/Graphics;
      5177: aload_0
      5178: getfield      #9                  // Field message:[Ljava/lang/String;
      5181: iload_1
      5182: aaload
      5183: aload_0
      5184: getfield      #3                  // Field x:[I
      5187: iload_1
      5188: iaload
      5189: bipush        24
      5191: iadd
      5192: aload_0
      5193: getfield      #4                  // Field y:[I
      5196: iload_1
      5197: iaload
      5198: bipush        6
      5200: iadd
      5201: bipush        12
      5203: iadd
      5204: bipush        18
      5206: iadd
      5207: invokevirtual #51                 // Method java/awt/Graphics.drawString:(Ljava/lang/String;II)V
      5210: aload_0
      5211: getfield      #7                  // Field item_kazu:[I
      5214: iload_1
      5215: iaload
      5216: iconst_1
      5217: if_icmplt     5287
      5220: iconst_0
      5221: istore_2
      5222: goto          5275
      5225: aload_0
      5226: getfield      #28                 // Field hg:Ljava/awt/Graphics;
      5229: aload_0
      5230: getfield      #11                 // Field item:[[Ljava/lang/String;
      5233: iload_1
      5234: aaload
      5235: iload_2
      5236: aaload
      5237: aload_0
      5238: getfield      #3                  // Field x:[I
      5241: iload_1
      5242: iaload
      5243: bipush        24
      5245: iadd
      5246: aload_0
      5247: getfield      #4                  // Field y:[I
      5250: iload_1
      5251: iaload
      5252: bipush        6
      5254: iadd
      5255: bipush        18
      5257: iadd
      5258: iload_2
      5259: bipush        14
      5261: imul
      5262: iadd
      5263: bipush        12
      5265: iadd
      5266: bipush        18
      5268: iadd
      5269: invokevirtual #51                 // Method java/awt/Graphics.drawString:(Ljava/lang/String;II)V
      5272: iinc          2, 1
      5275: iload_2
      5276: aload_0
      5277: getfield      #7                  // Field item_kazu:[I
      5280: iload_1
      5281: iaload
      5282: iconst_1
      5283: isub
      5284: if_icmple     5225
      5287: iload_1
      5288: aload_0
      5289: getfield      #17                 // Field aw:I
      5292: if_icmpne     5351
      5295: aload_0
      5296: getfield      #33                 // Field c_fc:I
      5299: iconst_3
      5300: if_icmpgt     6094
      5303: aload_0
      5304: getfield      #21                 // Field gg:LGameGraphics;
      5307: aload_0
      5308: getfield      #3                  // Field x:[I
      5311: iload_1
      5312: iaload
      5313: bipush        6
      5315: iadd
      5316: aload_0
      5317: getfield      #4                  // Field y:[I
      5320: iload_1
      5321: iaload
      5322: bipush        6
      5324: iadd
      5325: bipush        18
      5327: iadd
      5328: aload_0
      5329: getfield      #6                  // Field selectedIndex:[I
      5332: iload_1
      5333: iaload
      5334: bipush        14
      5336: imul
      5337: iadd
      5338: bipush        18
      5340: iadd
      5341: sipush        200
      5344: iconst_0
      5345: invokevirtual #67                 // Method GameGraphics.drawPT:(IIII)V
      5348: goto          6094
      5351: aload_0
      5352: getfield      #21                 // Field gg:LGameGraphics;
      5355: aload_0
      5356: getfield      #3                  // Field x:[I
      5359: iload_1
      5360: iaload
      5361: bipush        6
      5363: iadd
      5364: aload_0
      5365: getfield      #4                  // Field y:[I
      5368: iload_1
      5369: iaload
      5370: bipush        6
      5372: iadd
      5373: bipush        18
      5375: iadd
      5376: aload_0
      5377: getfield      #6                  // Field selectedIndex:[I
      5380: iload_1
      5381: iaload
      5382: bipush        14
      5384: imul
      5385: iadd
      5386: bipush        18
      5388: iadd
      5389: sipush        200
      5392: iconst_0
      5393: invokevirtual #67                 // Method GameGraphics.drawPT:(IIII)V
      5396: goto          6094
      5399: aload_0
      5400: aload_0
      5401: getfield      #3                  // Field x:[I
      5404: iload_1
      5405: iaload
      5406: aload_0
      5407: getfield      #4                  // Field y:[I
      5410: iload_1
      5411: iaload
      5412: aload_0
      5413: getfield      #5                  // Field width:[I
      5416: iload_1
      5417: iaload
      5418: bipush        44
      5420: invokevirtual #48                 // Method drawWindowbox:(IIII)V
      5423: aload_0
      5424: getfield      #28                 // Field hg:Ljava/awt/Graphics;
      5427: getstatic     #70                 // Field java/awt/Color.yellow:Ljava/awt/Color;
      5430: invokevirtual #50                 // Method java/awt/Graphics.setColor:(Ljava/awt/Color;)V
      5433: aload_0
      5434: getfield      #28                 // Field hg:Ljava/awt/Graphics;
      5437: ldc           #85                 // String おこづかい
      5439: aload_0
      5440: getfield      #3                  // Field x:[I
      5443: iload_1
      5444: iaload
      5445: bipush        6
      5447: iadd
      5448: aload_0
      5449: getfield      #4                  // Field y:[I
      5452: iload_1
      5453: iaload
      5454: bipush        6
      5456: iadd
      5457: bipush        12
      5459: iadd
      5460: invokevirtual #51                 // Method java/awt/Graphics.drawString:(Ljava/lang/String;II)V
      5463: aload_0
      5464: getfield      #28                 // Field hg:Ljava/awt/Graphics;
      5467: getstatic     #49                 // Field java/awt/Color.white:Ljava/awt/Color;
      5470: invokevirtual #50                 // Method java/awt/Graphics.setColor:(Ljava/awt/Color;)V
      5473: aload_0
      5474: getfield      #28                 // Field hg:Ljava/awt/Graphics;
      5477: new           #58                 // class java/lang/StringBuffer
      5480: dup
      5481: invokespecial #59                 // Method java/lang/StringBuffer."<init>":()V
      5484: ldc           #39                 // String
      5486: invokevirtual #61                 // Method java/lang/StringBuffer.append:(Ljava/lang/String;)Ljava/lang/StringBuffer;
      5489: aload_0
      5490: getfield      #13                 // Field item_int:[[I
      5493: iload_1
      5494: aaload
      5495: iconst_0
      5496: iaload
      5497: invokevirtual #62                 // Method java/lang/StringBuffer.append:(I)Ljava/lang/StringBuffer;
      5500: ldc           #73                 // String 円
      5502: invokevirtual #61                 // Method java/lang/StringBuffer.append:(Ljava/lang/String;)Ljava/lang/StringBuffer;
      5505: invokevirtual #64                 // Method java/lang/StringBuffer.toString:()Ljava/lang/String;
      5508: aload_0
      5509: getfield      #3                  // Field x:[I
      5512: iload_1
      5513: iaload
      5514: bipush        6
      5516: iadd
      5517: aload_0
      5518: getfield      #4                  // Field y:[I
      5521: iload_1
      5522: iaload
      5523: bipush        6
      5525: iadd
      5526: bipush        18
      5528: iadd
      5529: bipush        12
      5531: iadd
      5532: invokevirtual #51                 // Method java/awt/Graphics.drawString:(Ljava/lang/String;II)V
      5535: goto          6094
      5538: aload_0
      5539: aload_0
      5540: getfield      #3                  // Field x:[I
      5543: iload_1
      5544: iaload
      5545: aload_0
      5546: getfield      #4                  // Field y:[I
      5549: iload_1
      5550: iaload
      5551: aload_0
      5552: getfield      #5                  // Field width:[I
      5555: iload_1
      5556: iaload
      5557: bipush        30
      5559: aload_0
      5560: getfield      #7                  // Field item_kazu:[I
      5563: iload_1
      5564: iaload
      5565: bipush        14
      5567: imul
      5568: iadd
      5569: invokevirtual #48                 // Method drawWindowbox:(IIII)V
      5572: aload_0
      5573: getfield      #28                 // Field hg:Ljava/awt/Graphics;
      5576: getstatic     #49                 // Field java/awt/Color.white:Ljava/awt/Color;
      5579: invokevirtual #50                 // Method java/awt/Graphics.setColor:(Ljava/awt/Color;)V
      5582: aload_0
      5583: getfield      #28                 // Field hg:Ljava/awt/Graphics;
      5586: aload_0
      5587: getfield      #9                  // Field message:[Ljava/lang/String;
      5590: iload_1
      5591: aaload
      5592: aload_0
      5593: getfield      #3                  // Field x:[I
      5596: iload_1
      5597: iaload
      5598: bipush        24
      5600: iadd
      5601: aload_0
      5602: getfield      #4                  // Field y:[I
      5605: iload_1
      5606: iaload
      5607: bipush        6
      5609: iadd
      5610: bipush        12
      5612: iadd
      5613: invokevirtual #51                 // Method java/awt/Graphics.drawString:(Ljava/lang/String;II)V
      5616: aload_0
      5617: getfield      #7                  // Field item_kazu:[I
      5620: iload_1
      5621: iaload
      5622: iconst_1
      5623: if_icmplt     5755
      5626: iconst_0
      5627: istore_2
      5628: goto          5743
      5631: aload_0
      5632: getfield      #28                 // Field hg:Ljava/awt/Graphics;
      5635: aload_0
      5636: getfield      #11                 // Field item:[[Ljava/lang/String;
      5639: iload_1
      5640: aaload
      5641: iload_2
      5642: aaload
      5643: aload_0
      5644: getfield      #3                  // Field x:[I
      5647: iload_1
      5648: iaload
      5649: bipush        24
      5651: iadd
      5652: aload_0
      5653: getfield      #4                  // Field y:[I
      5656: iload_1
      5657: iaload
      5658: bipush        6
      5660: iadd
      5661: bipush        18
      5663: iadd
      5664: iload_2
      5665: bipush        14
      5667: imul
      5668: iadd
      5669: bipush        12
      5671: iadd
      5672: invokevirtual #51                 // Method java/awt/Graphics.drawString:(Ljava/lang/String;II)V
      5675: aload_0
      5676: getfield      #28                 // Field hg:Ljava/awt/Graphics;
      5679: new           #58                 // class java/lang/StringBuffer
      5682: dup
      5683: invokespecial #59                 // Method java/lang/StringBuffer."<init>":()V
      5686: ldc           #39                 // String
      5688: invokevirtual #61                 // Method java/lang/StringBuffer.append:(Ljava/lang/String;)Ljava/lang/StringBuffer;
      5691: aload_0
      5692: getfield      #13                 // Field item_int:[[I
      5695: iload_1
      5696: aaload
      5697: iload_2
      5698: iaload
      5699: invokevirtual #62                 // Method java/lang/StringBuffer.append:(I)Ljava/lang/StringBuffer;
      5702: invokevirtual #64                 // Method java/lang/StringBuffer.toString:()Ljava/lang/String;
      5705: aload_0
      5706: getfield      #3                  // Field x:[I
      5709: iload_1
      5710: iaload
      5711: bipush        24
      5713: iadd
      5714: bipush        116
      5716: iadd
      5717: aload_0
      5718: getfield      #4                  // Field y:[I
      5721: iload_1
      5722: iaload
      5723: bipush        6
      5725: iadd
      5726: bipush        18
      5728: iadd
      5729: iload_2
      5730: bipush        14
      5732: imul
      5733: iadd
      5734: bipush        12
      5736: iadd
      5737: invokevirtual #51                 // Method java/awt/Graphics.drawString:(Ljava/lang/String;II)V
      5740: iinc          2, 1
      5743: iload_2
      5744: aload_0
      5745: getfield      #7                  // Field item_kazu:[I
      5748: iload_1
      5749: iaload
      5750: iconst_1
      5751: isub
      5752: if_icmple     5631
      5755: iload_1
      5756: aload_0
      5757: getfield      #17                 // Field aw:I
      5760: if_icmpne     5816
      5763: aload_0
      5764: getfield      #33                 // Field c_fc:I
      5767: iconst_3
      5768: if_icmpgt     6094
      5771: aload_0
      5772: getfield      #21                 // Field gg:LGameGraphics;
      5775: aload_0
      5776: getfield      #3                  // Field x:[I
      5779: iload_1
      5780: iaload
      5781: bipush        6
      5783: iadd
      5784: aload_0
      5785: getfield      #4                  // Field y:[I
      5788: iload_1
      5789: iaload
      5790: bipush        6
      5792: iadd
      5793: bipush        18
      5795: iadd
      5796: aload_0
      5797: getfield      #6                  // Field selectedIndex:[I
      5800: iload_1
      5801: iaload
      5802: bipush        14
      5804: imul
      5805: iadd
      5806: sipush        200
      5809: iconst_0
      5810: invokevirtual #67                 // Method GameGraphics.drawPT:(IIII)V
      5813: goto          6094
      5816: aload_0
      5817: getfield      #21                 // Field gg:LGameGraphics;
      5820: aload_0
      5821: getfield      #3                  // Field x:[I
      5824: iload_1
      5825: iaload
      5826: bipush        6
      5828: iadd
      5829: aload_0
      5830: getfield      #4                  // Field y:[I
      5833: iload_1
      5834: iaload
      5835: bipush        6
      5837: iadd
      5838: bipush        18
      5840: iadd
      5841: aload_0
      5842: getfield      #6                  // Field selectedIndex:[I
      5845: iload_1
      5846: iaload
      5847: bipush        14
      5849: imul
      5850: iadd
      5851: sipush        200
      5854: iconst_0
      5855: invokevirtual #67                 // Method GameGraphics.drawPT:(IIII)V
      5858: goto          6094
      5861: aload_0
      5862: aload_0
      5863: getfield      #3                  // Field x:[I
      5866: iload_1
      5867: iaload
      5868: aload_0
      5869: getfield      #4                  // Field y:[I
      5872: iload_1
      5873: iaload
      5874: aload_0
      5875: getfield      #5                  // Field width:[I
      5878: iload_1
      5879: iaload
      5880: bipush        98
      5882: invokevirtual #48                 // Method drawWindowbox:(IIII)V
      5885: aload_0
      5886: getfield      #28                 // Field hg:Ljava/awt/Graphics;
      5889: new           #14                 // class java/awt/Color
      5892: dup
      5893: bipush        96
      5895: bipush        96
      5897: bipush        96
      5899: invokespecial #76                 // Method java/awt/Color."<init>":(III)V
      5902: invokevirtual #50                 // Method java/awt/Graphics.setColor:(Ljava/awt/Color;)V
      5905: aload_0
      5906: getfield      #28                 // Field hg:Ljava/awt/Graphics;
      5909: aload_0
      5910: getfield      #3                  // Field x:[I
      5913: iload_1
      5914: iaload
      5915: bipush        12
      5917: iadd
      5918: aload_0
      5919: getfield      #4                  // Field y:[I
      5922: iload_1
      5923: iaload
      5924: bipush        12
      5926: iadd
      5927: sipush        248
      5930: bipush        48
      5932: invokevirtual #53                 // Method java/awt/Graphics.fillRect:(IIII)V
      5935: iconst_0
      5936: istore_2
      5937: goto          5999
      5940: aload_0
      5941: getfield      #13                 // Field item_int:[[I
      5944: iload_1
      5945: aaload
      5946: iload_2
      5947: iaload
      5948: ifle          5996
      5951: aload_0
      5952: getfield      #21                 // Field gg:LGameGraphics;
      5955: aload_0
      5956: getfield      #3                  // Field x:[I
      5959: iload_1
      5960: iaload
      5961: bipush        12
      5963: iadd
      5964: bipush        8
      5966: iadd
      5967: iload_2
      5968: bipush        40
      5970: imul
      5971: iadd
      5972: aload_0
      5973: getfield      #4                  // Field y:[I
      5976: iload_1
      5977: iaload
      5978: bipush        12
      5980: iadd
      5981: bipush        8
      5983: iadd
      5984: aload_0
      5985: getfield      #13                 // Field item_int:[[I
      5988: iload_1
      5989: aaload
      5990: iload_2
      5991: iaload
      5992: iconst_0
      5993: invokevirtual #67                 // Method GameGraphics.drawPT:(IIII)V
      5996: iinc          2, 1
      5999: iload_2
      6000: iconst_5
      6001: if_icmple     5940
      6004: aload_0
      6005: getfield      #28                 // Field hg:Ljava/awt/Graphics;
      6008: getstatic     #49                 // Field java/awt/Color.white:Ljava/awt/Color;
      6011: invokevirtual #50                 // Method java/awt/Graphics.setColor:(Ljava/awt/Color;)V
      6014: aload_0
      6015: getfield      #28                 // Field hg:Ljava/awt/Graphics;
      6018: ldc           #86                 // String みんな、元気になった。
      6020: aload_0
      6021: getfield      #3                  // Field x:[I
      6024: iload_1
      6025: iaload
      6026: bipush        12
      6028: iadd
      6029: aload_0
      6030: getfield      #4                  // Field y:[I
      6033: iload_1
      6034: iaload
      6035: bipush        64
      6037: iadd
      6038: bipush        12
      6040: iadd
      6041: invokevirtual #51                 // Method java/awt/Graphics.drawString:(Ljava/lang/String;II)V
      6044: aload_0
      6045: getfield      #33                 // Field c_fc:I
      6048: iconst_3
      6049: if_icmpgt     6094
      6052: aload_0
      6053: getfield      #21                 // Field gg:LGameGraphics;
      6056: aload_0
      6057: getfield      #3                  // Field x:[I
      6060: iload_1
      6061: iaload
      6062: aload_0
      6063: getfield      #5                  // Field width:[I
      6066: iload_1
      6067: iaload
      6068: bipush        14
      6070: isub
      6071: iconst_2
      6072: idiv
      6073: iadd
      6074: aload_0
      6075: getfield      #4                  // Field y:[I
      6078: iload_1
      6079: iaload
      6080: bipush        64
      6082: iadd
      6083: bipush        14
      6085: iadd
      6086: iconst_2
      6087: iadd
      6088: bipush        71
      6090: iconst_0
      6091: invokevirtual #67                 // Method GameGraphics.drawPT:(IIII)V
      6094: iinc          1, 1
      6097: iload_1
      6098: bipush        15
      6100: if_icmple     24
      6103: return
      LineNumberTable:
        line 14153: 0
        line 14155: 19
        line 14156: 24
        line 14157: 31
        line 14158: 38
        line 14169: 216
        line 14173: 250
        line 14174: 260
        line 14177: 294
        line 14178: 304
        line 14179: 309
        line 14178: 353
        line 14184: 368
        line 14186: 376
        line 14188: 384
        line 14194: 434
        line 14197: 481
        line 14200: 484
        line 14201: 494
        line 14202: 510
        line 14203: 520
        line 14207: 535
        line 14208: 545
        line 14209: 565
        line 14210: 589
        line 14211: 599
        line 14213: 612
        line 14214: 622
        line 14216: 677
        line 14218: 732
        line 14221: 735
        line 14222: 745
        line 14223: 762
        line 14224: 772
        line 14228: 788
        line 14229: 798
        line 14230: 819
        line 14231: 831
        line 14232: 841
        line 14234: 855
        line 14235: 865
        line 14237: 921
        line 14239: 977
        line 14242: 980
        line 14243: 990
        line 14244: 1007
        line 14245: 1017
        line 14249: 1033
        line 14250: 1043
        line 14251: 1064
        line 14252: 1088
        line 14253: 1098
        line 14255: 1112
        line 14256: 1122
        line 14258: 1178
        line 14260: 1234
        line 14263: 1237
        line 14267: 1261
        line 14268: 1271
        line 14271: 1307
        line 14273: 1315
        line 14279: 1363
        line 14283: 1387
        line 14284: 1400
        line 14287: 1436
        line 14288: 1446
        line 14291: 1485
        line 14292: 1493
        line 14298: 1541
        line 14302: 1580
        line 14303: 1590
        line 14306: 1626
        line 14307: 1636
        line 14310: 1675
        line 14311: 1685
        line 14314: 1724
        line 14315: 1734
        line 14316: 1739
        line 14315: 1785
        line 14321: 1800
        line 14323: 1808
        line 14330: 1868
        line 14334: 1892
        line 14335: 1902
        line 14338: 1938
        line 14339: 1948
        line 14342: 1987
        line 14343: 1997
        line 14346: 2036
        line 14347: 2046
        line 14350: 2085
        line 14351: 2095
        line 14354: 2137
        line 14355: 2145
        line 14361: 2199
        line 14365: 2235
        line 14366: 2248
        line 14369: 2282
        line 14370: 2292
        line 14371: 2302
        line 14372: 2307
        line 14371: 2351
        line 14377: 2366
        line 14379: 2374
        line 14380: 2382
        line 14385: 2438
        line 14387: 2491
        line 14389: 2494
        line 14391: 2507
        line 14395: 2520
        line 14399: 2544
        line 14400: 2554
        line 14403: 2590
        line 14404: 2602
        line 14405: 2613
        line 14411: 2621
        line 14415: 2635
        line 14419: 2659
        line 14420: 2672
        line 14423: 2708
        line 14424: 2718
        line 14426: 2760
        line 14428: 2773
        line 14432: 2786
        line 14436: 2810
        line 14437: 2823
        line 14440: 2859
        line 14441: 2869
        line 14444: 2908
        line 14445: 2920
        line 14446: 2931
        line 14454: 2939
        line 14458: 2964
        line 14460: 2974
        line 14461: 3024
        line 14462: 3034
        line 14463: 3111
        line 14464: 3147
        line 14465: 3216
        line 14466: 3252
        line 14469: 3321
        line 14470: 3329
        line 14476: 3377
        line 14477: 3401
        line 14478: 3421
        line 14479: 3457
        line 14482: 3509
        line 14483: 3519
        line 14484: 3555
        line 14485: 3565
        line 14488: 3598
        line 14489: 3606
        line 14494: 3651
        line 14498: 3664
        line 14499: 3688
        line 14500: 3708
        line 14501: 3744
        line 14504: 3796
        line 14505: 3806
        line 14506: 3842
        line 14507: 3852
        line 14510: 3885
        line 14511: 3893
        line 14514: 3938
        line 14518: 3949
        line 14519: 3973
        line 14520: 3993
        line 14521: 4029
        line 14524: 4081
        line 14525: 4091
        line 14526: 4127
        line 14527: 4137
        line 14530: 4170
        line 14531: 4178
        line 14538: 4223
        line 14539: 4248
        line 14540: 4268
        line 14541: 4304
        line 14544: 4356
        line 14545: 4366
        line 14546: 4402
        line 14547: 4412
        line 14548: 4445
        line 14549: 4502
        line 14550: 4535
        line 14553: 4592
        line 14554: 4600
        line 14561: 4645
        line 14563: 4660
        line 14568: 4697
        line 14571: 4731
        line 14574: 4734
        line 14576: 4758
        line 14577: 4767
        line 14578: 4787
        line 14579: 4798
        line 14580: 4811
        line 14581: 4829
        line 14582: 4848
        line 14584: 4870
        line 14588: 4873
        line 14592: 4907
        line 14593: 4917
        line 14596: 4947
        line 14597: 4957
        line 14598: 5016
        line 14600: 5076
        line 14603: 5079
        line 14607: 5116
        line 14608: 5126
        line 14612: 5163
        line 14613: 5173
        line 14616: 5210
        line 14617: 5220
        line 14618: 5225
        line 14617: 5272
        line 14623: 5287
        line 14625: 5295
        line 14626: 5303
        line 14631: 5351
        line 14634: 5396
        line 14637: 5399
        line 14641: 5423
        line 14642: 5433
        line 14645: 5463
        line 14646: 5473
        line 14648: 5535
        line 14651: 5538
        line 14655: 5572
        line 14656: 5582
        line 14659: 5616
        line 14660: 5626
        line 14661: 5631
        line 14663: 5675
        line 14660: 5740
        line 14668: 5755
        line 14670: 5763
        line 14671: 5771
        line 14676: 5816
        line 14679: 5858
        line 14682: 5861
        line 14683: 5885
        line 14684: 5905
        line 14687: 5935
        line 14688: 5940
        line 14689: 5951
        line 14687: 5996
        line 14694: 6004
        line 14695: 6014
        line 14698: 6044
        line 14699: 6052
        line 14155: 6094
        line 14705: 6103

  void drawWindowbox(int, int, int, int);
    descriptor: (IIII)V
    flags: (0x0000)
    Code:
      stack=6, locals=5, args_size=5
         0: aload_0
         1: getfield      #28                 // Field hg:Ljava/awt/Graphics;
         4: getstatic     #49                 // Field java/awt/Color.white:Ljava/awt/Color;
         7: invokevirtual #50                 // Method java/awt/Graphics.setColor:(Ljava/awt/Color;)V
        10: aload_0
        11: getfield      #28                 // Field hg:Ljava/awt/Graphics;
        14: iload_1
        15: iload_2
        16: iload_3
        17: iload         4
        19: invokevirtual #53                 // Method java/awt/Graphics.fillRect:(IIII)V
        22: aload_0
        23: getfield      #28                 // Field hg:Ljava/awt/Graphics;
        26: getstatic     #54                 // Field java/awt/Color.black:Ljava/awt/Color;
        29: invokevirtual #50                 // Method java/awt/Graphics.setColor:(Ljava/awt/Color;)V
        32: aload_0
        33: getfield      #28                 // Field hg:Ljava/awt/Graphics;
        36: iload_1
        37: iconst_2
        38: iadd
        39: iload_2
        40: iconst_2
        41: iadd
        42: iload_3
        43: iconst_4
        44: isub
        45: iload         4
        47: iconst_4
        48: isub
        49: invokevirtual #53                 // Method java/awt/Graphics.fillRect:(IIII)V
        52: return
      LineNumberTable:
        line 14725: 0
        line 14726: 10
        line 14727: 22
        line 14728: 32
        line 14729: 52
}
SourceFile: "MasaoConstruction.java"
